Workbook
Name Master: #REF!
Name Sub_head: #REF!
Name NamedRange1: #REF!

Sheet YES Master 0264
B1: XX0264 | D1: Cust ID | E1: 33167514 | H1: 46258 | I1: =SUBTOTAL(9,I9:I236) -> 0 | J1: =SUBTOTAL(9,J9:J236) -> 10724949 | K1: =J1-I1 -> 10724949
A2: SL# | B2: QTR | C2: MONTH | D2: TXN DATE | E2: VALUE DATE | F2: TYPE | G2: DESCRIPTION | H2: REFERENCE | I2: DEBITS | J2: CREDITS | K2: BALANCE | L2: BUSINESS UNIT | M2: HEAD | N2: SUB HEAD | O2: RECO | P2: TYPE FOR RERA IDW | Q2: TCP Head | R2: CONCERN | S2: CUST ID | T2: APT# | U2: ACC REMARKS | V2: CRM REMARKS | W2: NARRATION | X2: Tax Rate | Y2: Bal as per AI | Z2: Check | AA2: Auth MB | AB2: Auth MK | AC2: Auth NM
A5: =ROW()-1 -> 4 | B5: =IFERROR("Q"&(INT(MOD(C5-4,12)/3)+1),"") -> Q2 | C5: =IFERROR(MONTH(DATEVALUE(D5)),"") -> 8 | D5: 17-Aug-2026 | E5: 17-Aug-2026 | G5: YIB-TPT-DWARKADHIS PROJECTS PVT LT D-TRANSFERFROM0264TO0477ONACCONTOFC USTOMER-045563400002477 | I5: 49426 | K5: =IFERROR(K6+J5-I5,"") -> 29079.78 | L5: Casa Romana | M5: Internal | O5: Reco | P5: Master to Free | Q5: Internal transfer | W5: =TRIM(IF(M5="Internal", IF(ISBLANK(G5), IF(LEN(G5)-LEN(SUBSTITUTE(G5,"-",""))>=3, "Fund Transfer: From x" & RIGHT(MID(G5, FIND("|", SUBSTITUTE(G5, "-", "|", 3)) + 1, LEN(G5)), 4) & " to YES MASTER 0264 (Ref: " & H5 & ") (Type: " & P5 & ") (BU: " & L5 & ") (Head: " & M5 & ")", "Fund Transfer: To YES MASTER 0264 (Ref: " & H5 & ") (Type: " & P5 & ") (BU: " & L5 & ") (Head: " & M5 & ")"), IF(LEN(G5)-LEN(SUBSTITUTE(G5,"-",""))>=3, "Fund Transfer: From YES MASTER 0264 to x" & RIGHT(MID(G5, FIND("|", SUBSTITUTE(G5, "-", "|", 3)) + 1, LEN(G5)), 4) & " (Ref: " & H5 & ") (Type: " & P5 & ") (BU: " & L5 & ") (Head: " & M5 & ")", "Fund Transfer: From YES MASTER 0264 (Ref: " & H5 & ") (Type: " & P5 & ") (BU: " & L5 & ") (Head: " & M5 & ")")), IF(NOT(ISBLANK(J5)), IF(P5="Customer Collection", "Receipt: For " & IF(ISBLANK(T5), "", "(Apt#: " & T5 & ") ") & "(Ref: " & H5 & ") (" & IF(ISNUMBER(SEARCH("NEFT",G5)), "NEFT:", IF(ISNUMBER(SEARCH("RTGS",G5)), "RTGS:", IF(ISNUMBER(SEARCH("IMPS",G5)), "IMPS:", ""))) & " " & IF(ISNUMBER(SEARCH("SOHNA ROAD", G5)), "", IFERROR(MID(G5, FIND("-", G5, FIND("-", G5) + 1) + 1, LEN(G5)), SUBSTITUTE(SUBSTITUTE(SUBSTITUTE(G5, "IMPS/", ""), "NEFT/", ""), "RTGS/", ""))) & ") (Type: " & P5 & ") (BU: " & L5 & ")", IF(LEN(G5)-LEN(SUBSTITUTE(G5,"-",""))>=3, "Receipt: From x" & RIGHT(MID(G5, FIND("|", SUBSTITUTE(G5, "-", "|", 3)) + 1, LEN(G5)), 4) & " towards " & IF(ISBLANK(U5), L5, U5) & IF(OR(L5="Cancellation", L5="Collection"), " Apt No " & T5, "") & " (Ref: " & H5 & ") (Type: " & P5 & ") (BU: " & L5 & ") (Head: " & M5 & ")" & IF(ISBLANK(T5), "", " (Apt#: " & T5 & ")"), "Receipt: Against " & IF(ISBLANK(U5), L5, U5) & IF(OR(L5="Cancellation", L5="Collection"), " Apt No " & T5, "") & " (Ref: " & H5 & ") (Type: " & P5 & ") (BU: " & L5 & ") (Head: " & M5 & ")" & IF(ISBLANK(T5), "", " (Apt#: " & T5 & ")"))), IF(LEN(G5)-LEN(SUBSTITUTE(G5,"-",""))>=3, "Payment: To x" & RIGHT(MID(G5, FIND("|", SUBSTITUTE(G5, "-", "|", 3)) + 1, LEN(G5)), 4) & " for " & IF(ISBLANK(U5), L5, U5) & " (Ref: " & H5 & ") (Type: " & P5 & ") (BU: " & L5 & ") (Head: " & M5 & ")" & IF(ISBLANK(T5), "", " (Apt#: " & T5 & ")"), "Payment: Disbursement for " & IF(ISBLANK(U5), "", IF(ISBLANK(U5), "", U5) & " ") & "(Ref: " & H5 & ") (Type: " & P5 & ") (BU: " & L5 & ") (Head: " & M5 & ")" & IF(ISBLANK(T5), "", " (Apt#: " & T5 & ")"))))) -> Fund Transfer: From YES MASTER 0264 to x2477 (Ref: ) (Type: Master to Free) (BU: Casa Romana) (Head: Internal) | Y5: 29079.78 | Z5: =IFERROR(ROUND(Y5-K5,2),"") -> 0
A6: =ROW()-1 -> 5 | B6: =IFERROR("Q"&(INT(MOD(C6-4,12)/3)+1),"") -> Q2 | C6: =IFERROR(MONTH(DATEVALUE(D6)),"") -> 8 | D6: 17-Aug-2026 | E6: 17-Aug-2026 | G6: YIB-TPT-DWARKADHIS PROJECTS PRIVATE LIMITED-TRANSFERFROM026 4TO0377ONACCONTOFCUSTOMER-04556320 0000377 | I6: 115326 | K6: =IFERROR(K7+J6-I6,"") -> 78505.78 | L6: Casa Romana | M6: Internal | O6: Entry | P6: Master 2 RERA | Q6: Internal transfer | W6: =TRIM(IF(M6="Internal", IF(ISBLANK(G6), IF(LEN(G6)-LEN(SUBSTITUTE(G6,"-",""))>=3, "Fund Transfer: From x" & RIGHT(MID(G6, FIND("|", SUBSTITUTE(G6, "-", "|", 3)) + 1, LEN(G6)), 4) & " to YES MASTER 0264 (Ref: " & H6 & ") (Type: " & P6 & ") (BU: " & L6 & ") (Head: " & M6 & ")", "Fund Transfer: To YES MASTER 0264 (Ref: " & H6 & ") (Type: " & P6 & ") (BU: " & L6 & ") (Head: " & M6 & ")"), IF(LEN(G6)-LEN(SUBSTITUTE(G6,"-",""))>=3, "Fund Transfer: From YES MASTER 0264 to x" & RIGHT(MID(G6, FIND("|", SUBSTITUTE(G6, "-", "|", 3)) + 1, LEN(G6)), 4) & " (Ref: " & H6 & ") (Type: " & P6 & ") (BU: " & L6 & ") (Head: " & M6 & ")", "Fund Transfer: From YES MASTER 0264 (Ref: " & H6 & ") (Type: " & P6 & ") (BU: " & L6 & ") (Head: " & M6 & ")")), IF(NOT(ISBLANK(J6)), IF(P6="Customer Collection", "Receipt: For " & IF(ISBLANK(T6), "", "(Apt#: " & T6 & ") ") & "(Ref: " & H6 & ") (" & IF(ISNUMBER(SEARCH("NEFT",G6)), "NEFT:", IF(ISNUMBER(SEARCH("RTGS",G6)), "RTGS:", IF(ISNUMBER(SEARCH("IMPS",G6)), "IMPS:", ""))) & " " & IF(ISNUMBER(SEARCH("SOHNA ROAD", G6)), "", IFERROR(MID(G6, FIND("-", G6, FIND("-", G6) + 1) + 1, LEN(G6)), SUBSTITUTE(SUBSTITUTE(SUBSTITUTE(G6, "IMPS/", ""), "NEFT/", ""), "RTGS/", ""))) & ") (Type: " & P6 & ") (BU: " & L6 & ")", IF(LEN(G6)-LEN(SUBSTITUTE(G6,"-",""))>=3, "Receipt: From x" & RIGHT(MID(G6, FIND("|", SUBSTITUTE(G6, "-", "|", 3)) + 1, LEN(G6)), 4) & " towards " & IF(ISBLANK(U6), L6, U6) & IF(OR(L6="Cancellation", L6="Collection"), " Apt No " & T6, "") & " (Ref: " & H6 & ") (Type: " & P6 & ") (BU: " & L6 & ") (Head: " & M6 & ")" & IF(ISBLANK(T6), "", " (Apt#: " & T6 & ")"), "Receipt: Against " & IF(ISBLANK(U6), L6, U6) & IF(OR(L6="Cancellation", L6="Collection"), " Apt No " & T6, "") & " (Ref: " & H6 & ") (Type: " & P6 & ") (BU: " & L6 & ") (Head: " & M6 & ")" & IF(ISBLANK(T6), "", " (Apt#: " & T6 & ")"))), IF(LEN(G6)-LEN(SUBSTITUTE(G6,"-",""))>=3, "Payment: To x" & RIGHT(MID(G6, FIND("|", SUBSTITUTE(G6, "-", "|", 3)) + 1, LEN(G6)), 4) & " for " & IF(ISBLANK(U6), L6, U6) & " (Ref: " & H6 & ") (Type: " & P6 & ") (BU: " & L6 & ") (Head: " & M6 & ")" & IF(ISBLANK(T6), "", " (Apt#: " & T6 & ")"), "Payment: Disbursement for " & IF(ISBLANK(U6), "", IF(ISBLANK(U6), "", U6) & " ") & "(Ref: " & H6 & ") (Type: " & P6 & ") (BU: " & L6 & ") (Head: " & M6 & ")" & IF(ISBLANK(T6), "", " (Apt#: " & T6 & ")"))))) -> Fund Transfer: From YES MASTER 0264 to x0377 (Ref: ) (Type: Master 2 RERA) (BU: Casa Romana) (Head: Internal) | Y6: 78505.78 | Z6: =IFERROR(ROUND(Y6-K6,2),"") -> 0
A7: =ROW()-1 -> 6 | B7: =IFERROR("Q"&(INT(MOD(C7-4,12)/3)+1),"") -> Q2 | C7: =IFERROR(MONTH(DATEVALUE(D7)),"") -> 8 | D7: 17-Aug-2026 | E7: 17-Aug-2026 | G7: IMPS/SUNITA SUNITA/XXX8258/ RRN:622911882764/STATE BANK OF INDIA | J7: 64752 | K7: =Y7 -> 193831.78 | L7: Casa Romana | M7: Collection | O7: Entry | P7: Customer Collection | Q7: Credit- no effect | T7: P-064 | V7: Adjust | W7: =TRIM(IF(M7="Internal", IF(ISBLANK(G7), IF(LEN(G7)-LEN(SUBSTITUTE(G7,"-",""))>=3, "Fund Transfer: From x" & RIGHT(MID(G7, FIND("|", SUBSTITUTE(G7, "-", "|", 3)) + 1, LEN(G7)), 4) & " to YES MASTER 0264 (Ref: " & H7 & ") (Type: " & P7 & ") (BU: " & L7 & ") (Head: " & M7 & ")", "Fund Transfer: To YES MASTER 0264 (Ref: " & H7 & ") (Type: " & P7 & ") (BU: " & L7 & ") (Head: " & M7 & ")"), IF(LEN(G7)-LEN(SUBSTITUTE(G7,"-",""))>=3, "Fund Transfer: From YES MASTER 0264 to x" & RIGHT(MID(G7, FIND("|", SUBSTITUTE(G7, "-", "|", 3)) + 1, LEN(G7)), 4) & " (Ref: " & H7 & ") (Type: " & P7 & ") (BU: " & L7 & ") (Head: " & M7 & ")", "Fund Transfer: From YES MASTER 0264 (Ref: " & H7 & ") (Type: " & P7 & ") (BU: " & L7 & ") (Head: " & M7 & ")")), IF(NOT(ISBLANK(J7)), IF(P7="Customer Collection", "Receipt: For " & IF(ISBLANK(T7), "", "(Apt#: " & T7 & ") ") & "(Ref: " & H7 & ") (" & IF(ISNUMBER(SEARCH("NEFT",G7)), "NEFT:", IF(ISNUMBER(SEARCH("RTGS",G7)), "RTGS:", IF(ISNUMBER(SEARCH("IMPS",G7)), "IMPS:", ""))) & " " & IF(ISNUMBER(SEARCH("SOHNA ROAD", G7)), "", IFERROR(MID(G7, FIND("-", G7, FIND("-", G7) + 1) + 1, LEN(G7)), SUBSTITUTE(SUBSTITUTE(SUBSTITUTE(G7, "IMPS/", ""), "NEFT/", ""), "RTGS/", ""))) & ") (Type: " & P7 & ") (BU: " & L7 & ")", IF(LEN(G7)-LEN(SUBSTITUTE(G7,"-",""))>=3, "Receipt: From x" & RIGHT(MID(G7, FIND("|", SUBSTITUTE(G7, "-", "|", 3)) + 1, LEN(G7)), 4) & " towards " & IF(ISBLANK(U7), L7, U7) & IF(OR(L7="Cancellation", L7="Collection"), " Apt No " & T7, "") & " (Ref: " & H7 & ") (Type: " & P7 & ") (BU: " & L7 & ") (Head: " & M7 & ")" & IF(ISBLANK(T7), "", " (Apt#: " & T7 & ")"), "Receipt: Against " & IF(ISBLANK(U7), L7, U7) & IF(OR(L7="Cancellation", L7="Collection"), " Apt No " & T7, "") & " (Ref: " & H7 & ") (Type: " & P7 & ") (BU: " & L7 & ") (Head: " & M7 & ")" & IF(ISBLANK(T7), "", " (Apt#: " & T7 & ")"))), IF(LEN(G7)-LEN(SUBSTITUTE(G7,"-",""))>=3, "Payment: To x" & RIGHT(MID(G7, FIND("|", SUBSTITUTE(G7, "-", "|", 3)) + 1, LEN(G7)), 4) & " for " & IF(ISBLANK(U7), L7, U7) & " (Ref: " & H7 & ") (Type: " & P7 & ") (BU: " & L7 & ") (Head: " & M7 & ")" & IF(ISBLANK(T7), "", " (Apt#: " & T7 & ")"), "Payment: Disbursement for " & IF(ISBLANK(U7), "", IF(ISBLANK(U7), "", U7) & " ") & "(Ref: " & H7 & ") (Type: " & P7 & ") (BU: " & L7 & ") (Head: " & M7 & ")" & IF(ISBLANK(T7), "", " (Apt#: " & T7 & ")"))))) -> Receipt: For (Apt#: P-064) (Ref: ) (IMPS: SUNITA SUNITA/XXX8258/ RRN:622911882764/STATE BANK OF INDIA) (Type: Customer Collection) (BU: Casa Romana) | Y7: 193831.78 | Z7: =IFERROR(ROUND(Y7-K7,2),"") -> 0
A8: 229 | B8: =IFERROR("Q"&(INT(MOD(C8-4,12)/3)+1),"") -> Q2 | C8: =IFERROR(MONTH(DATEVALUE(D8)),"") -> 8 | D8: 46250 | E8: 46250 | G8: IMPS/MRIGANKACHAKRABORTY/XXX7113/RRN:622810783912/AXIS BANK | H8: YBP6228654732943 | J8: 100000 | K8: =K9+J8-I8 -> 129078 | L8: Casa Romana | M8: Collection | O8: Entry | P8: Customer Collection | Q8: Credit- no effect | T8: P-071 | V8: Adjust | W8: =TRIM(IF(M8="Internal", IF(ISBLANK(G8), IF(LEN(G8)-LEN(SUBSTITUTE(G8,"-",""))>=3, "Fund Transfer: From x" & RIGHT(MID(G8, FIND("|", SUBSTITUTE(G8, "-", "|", 3)) + 1, LEN(G8)), 4) & " to YES MASTER 0264 (Ref: " & H8 & ") (Type: " & P8 & ") (BU: " & L8 & ") (Head: " & M8 & ")", "Fund Transfer: To YES MASTER 0264 (Ref: " & H8 & ") (Type: " & P8 & ") (BU: " & L8 & ") (Head: " & M8 & ")"), IF(LEN(G8)-LEN(SUBSTITUTE(G8,"-",""))>=3, "Fund Transfer: From YES MASTER 0264 to x" & RIGHT(MID(G8, FIND("|", SUBSTITUTE(G8, "-", "|", 3)) + 1, LEN(G8)), 4) & " (Ref: " & H8 & ") (Type: " & P8 & ") (BU: " & L8 & ") (Head: " & M8 & ")", "Fund Transfer: From YES MASTER 0264 (Ref: " & H8 & ") (Type: " & P8 & ") (BU: " & L8 & ") (Head: " & M8 & ")")), IF(NOT(ISBLANK(J8)), IF(P8="Customer Collection", "Receipt: For " & IF(ISBLANK(T8), "", "(Apt#: " & T8 & ") ") & "(Ref: " & H8 & ") (" & IF(ISNUMBER(SEARCH("NEFT",G8)), "NEFT:", IF(ISNUMBER(SEARCH("RTGS",G8)), "RTGS:", IF(ISNUMBER(SEARCH("IMPS",G8)), "IMPS:", ""))) & " " & IF(ISNUMBER(SEARCH("SOHNA ROAD", G8)), "", IFERROR(MID(G8, FIND("-", G8, FIND("-", G8) + 1) + 1, LEN(G8)), SUBSTITUTE(SUBSTITUTE(SUBSTITUTE(G8, "IMPS/", ""), "NEFT/", ""), "RTGS/", ""))) & ") (Type: " & P8 & ") (BU: " & L8 & ")", IF(LEN(G8)-LEN(SUBSTITUTE(G8,"-",""))>=3, "Receipt: From x" & RIGHT(MID(G8, FIND("|", SUBSTITUTE(G8, "-", "|", 3)) + 1, LEN(G8)), 4) & " towards " & IF(ISBLANK(U8), L8, U8) & IF(OR(L8="Cancellation", L8="Collection"), " Apt No " & T8, "") & " (Ref: " & H8 & ") (Type: " & P8 & ") (BU: " & L8 & ") (Head: " & M8 & ")" & IF(ISBLANK(T8), "", " (Apt#: " & T8 & ")"), "Receipt: Against " & IF(ISBLANK(U8), L8, U8) & IF(OR(L8="Cancellation", L8="Collection"), " Apt No " & T8, "") & " (Ref: " & H8 & ") (Type: " & P8 & ") (BU: " & L8 & ") (Head: " & M8 & ")" & IF(ISBLANK(T8), "", " (Apt#: " & T8 & ")"))), IF(LEN(G8)-LEN(SUBSTITUTE(G8,"-",""))>=3, "Payment: To x" & RIGHT(MID(G8, FIND("|", SUBSTITUTE(G8, "-", "|", 3)) + 1, LEN(G8)), 4) & " for " & IF(ISBLANK(U8), L8, U8) & " (Ref: " & H8 & ") (Type: " & P8 & ") (BU: " & L8 & ") (Head: " & M8 & ")" & IF(ISBLANK(T8), "", " (Apt#: " & T8 & ")"), "Payment: Disbursement for " & IF(ISBLANK(U8), "", IF(ISBLANK(U8), "", U8) & " ") & "(Ref: " & H8 & ") (Type: " & P8 & ") (BU: " & L8 & ") (Head: " & M8 & ")" & IF(ISBLANK(T8), "", " (Apt#: " & T8 & ")"))))) -> Receipt: For (Apt#: P-071) (Ref: YBP6228654732943) (IMPS: MRIGANKACHAKRABORTY/XXX7113/RRN:622810783912/AXIS BANK) (Type: Customer Collection) (BU: Casa Romana) | Y8: 129079.78 | Z8: =IFERROR(ROUND(Y8-K8,2),"") -> 1.78
A9: 228 | B9: =IFERROR("Q"&(INT(MOD(C9-4,12)/3)+1),"") -> Q2 | C9: =IFERROR(MONTH(DATEVALUE(D9)),"") -> 8 | D9: 12-Aug-2026 | E9: 12-Aug-2026 | G9: YIB-TPT-DWARKADHIS PROJECTS PVT LT D-INTERNAL-045563400002477 | I9: 45000 | K9: =K10+J9-I9 -> 29078 | L9: Casa Romana | M9: Internal | O9: Entry | P9: Master to Free | Q9: Internal transfer | W9: =TRIM(IF(M9="Internal", IF(ISBLANK(G9), IF(LEN(G9)-LEN(SUBSTITUTE(G9,"-",""))>=3, "Fund Transfer: From x" & RIGHT(MID(G9, FIND("|", SUBSTITUTE(G9, "-", "|", 3)) + 1, LEN(G9)), 4) & " to YES MASTER 0264 (Ref: " & H9 & ") (Type: " & P9 & ") (BU: " & L9 & ") (Head: " & M9 & ")", "Fund Transfer: To YES MASTER 0264 (Ref: " & H9 & ") (Type: " & P9 & ") (BU: " & L9 & ") (Head: " & M9 & ")"), IF(LEN(G9)-LEN(SUBSTITUTE(G9,"-",""))>=3, "Fund Transfer: From YES MASTER 0264 to x" & RIGHT(MID(G9, FIND("|", SUBSTITUTE(G9, "-", "|", 3)) + 1, LEN(G9)), 4) & " (Ref: " & H9 & ") (Type: " & P9 & ") (BU: " & L9 & ") (Head: " & M9 & ")", "Fund Transfer: From YES MASTER 0264 (Ref: " & H9 & ") (Type: " & P9 & ") (BU: " & L9 & ") (Head: " & M9 & ")")), IF(NOT(ISBLANK(J9)), IF(P9="Customer Collection", "Receipt: For " & IF(ISBLANK(T9), "", "(Apt#: " & T9 & ") ") & "(Ref: " & H9 & ") (" & IF(ISNUMBER(SEARCH("NEFT",G9)), "NEFT:", IF(ISNUMBER(SEARCH("RTGS",G9)), "RTGS:", IF(ISNUMBER(SEARCH("IMPS",G9)), "IMPS:", ""))) & " " & IF(ISNUMBER(SEARCH("SOHNA ROAD", G9)), "", IFERROR(MID(G9, FIND("-", G9, FIND("-", G9) + 1) + 1, LEN(G9)), SUBSTITUTE(SUBSTITUTE(SUBSTITUTE(G9, "IMPS/", ""), "NEFT/", ""), "RTGS/", ""))) & ") (Type: " & P9 & ") (BU: " & L9 & ")", IF(LEN(G9)-LEN(SUBSTITUTE(G9,"-",""))>=3, "Receipt: From x" & RIGHT(MID(G9, FIND("|", SUBSTITUTE(G9, "-", "|", 3)) + 1, LEN(G9)), 4) & " towards " & IF(ISBLANK(U9), L9, U9) & IF(OR(L9="Cancellation", L9="Collection"), " Apt No " & T9, "") & " (Ref: " & H9 & ") (Type: " & P9 & ") (BU: " & L9 & ") (Head: " & M9 & ")" & IF(ISBLANK(T9), "", " (Apt#: " & T9 & ")"), "Receipt: Against " & IF(ISBLANK(U9), L9, U9) & IF(OR(L9="Cancellation", L9="Collection"), " Apt No " & T9, "") & " (Ref: " & H9 & ") (Type: " & P9 & ") (BU: " & L9 & ") (Head: " & M9 & ")" & IF(ISBLANK(T9), "", " (Apt#: " & T9 & ")"))), IF(LEN(G9)-LEN(SUBSTITUTE(G9,"-",""))>=3, "Payment: To x" & RIGHT(MID(G9, FIND("|", SUBSTITUTE(G9, "-", "|", 3)) + 1, LEN(G9)), 4) & " for " & IF(ISBLANK(U9), L9, U9) & " (Ref: " & H9 & ") (Type: " & P9 & ") (BU: " & L9 & ") (Head: " & M9 & ")" & IF(ISBLANK(T9), "", " (Apt#: " & T9 & ")"), "Payment: Disbursement for " & IF(ISBLANK(U9), "", IF(ISBLANK(U9), "", U9) & " ") & "(Ref: " & H9 & ") (Type: " & P9 & ") (BU: " & L9 & ") (Head: " & M9 & ")" & IF(ISBLANK(T9), "", " (Apt#: " & T9 & ")"))))) -> Fund Transfer: From YES MASTER 0264 to x2477 (Ref: ) (Type: Master to Free) (BU: Casa Romana) (Head: Internal) | Y9: 29079.78 | Z9: =IFERROR(ROUND(Y9-K9,2),"") -> 1.78
A10: 227 | B10: =IFERROR("Q"&(INT(MOD(C10-4,12)/3)+1),"") -> Q2 | C10: =IFERROR(MONTH(DATEVALUE(D10)),"") -> 8 | D10: 12-Aug-2026 | E10: 12-Aug-2026 | G10: YIB-TPT-DWARKADHIS PROJECTS PRIVATE LIMITED-INTERNAL-0455632 00000377 | I10: 105000 | K10: =K11+J10-I10 -> 74078 | L10: Casa Romana | M10: Internal | O10: Entry | P10: Master 2 RERA | Q10: Internal transfer | W10: =TRIM(IF(M10="Internal", IF(ISBLANK(G10), IF(LEN(G10)-LEN(SUBSTITUTE(G10,"-",""))>=3, "Fund Transfer: From x" & RIGHT(MID(G10, FIND("|", SUBSTITUTE(G10, "-", "|", 3)) + 1, LEN(G10)), 4) & " to YES MASTER 0264 (Ref: " & H10 & ") (Type: " & P10 & ") (BU: " & L10 & ") (Head: " & M10 & ")", "Fund Transfer: To YES MASTER 0264 (Ref: " & H10 & ") (Type: " & P10 & ") (BU: " & L10 & ") (Head: " & M10 & ")"), IF(LEN(G10)-LEN(SUBSTITUTE(G10,"-",""))>=3, "Fund Transfer: From YES MASTER 0264 to x" & RIGHT(MID(G10, FIND("|", SUBSTITUTE(G10, "-", "|", 3)) + 1, LEN(G10)), 4) & " (Ref: " & H10 & ") (Type: " & P10 & ") (BU: " & L10 & ") (Head: " & M10 & ")", "Fund Transfer: From YES MASTER 0264 (Ref: " & H10 & ") (Type: " & P10 & ") (BU: " & L10 & ") (Head: " & M10 & ")")), IF(NOT(ISBLANK(J10)), IF(P10="Customer Collection", "Receipt: For " & IF(ISBLANK(T10), "", "(Apt#: " & T10 & ") ") & "(Ref: " & H10 & ") (" & IF(ISNUMBER(SEARCH("NEFT",G10)), "NEFT:", IF(ISNUMBER(SEARCH("RTGS",G10)), "RTGS:", IF(ISNUMBER(SEARCH("IMPS",G10)), "IMPS:", ""))) & " " & IF(ISNUMBER(SEARCH("SOHNA ROAD", G10)), "", IFERROR(MID(G10, FIND("-", G10, FIND("-", G10) + 1) + 1, LEN(G10)), SUBSTITUTE(SUBSTITUTE(SUBSTITUTE(G10, "IMPS/", ""), "NEFT/", ""), "RTGS/", ""))) & ") (Type: " & P10 & ") (BU: " & L10 & ")", IF(LEN(G10)-LEN(SUBSTITUTE(G10,"-",""))>=3, "Receipt: From x" & RIGHT(MID(G10, FIND("|", SUBSTITUTE(G10, "-", "|", 3)) + 1, LEN(G10)), 4) & " towards " & IF(ISBLANK(U10), L10, U10) & IF(OR(L10="Cancellation", L10="Collection"), " Apt No " & T10, "") & " (Ref: " & H10 & ") (Type: " & P10 & ") (BU: " & L10 & ") (Head: " & M10 & ")" & IF(ISBLANK(T10), "", " (Apt#: " & T10 & ")"), "Receipt: Against " & IF(ISBLANK(U10), L10, U10) & IF(OR(L10="Cancellation", L10="Collection"), " Apt No " & T10, "") & " (Ref: " & H10 & ") (Type: " & P10 & ") (BU: " & L10 & ") (Head: " & M10 & ")" & IF(ISBLANK(T10), "", " (Apt#: " & T10 & ")"))), IF(LEN(G10)-LEN(SUBSTITUTE(G10,"-",""))>=3, "Payment: To x" & RIGHT(MID(G10, FIND("|", SUBSTITUTE(G10, "-", "|", 3)) + 1, LEN(G10)), 4) & " for " & IF(ISBLANK(U10), L10, U10) & " (Ref: " & H10 & ") (Type: " & P10 & ") (BU: " & L10 & ") (Head: " & M10 & ")" & IF(ISBLANK(T10), "", " (Apt#: " & T10 & ")"), "Payment: Disbursement for " & IF(ISBLANK(U10), "", IF(ISBLANK(U10), "", U10) & " ") & "(Ref: " & H10 & ") (Type: " & P10 & ") (BU: " & L10 & ") (Head: " & M10 & ")" & IF(ISBLANK(T10), "", " (Apt#: " & T10 & ")"))))) -> Fund Transfer: From YES MASTER 0264 to x0377 (Ref: ) (Type: Master 2 RERA) (BU: Casa Romana) (Head: Internal) | Y10: 74079.78 | Z10: =IFERROR(ROUND(Y10-K10,2),"") -> 1.78
A11: 226 | B11: =IFERROR("Q"&(INT(MOD(#REF!-4,12)/3)+1),"") | C11: =IFERROR(MONTH(DATEVALUE(D11)),"") -> 8 | D11: 11-Aug-2026 | E11: 11-Aug-2026 | G11: NEFT CR-HDFC0000240- AMIT JAIN-LEKH RAJ BAJAJ-HDFCH01188134343 | H11: YES0N6223910853400 | J11: 50000 | K11: =K12+J11-F11 -> 179078 | L11: Casa Romana | M11: Collection | O11: Entry | P11: Customer Collection | Q11: Credit- no effect | T11: M-105 | V11: On Account | W11: =TRIM(IF(M11="Internal", IF(ISBLANK(G11), IF(LEN(G11)-LEN(SUBSTITUTE(G11,"-",""))>=3, "Fund Transfer: From x" & RIGHT(MID(G11, FIND("|", SUBSTITUTE(G11, "-", "|", 3)) + 1, LEN(G11)), 4) & " to YES MASTER 0264 (Ref: " & H11 & ") (Type: " & P11 & ") (BU: " & L11 & ") (Head: " & M11 & ")", "Fund Transfer: To YES MASTER 0264 (Ref: " & H11 & ") (Type: " & P11 & ") (BU: " & L11 & ") (Head: " & M11 & ")"), IF(LEN(G11)-LEN(SUBSTITUTE(G11,"-",""))>=3, "Fund Transfer: From YES MASTER 0264 to x" & RIGHT(MID(G11, FIND("|", SUBSTITUTE(G11, "-", "|", 3)) + 1, LEN(G11)), 4) & " (Ref: " & H11 & ") (Type: " & P11 & ") (BU: " & L11 & ") (Head: " & M11 & ")", "Fund Transfer: From YES MASTER 0264 (Ref: " & H11 & ") (Type: " & P11 & ") (BU: " & L11 & ") (Head: " & M11 & ")")), IF(NOT(ISBLANK(J11)), IF(P11="Customer Collection", "Receipt: For " & IF(ISBLANK(T11), "", "(Apt#: " & T11 & ") ") & "(Ref: " & H11 & ") (" & IF(ISNUMBER(SEARCH("NEFT",G11)), "NEFT:", IF(ISNUMBER(SEARCH("RTGS",G11)), "RTGS:", IF(ISNUMBER(SEARCH("IMPS",G11)), "IMPS:", ""))) & " " & IF(ISNUMBER(SEARCH("SOHNA ROAD", G11)), "", IFERROR(MID(G11, FIND("-", G11, FIND("-", G11) + 1) + 1, LEN(G11)), SUBSTITUTE(SUBSTITUTE(SUBSTITUTE(G11, "IMPS/", ""), "NEFT/", ""), "RTGS/", ""))) & ") (Type: " & P11 & ") (BU: " & L11 & ")", IF(LEN(G11)-LEN(SUBSTITUTE(G11,"-",""))>=3, "Receipt: From x" & RIGHT(MID(G11, FIND("|", SUBSTITUTE(G11, "-", "|", 3)) + 1, LEN(G11)), 4) & " towards " & IF(ISBLANK(U11), L11, U11) & IF(OR(L11="Cancellation", L11="Collection"), " Apt No " & T11, "") & " (Ref: " & H11 & ") (Type: " & P11 & ") (BU: " & L11 & ") (Head: " & M11 & ")" & IF(ISBLANK(T11), "", " (Apt#: " & T11 & ")"), "Receipt: Against " & IF(ISBLANK(U11), L11, U11) & IF(OR(L11="Cancellation", L11="Collection"), " Apt No " & T11, "") & " (Ref: " & H11 & ") (Type: " & P11 & ") (BU: " & L11 & ") (Head: " & M11 & ")" & IF(ISBLANK(T11), "", " (Apt#: " & T11 & ")"))), IF(LEN(G11)-LEN(SUBSTITUTE(G11,"-",""))>=3, "Payment: To x" & RIGHT(MID(G11, FIND("|", SUBSTITUTE(G11, "-", "|", 3)) + 1, LEN(G11)), 4) & " for " & IF(ISBLANK(U11), L11, U11) & " (Ref: " & H11 & ") (Type: " & P11 & ") (BU: " & L11 & ") (Head: " & M11 & ")" & IF(ISBLANK(T11), "", " (Apt#: " & T11 & ")"), "Payment: Disbursement for " & IF(ISBLANK(U11), "", IF(ISBLANK(U11), "", U11) & " ") & "(Ref: " & H11 & ") (Type: " & P11 & ") (BU: " & L11 & ") (Head: " & M11 & ")" & IF(ISBLANK(T11), "", " (Apt#: " & T11 & ")"))))) -> Receipt: For (Apt#: M-105) (Ref: YES0N6223910853400) (NEFT: AMIT JAIN-LEKH RAJ BAJAJ-HDFCH01188134343) (Type: Customer Collection) (BU: Casa Romana) | X11: 0.01 | Y11: 179079.78 | Z11: =IFERROR(ROUND(Y11-K11,2),"") -> 1.78
A12: 225 | B12: =IFERROR("Q"&(INT(MOD(C12-4,12)/3)+1),"") -> Q2 | C12: =IFERROR(MONTH(DATEVALUE(D12)),"") -> 8 | D12: 10-Aug-2026 | E12: 10-Aug-2026 | G12: NEFT CR-KVBL0002101-RAHULENT ERPRISES-DWARKADHIS PROJECTS PRIVA-KVBLH00267884483 | J12: 100000 | K12: =K13+J12-I12 -> 129078 | L12: Casa Romana | M12: Collection | O12: Entry | P12: Customer Collection | Q12: Credit- no effect | T12: U-013 | V12: On Account | W12: =TRIM(IF(M12="Internal", IF(ISBLANK(G12), IF(LEN(G12)-LEN(SUBSTITUTE(G12,"-",""))>=3, "Fund Transfer: From x" & RIGHT(MID(G12, FIND("|", SUBSTITUTE(G12, "-", "|", 3)) + 1, LEN(G12)), 4) & " to YES MASTER 0264 (Ref: " & H12 & ") (Type: " & P12 & ") (BU: " & L12 & ") (Head: " & M12 & ")", "Fund Transfer: To YES MASTER 0264 (Ref: " & H12 & ") (Type: " & P12 & ") (BU: " & L12 & ") (Head: " & M12 & ")"), IF(LEN(G12)-LEN(SUBSTITUTE(G12,"-",""))>=3, "Fund Transfer: From YES MASTER 0264 to x" & RIGHT(MID(G12, FIND("|", SUBSTITUTE(G12, "-", "|", 3)) + 1, LEN(G12)), 4) & " (Ref: " & H12 & ") (Type: " & P12 & ") (BU: " & L12 & ") (Head: " & M12 & ")", "Fund Transfer: From YES MASTER 0264 (Ref: " & H12 & ") (Type: " & P12 & ") (BU: " & L12 & ") (Head: " & M12 & ")")), IF(NOT(ISBLANK(J12)), IF(P12="Customer Collection", "Receipt: For " & IF(ISBLANK(T12), "", "(Apt#: " & T12 & ") ") & "(Ref: " & H12 & ") (" & IF(ISNUMBER(SEARCH("NEFT",G12)), "NEFT:", IF(ISNUMBER(SEARCH("RTGS",G12)), "RTGS:", IF(ISNUMBER(SEARCH("IMPS",G12)), "IMPS:", ""))) & " " & IF(ISNUMBER(SEARCH("SOHNA ROAD", G12)), "", IFERROR(MID(G12, FIND("-", G12, FIND("-", G12) + 1) + 1, LEN(G12)), SUBSTITUTE(SUBSTITUTE(SUBSTITUTE(G12, "IMPS/", ""), "NEFT/", ""), "RTGS/", ""))) & ") (Type: " & P12 & ") (BU: " & L12 & ")", IF(LEN(G12)-LEN(SUBSTITUTE(G12,"-",""))>=3, "Receipt: From x" & RIGHT(MID(G12, FIND("|", SUBSTITUTE(G12, "-", "|", 3)) + 1, LEN(G12)), 4) & " towards " & IF(ISBLANK(U12), L12, U12) & IF(OR(L12="Cancellation", L12="Collection"), " Apt No " & T12, "") & " (Ref: " & H12 & ") (Type: " & P12 & ") (BU: " & L12 & ") (Head: " & M12 & ")" & IF(ISBLANK(T12), "", " (Apt#: " & T12 & ")"), "Receipt: Against " & IF(ISBLANK(U12), L12, U12) & IF(OR(L12="Cancellation", L12="Collection"), " Apt No " & T12, "") & " (Ref: " & H12 & ") (Type: " & P12 & ") (BU: " & L12 & ") (Head: " & M12 & ")" & IF(ISBLANK(T12), "", " (Apt#: " & T12 & ")"))), IF(LEN(G12)-LEN(SUBSTITUTE(G12,"-",""))>=3, "Payment: To x" & RIGHT(MID(G12, FIND("|", SUBSTITUTE(G12, "-", "|", 3)) + 1, LEN(G12)), 4) & " for " & IF(ISBLANK(U12), L12, U12) & " (Ref: " & H12 & ") (Type: " & P12 & ") (BU: " & L12 & ") (Head: " & M12 & ")" & IF(ISBLANK(T12), "", " (Apt#: " & T12 & ")"), "Payment: Disbursement for " & IF(ISBLANK(U12), "", IF(ISBLANK(U12), "", U12) & " ") & "(Ref: " & H12 & ") (Type: " & P12 & ") (BU: " & L12 & ") (Head: " & M12 & ")" & IF(ISBLANK(T12), "", " (Apt#: " & T12 & ")"))))) -> Receipt: For (Apt#: U-013) (Ref: ) (NEFT: RAHULENT ERPRISES-DWARKADHIS PROJECTS PRIVA-KVBLH00267884483) (Type: Customer Collection) (BU: Casa Romana) | X12: 0.05 | Y12: 129079.78 | Z12: =IFERROR(ROUND(Y12-K12,2),"") -> 1.78
A13: 224 | B13: =IFERROR("Q"&(INT(MOD(C13-4,12)/3)+1),"") -> Q2 | C13: =IFERROR(MONTH(DATEVALUE(D13)),"") -> 8 | D13: 06-Aug-2026 | E13: 06-Aug-2026 | G13: YIB-TPT-DWARKADHIS PROJECTS PRIVATE LIMITED-INTERNAL-0455632 00000377 | I13: 198629 | K13: =K14+J13-I13 -> 29078 | L13: Casa Romana | M13: Internal | O13: Entry | P13: Master 2 RERA | Q13: Internal transfer | W13: =TRIM(IF(M13="Internal", IF(ISBLANK(G13), IF(LEN(G13)-LEN(SUBSTITUTE(G13,"-",""))>=3, "Fund Transfer: From x" & RIGHT(MID(G13, FIND("|", SUBSTITUTE(G13, "-", "|", 3)) + 1, LEN(G13)), 4) & " to YES MASTER 0264 (Ref: " & H13 & ") (Type: " & P13 & ") (BU: " & L13 & ") (Head: " & M13 & ")", "Fund Transfer: To YES MASTER 0264 (Ref: " & H13 & ") (Type: " & P13 & ") (BU: " & L13 & ") (Head: " & M13 & ")"), IF(LEN(G13)-LEN(SUBSTITUTE(G13,"-",""))>=3, "Fund Transfer: From YES MASTER 0264 to x" & RIGHT(MID(G13, FIND("|", SUBSTITUTE(G13, "-", "|", 3)) + 1, LEN(G13)), 4) & " (Ref: " & H13 & ") (Type: " & P13 & ") (BU: " & L13 & ") (Head: " & M13 & ")", "Fund Transfer: From YES MASTER 0264 (Ref: " & H13 & ") (Type: " & P13 & ") (BU: " & L13 & ") (Head: " & M13 & ")")), IF(NOT(ISBLANK(J13)), IF(P13="Customer Collection", "Receipt: For " & IF(ISBLANK(T13), "", "(Apt#: " & T13 & ") ") & "(Ref: " & H13 & ") (" & IF(ISNUMBER(SEARCH("NEFT",G13)), "NEFT:", IF(ISNUMBER(SEARCH("RTGS",G13)), "RTGS:", IF(ISNUMBER(SEARCH("IMPS",G13)), "IMPS:", ""))) & " " & IF(ISNUMBER(SEARCH("SOHNA ROAD", G13)), "", IFERROR(MID(G13, FIND("-", G13, FIND("-", G13) + 1) + 1, LEN(G13)), SUBSTITUTE(SUBSTITUTE(SUBSTITUTE(G13, "IMPS/", ""), "NEFT/", ""), "RTGS/", ""))) & ") (Type: " & P13 & ") (BU: " & L13 & ")", IF(LEN(G13)-LEN(SUBSTITUTE(G13,"-",""))>=3, "Receipt: From x" & RIGHT(MID(G13, FIND("|", SUBSTITUTE(G13, "-", "|", 3)) + 1, LEN(G13)), 4) & " towards " & IF(ISBLANK(U13), L13, U13) & IF(OR(L13="Cancellation", L13="Collection"), " Apt No " & T13, "") & " (Ref: " & H13 & ") (Type: " & P13 & ") (BU: " & L13 & ") (Head: " & M13 & ")" & IF(ISBLANK(T13), "", " (Apt#: " & T13 & ")"), "Receipt: Against " & IF(ISBLANK(U13), L13, U13) & IF(OR(L13="Cancellation", L13="Collection"), " Apt No " & T13, "") & " (Ref: " & H13 & ") (Type: " & P13 & ") (BU: " & L13 & ") (Head: " & M13 & ")" & IF(ISBLANK(T13), "", " (Apt#: " & T13 & ")"))), IF(LEN(G13)-LEN(SUBSTITUTE(G13,"-",""))>=3, "Payment: To x" & RIGHT(MID(G13, FIND("|", SUBSTITUTE(G13, "-", "|", 3)) + 1, LEN(G13)), 4) & " for " & IF(ISBLANK(U13), L13, U13) & " (Ref: " & H13 & ") (Type: " & P13 & ") (BU: " & L13 & ") (Head: " & M13 & ")" & IF(ISBLANK(T13), "", " (Apt#: " & T13 & ")"), "Payment: Disbursement for " & IF(ISBLANK(U13), "", IF(ISBLANK(U13), "", U13) & " ") & "(Ref: " & H13 & ") (Type: " & P13 & ") (BU: " & L13 & ") (Head: " & M13 & ")" & IF(ISBLANK(T13), "", " (Apt#: " & T13 & ")"))))) -> Fund Transfer: From YES MASTER 0264 to x0377 (Ref: ) (Type: Master 2 RERA) (BU: Casa Romana) (Head: Internal) | Y13: 29079.78 | Z13: =Y13-K13 -> 1.78
A14: 223 | B14: =IFERROR("Q"&(INT(MOD(C14-4,12)/3)+1),"") -> Q2 | C14: =IFERROR(MONTH(DATEVALUE(D14)),"") -> 8 | D14: 06-Aug-2026 | E14: 06-Aug-2026 | G14: YIB-TPT-DWARKADHIS PROJECTS PVT LT D-INTERNAL-045563400002477 | I14: 85127 | K14: =K15+J14-I14 -> 227707 | L14: Casa Romana | M14: Internal | O14: Entry | P14: Master to Free | Q14: Internal transfer | W14: =TRIM(IF(M14="Internal", IF(ISBLANK(G14), IF(LEN(G14)-LEN(SUBSTITUTE(G14,"-",""))>=3, "Fund Transfer: From x" & RIGHT(MID(G14, FIND("|", SUBSTITUTE(G14, "-", "|", 3)) + 1, LEN(G14)), 4) & " to YES MASTER 0264 (Ref: " & H14 & ") (Type: " & P14 & ") (BU: " & L14 & ") (Head: " & M14 & ")", "Fund Transfer: To YES MASTER 0264 (Ref: " & H14 & ") (Type: " & P14 & ") (BU: " & L14 & ") (Head: " & M14 & ")"), IF(LEN(G14)-LEN(SUBSTITUTE(G14,"-",""))>=3, "Fund Transfer: From YES MASTER 0264 to x" & RIGHT(MID(G14, FIND("|", SUBSTITUTE(G14, "-", "|", 3)) + 1, LEN(G14)), 4) & " (Ref: " & H14 & ") (Type: " & P14 & ") (BU: " & L14 & ") (Head: " & M14 & ")", "Fund Transfer: From YES MASTER 0264 (Ref: " & H14 & ") (Type: " & P14 & ") (BU: " & L14 & ") (Head: " & M14 & ")")), IF(NOT(ISBLANK(J14)), IF(P14="Customer Collection", "Receipt: For " & IF(ISBLANK(T14), "", "(Apt#: " & T14 & ") ") & "(Ref: " & H14 & ") (" & IF(ISNUMBER(SEARCH("NEFT",G14)), "NEFT:", IF(ISNUMBER(SEARCH("RTGS",G14)), "RTGS:", IF(ISNUMBER(SEARCH("IMPS",G14)), "IMPS:", ""))) & " " & IF(ISNUMBER(SEARCH("SOHNA ROAD", G14)), "", IFERROR(MID(G14, FIND("-", G14, FIND("-", G14) + 1) + 1, LEN(G14)), SUBSTITUTE(SUBSTITUTE(SUBSTITUTE(G14, "IMPS/", ""), "NEFT/", ""), "RTGS/", ""))) & ") (Type: " & P14 & ") (BU: " & L14 & ")", IF(LEN(G14)-LEN(SUBSTITUTE(G14,"-",""))>=3, "Receipt: From x" & RIGHT(MID(G14, FIND("|", SUBSTITUTE(G14, "-", "|", 3)) + 1, LEN(G14)), 4) & " towards " & IF(ISBLANK(U14), L14, U14) & IF(OR(L14="Cancellation", L14="Collection"), " Apt No " & T14, "") & " (Ref: " & H14 & ") (Type: " & P14 & ") (BU: " & L14 & ") (Head: " & M14 & ")" & IF(ISBLANK(T14), "", " (Apt#: " & T14 & ")"), "Receipt: Against " & IF(ISBLANK(U14), L14, U14) & IF(OR(L14="Cancellation", L14="Collection"), " Apt No " & T14, "") & " (Ref: " & H14 & ") (Type: " & P14 & ") (BU: " & L14 & ") (Head: " & M14 & ")" & IF(ISBLANK(T14), "", " (Apt#: " & T14 & ")"))), IF(LEN(G14)-LEN(SUBSTITUTE(G14,"-",""))>=3, "Payment: To x" & RIGHT(MID(G14, FIND("|", SUBSTITUTE(G14, "-", "|", 3)) + 1, LEN(G14)), 4) & " for " & IF(ISBLANK(U14), L14, U14) & " (Ref: " & H14 & ") (Type: " & P14 & ") (BU: " & L14 & ") (Head: " & M14 & ")" & IF(ISBLANK(T14), "", " (Apt#: " & T14 & ")"), "Payment: Disbursement for " & IF(ISBLANK(U14), "", IF(ISBLANK(U14), "", U14) & " ") & "(Ref: " & H14 & ") (Type: " & P14 & ") (BU: " & L14 & ") (Head: " & M14 & ")" & IF(ISBLANK(T14), "", " (Apt#: " & T14 & ")"))))) -> Fund Transfer: From YES MASTER 0264 to x2477 (Ref: ) (Type: Master to Free) (BU: Casa Romana) (Head: Internal) | Y14: 227708.78 | Z14: =Y14-K14 -> 1.78
A15: 222 | B15: =IFERROR("Q"&(INT(MOD(C15-4,12)/3)+1),"") -> Q2 | C15: =IFERROR(MONTH(DATEVALUE(D15)),"") -> 8 | D15: 06-Aug-2026 | E15: 06-Aug-2026 | G15: NET-TPT-ASHISH SHUKLA-071691900001571 | J15: 15000 | K15: =K16+J15-I15 -> 312834 | L15: Casa Romana | M15: Collection | O15: Entry | P15: Customer Collection | Q15: Credit- no effect | T15: T-052 | V15: On Account | W15: =TRIM(IF(M15="Internal", IF(ISBLANK(G15), IF(LEN(G15)-LEN(SUBSTITUTE(G15,"-",""))>=3, "Fund Transfer: From x" & RIGHT(MID(G15, FIND("|", SUBSTITUTE(G15, "-", "|", 3)) + 1, LEN(G15)), 4) & " to YES MASTER 0264 (Ref: " & H15 & ") (Type: " & P15 & ") (BU: " & L15 & ") (Head: " & M15 & ")", "Fund Transfer: To YES MASTER 0264 (Ref: " & H15 & ") (Type: " & P15 & ") (BU: " & L15 & ") (Head: " & M15 & ")"), IF(LEN(G15)-LEN(SUBSTITUTE(G15,"-",""))>=3, "Fund Transfer: From YES MASTER 0264 to x" & RIGHT(MID(G15, FIND("|", SUBSTITUTE(G15, "-", "|", 3)) + 1, LEN(G15)), 4) & " (Ref: " & H15 & ") (Type: " & P15 & ") (BU: " & L15 & ") (Head: " & M15 & ")", "Fund Transfer: From YES MASTER 0264 (Ref: " & H15 & ") (Type: " & P15 & ") (BU: " & L15 & ") (Head: " & M15 & ")")), IF(NOT(ISBLANK(J15)), IF(P15="Customer Collection", "Receipt: For " & IF(ISBLANK(T15), "", "(Apt#: " & T15 & ") ") & "(Ref: " & H15 & ") (" & IF(ISNUMBER(SEARCH("NEFT",G15)), "NEFT:", IF(ISNUMBER(SEARCH("RTGS",G15)), "RTGS:", IF(ISNUMBER(SEARCH("IMPS",G15)), "IMPS:", ""))) & " " & IF(ISNUMBER(SEARCH("SOHNA ROAD", G15)), "", IFERROR(MID(G15, FIND("-", G15, FIND("-", G15) + 1) + 1, LEN(G15)), SUBSTITUTE(SUBSTITUTE(SUBSTITUTE(G15, "IMPS/", ""), "NEFT/", ""), "RTGS/", ""))) & ") (Type: " & P15 & ") (BU: " & L15 & ")", IF(LEN(G15)-LEN(SUBSTITUTE(G15,"-",""))>=3, "Receipt: From x" & RIGHT(MID(G15, FIND("|", SUBSTITUTE(G15, "-", "|", 3)) + 1, LEN(G15)), 4) & " towards " & IF(ISBLANK(U15), L15, U15) & IF(OR(L15="Cancellation", L15="Collection"), " Apt No " & T15, "") & " (Ref: " & H15 & ") (Type: " & P15 & ") (BU: " & L15 & ") (Head: " & M15 & ")" & IF(ISBLANK(T15), "", " (Apt#: " & T15 & ")"), "Receipt: Against " & IF(ISBLANK(U15), L15, U15) & IF(OR(L15="Cancellation", L15="Collection"), " Apt No " & T15, "") & " (Ref: " & H15 & ") (Type: " & P15 & ") (BU: " & L15 & ") (Head: " & M15 & ")" & IF(ISBLANK(T15), "", " (Apt#: " & T15 & ")"))), IF(LEN(G15)-LEN(SUBSTITUTE(G15,"-",""))>=3, "Payment: To x" & RIGHT(MID(G15, FIND("|", SUBSTITUTE(G15, "-", "|", 3)) + 1, LEN(G15)), 4) & " for " & IF(ISBLANK(U15), L15, U15) & " (Ref: " & H15 & ") (Type: " & P15 & ") (BU: " & L15 & ") (Head: " & M15 & ")" & IF(ISBLANK(T15), "", " (Apt#: " & T15 & ")"), "Payment: Disbursement for " & IF(ISBLANK(U15), "", IF(ISBLANK(U15), "", U15) & " ") & "(Ref: " & H15 & ") (Type: " & P15 & ") (BU: " & L15 & ") (Head: " & M15 & ")" & IF(ISBLANK(T15), "", " (Apt#: " & T15 & ")"))))) -> Receipt: For (Apt#: T-052) (Ref: ) ( ASHISH SHUKLA-071691900001571) (Type: Customer Collection) (BU: Casa Romana) | X15: 0.05 | Y15: 312835.78 | Z15: =Y15-K15 -> 1.78
A16: 221 | B16: =IFERROR("Q"&(INT(MOD(C16-4,12)/3)+1),"") -> Q2 | C16: =IFERROR(MONTH(DATEVALUE(D16)),"") -> 8 | D16: 05-Aug-2026 | E16: 05-Aug-2026 | G16: RTGS CR-HDFC0000240-VANDANA KHULLAR-DWARKADHIS PROJECTS PVTL-HDFCR52026080592593517 | J16: 218756 | K16: =K17+J16-I16 -> 297834 | L16: Casa Romana | M16: Collection | O16: Entry | P16: Customer Collection | Q16: Credit- no effect | T16: L-064 | V16: Adjust | W16: =TRIM(IF(M16="Internal", IF(ISBLANK(G16), IF(LEN(G16)-LEN(SUBSTITUTE(G16,"-",""))>=3, "Fund Transfer: From x" & RIGHT(MID(G16, FIND("|", SUBSTITUTE(G16, "-", "|", 3)) + 1, LEN(G16)), 4) & " to YES MASTER 0264 (Ref: " & H16 & ") (Type: " & P16 & ") (BU: " & L16 & ") (Head: " & M16 & ")", "Fund Transfer: To YES MASTER 0264 (Ref: " & H16 & ") (Type: " & P16 & ") (BU: " & L16 & ") (Head: " & M16 & ")"), IF(LEN(G16)-LEN(SUBSTITUTE(G16,"-",""))>=3, "Fund Transfer: From YES MASTER 0264 to x" & RIGHT(MID(G16, FIND("|", SUBSTITUTE(G16, "-", "|", 3)) + 1, LEN(G16)), 4) & " (Ref: " & H16 & ") (Type: " & P16 & ") (BU: " & L16 & ") (Head: " & M16 & ")", "Fund Transfer: From YES MASTER 0264 (Ref: " & H16 & ") (Type: " & P16 & ") (BU: " & L16 & ") (Head: " & M16 & ")")), IF(NOT(ISBLANK(J16)), IF(P16="Customer Collection", "Receipt: For " & IF(ISBLANK(T16), "", "(Apt#: " & T16 & ") ") & "(Ref: " & H16 & ") (" & IF(ISNUMBER(SEARCH("NEFT",G16)), "NEFT:", IF(ISNUMBER(SEARCH("RTGS",G16)), "RTGS:", IF(ISNUMBER(SEARCH("IMPS",G16)), "IMPS:", ""))) & " " & IF(ISNUMBER(SEARCH("SOHNA ROAD", G16)), "", IFERROR(MID(G16, FIND("-", G16, FIND("-", G16) + 1) + 1, LEN(G16)), SUBSTITUTE(SUBSTITUTE(SUBSTITUTE(G16, "IMPS/", ""), "NEFT/", ""), "RTGS/", ""))) & ") (Type: " & P16 & ") (BU: " & L16 & ")", IF(LEN(G16)-LEN(SUBSTITUTE(G16,"-",""))>=3, "Receipt: From x" & RIGHT(MID(G16, FIND("|", SUBSTITUTE(G16, "-", "|", 3)) + 1, LEN(G16)), 4) & " towards " & IF(ISBLANK(U16), L16, U16) & IF(OR(L16="Cancellation", L16="Collection"), " Apt No " & T16, "") & " (Ref: " & H16 & ") (Type: " & P16 & ") (BU: " & L16 & ") (Head: " & M16 & ")" & IF(ISBLANK(T16), "", " (Apt#: " & T16 & ")"), "Receipt: Against " & IF(ISBLANK(U16), L16, U16) & IF(OR(L16="Cancellation", L16="Collection"), " Apt No " & T16, "") & " (Ref: " & H16 & ") (Type: " & P16 & ") (BU: " & L16 & ") (Head: " & M16 & ")" & IF(ISBLANK(T16), "", " (Apt#: " & T16 & ")"))), IF(LEN(G16)-LEN(SUBSTITUTE(G16,"-",""))>=3, "Payment: To x" & RIGHT(MID(G16, FIND("|", SUBSTITUTE(G16, "-", "|", 3)) + 1, LEN(G16)), 4) & " for " & IF(ISBLANK(U16), L16, U16) & " (Ref: " & H16 & ") (Type: " & P16 & ") (BU: " & L16 & ") (Head: " & M16 & ")" & IF(ISBLANK(T16), "", " (Apt#: " & T16 & ")"), "Payment: Disbursement for " & IF(ISBLANK(U16), "", IF(ISBLANK(U16), "", U16) & " ") & "(Ref: " & H16 & ") (Type: " & P16 & ") (BU: " & L16 & ") (Head: " & M16 & ")" & IF(ISBLANK(T16), "", " (Apt#: " & T16 & ")"))))) -> Receipt: For (Apt#: L-064) (Ref: ) (RTGS: VANDANA KHULLAR-DWARKADHIS PROJECTS PVTL-HDFCR52026080592593517) (Type: Customer Collection) (BU: Casa Romana) | Y16: 297835.78 | Z16: =Y16-K16 -> 1.78
A17: 220 | B17: =IFERROR("Q"&(INT(MOD(C17-4,12)/3)+1),"") -> Q2 | C17: =IFERROR(MONTH(DATEVALUE(D17)),"") -> 8 | D17: 05-Aug-2026 | E17: 05-Aug-2026 | G17: NEFT CR-HDFC0000001-CHETAN A HUJA-DWARKADHIS PROJECTS PRIVA-HDFCH01173383398 | J17: 50000 | K17: =K18+J17-I17 -> 79078 | L17: Casa Romana | M17: Collection | O17: Entry | P17: Customer Collection | Q17: Credit- no effect | T17: U-062 | V17: Adjust | W17: =TRIM(IF(M17="Internal", IF(ISBLANK(G17), IF(LEN(G17)-LEN(SUBSTITUTE(G17,"-",""))>=3, "Fund Transfer: From x" & RIGHT(MID(G17, FIND("|", SUBSTITUTE(G17, "-", "|", 3)) + 1, LEN(G17)), 4) & " to YES MASTER 0264 (Ref: " & H17 & ") (Type: " & P17 & ") (BU: " & L17 & ") (Head: " & M17 & ")", "Fund Transfer: To YES MASTER 0264 (Ref: " & H17 & ") (Type: " & P17 & ") (BU: " & L17 & ") (Head: " & M17 & ")"), IF(LEN(G17)-LEN(SUBSTITUTE(G17,"-",""))>=3, "Fund Transfer: From YES MASTER 0264 to x" & RIGHT(MID(G17, FIND("|", SUBSTITUTE(G17, "-", "|", 3)) + 1, LEN(G17)), 4) & " (Ref: " & H17 & ") (Type: " & P17 & ") (BU: " & L17 & ") (Head: " & M17 & ")", "Fund Transfer: From YES MASTER 0264 (Ref: " & H17 & ") (Type: " & P17 & ") (BU: " & L17 & ") (Head: " & M17 & ")")), IF(NOT(ISBLANK(J17)), IF(P17="Customer Collection", "Receipt: For " & IF(ISBLANK(T17), "", "(Apt#: " & T17 & ") ") & "(Ref: " & H17 & ") (" & IF(ISNUMBER(SEARCH("NEFT",G17)), "NEFT:", IF(ISNUMBER(SEARCH("RTGS",G17)), "RTGS:", IF(ISNUMBER(SEARCH("IMPS",G17)), "IMPS:", ""))) & " " & IF(ISNUMBER(SEARCH("SOHNA ROAD", G17)), "", IFERROR(MID(G17, FIND("-", G17, FIND("-", G17) + 1) + 1, LEN(G17)), SUBSTITUTE(SUBSTITUTE(SUBSTITUTE(G17, "IMPS/", ""), "NEFT/", ""), "RTGS/", ""))) & ") (Type: " & P17 & ") (BU: " & L17 & ")", IF(LEN(G17)-LEN(SUBSTITUTE(G17,"-",""))>=3, "Receipt: From x" & RIGHT(MID(G17, FIND("|", SUBSTITUTE(G17, "-", "|", 3)) + 1, LEN(G17)), 4) & " towards " & IF(ISBLANK(U17), L17, U17) & IF(OR(L17="Cancellation", L17="Collection"), " Apt No " & T17, "") & " (Ref: " & H17 & ") (Type: " & P17 & ") (BU: " & L17 & ") (Head: " & M17 & ")" & IF(ISBLANK(T17), "", " (Apt#: " & T17 & ")"), "Receipt: Against " & IF(ISBLANK(U17), L17, U17) & IF(OR(L17="Cancellation", L17="Collection"), " Apt No " & T17, "") & " (Ref: " & H17 & ") (Type: " & P17 & ") (BU: " & L17 & ") (Head: " & M17 & ")" & IF(ISBLANK(T17), "", " (Apt#: " & T17 & ")"))), IF(LEN(G17)-LEN(SUBSTITUTE(G17,"-",""))>=3, "Payment: To x" & RIGHT(MID(G17, FIND("|", SUBSTITUTE(G17, "-", "|", 3)) + 1, LEN(G17)), 4) & " for " & IF(ISBLANK(U17), L17, U17) & " (Ref: " & H17 & ") (Type: " & P17 & ") (BU: " & L17 & ") (Head: " & M17 & ")" & IF(ISBLANK(T17), "", " (Apt#: " & T17 & ")"), "Payment: Disbursement for " & IF(ISBLANK(U17), "", IF(ISBLANK(U17), "", U17) & " ") & "(Ref: " & H17 & ") (Type: " & P17 & ") (BU: " & L17 & ") (Head: " & M17 & ")" & IF(ISBLANK(T17), "", " (Apt#: " & T17 & ")"))))) -> Receipt: For (Apt#: U-062) (Ref: ) (NEFT: CHETAN A HUJA-DWARKADHIS PROJECTS PRIVA-HDFCH01173383398) (Type: Customer Collection) (BU: Casa Romana) | Y17: 79079.78 | Z17: =Y17-K17 -> 1.78
A18: 219 | B18: =IFERROR("Q"&(INT(MOD(C18-4,12)/3)+1),"") -> Q2 | C18: =IFERROR(MONTH(DATEVALUE(D18)),"") -> 8 | D18: 05-Aug-2026 | E18: 05-Aug-2026 | G18: YIB-TPT-DWARKADHIS PROJECTS PVT LT D-INTERNAL-045563400002477 | I18: 99576 | K18: =K19+J18-I18 -> 29078 | L18: Casa Romana | M18: Internal | O18: Entry | P18: Master to Free | Q18: Internal transfer | W18: =TRIM(IF(M18="Internal", IF(ISBLANK(G18), IF(LEN(G18)-LEN(SUBSTITUTE(G18,"-",""))>=3, "Fund Transfer: From x" & RIGHT(MID(G18, FIND("|", SUBSTITUTE(G18, "-", "|", 3)) + 1, LEN(G18)), 4) & " to YES MASTER 0264 (Ref: " & H18 & ") (Type: " & P18 & ") (BU: " & L18 & ") (Head: " & M18 & ")", "Fund Transfer: To YES MASTER 0264 (Ref: " & H18 & ") (Type: " & P18 & ") (BU: " & L18 & ") (Head: " & M18 & ")"), IF(LEN(G18)-LEN(SUBSTITUTE(G18,"-",""))>=3, "Fund Transfer: From YES MASTER 0264 to x" & RIGHT(MID(G18, FIND("|", SUBSTITUTE(G18, "-", "|", 3)) + 1, LEN(G18)), 4) & " (Ref: " & H18 & ") (Type: " & P18 & ") (BU: " & L18 & ") (Head: " & M18 & ")", "Fund Transfer: From YES MASTER 0264 (Ref: " & H18 & ") (Type: " & P18 & ") (BU: " & L18 & ") (Head: " & M18 & ")")), IF(NOT(ISBLANK(J18)), IF(P18="Customer Collection", "Receipt: For " & IF(ISBLANK(T18), "", "(Apt#: " & T18 & ") ") & "(Ref: " & H18 & ") (" & IF(ISNUMBER(SEARCH("NEFT",G18)), "NEFT:", IF(ISNUMBER(SEARCH("RTGS",G18)), "RTGS:", IF(ISNUMBER(SEARCH("IMPS",G18)), "IMPS:", ""))) & " " & IF(ISNUMBER(SEARCH("SOHNA ROAD", G18)), "", IFERROR(MID(G18, FIND("-", G18, FIND("-", G18) + 1) + 1, LEN(G18)), SUBSTITUTE(SUBSTITUTE(SUBSTITUTE(G18, "IMPS/", ""), "NEFT/", ""), "RTGS/", ""))) & ") (Type: " & P18 & ") (BU: " & L18 & ")", IF(LEN(G18)-LEN(SUBSTITUTE(G18,"-",""))>=3, "Receipt: From x" & RIGHT(MID(G18, FIND("|", SUBSTITUTE(G18, "-", "|", 3)) + 1, LEN(G18)), 4) & " towards " & IF(ISBLANK(U18), L18, U18) & IF(OR(L18="Cancellation", L18="Collection"), " Apt No " & T18, "") & " (Ref: " & H18 & ") (Type: " & P18 & ") (BU: " & L18 & ") (Head: " & M18 & ")" & IF(ISBLANK(T18), "", " (Apt#: " & T18 & ")"), "Receipt: Against " & IF(ISBLANK(U18), L18, U18) & IF(OR(L18="Cancellation", L18="Collection"), " Apt No " & T18, "") & " (Ref: " & H18 & ") (Type: " & P18 & ") (BU: " & L18 & ") (Head: " & M18 & ")" & IF(ISBLANK(T18), "", " (Apt#: " & T18 & ")"))), IF(LEN(G18)-LEN(SUBSTITUTE(G18,"-",""))>=3, "Payment: To x" & RIGHT(MID(G18, FIND("|", SUBSTITUTE(G18, "-", "|", 3)) + 1, LEN(G18)), 4) & " for " & IF(ISBLANK(U18), L18, U18) & " (Ref: " & H18 & ") (Type: " & P18 & ") (BU: " & L18 & ") (Head: " & M18 & ")" & IF(ISBLANK(T18), "", " (Apt#: " & T18 & ")"), "Payment: Disbursement for " & IF(ISBLANK(U18), "", IF(ISBLANK(U18), "", U18) & " ") & "(Ref: " & H18 & ") (Type: " & P18 & ") (BU: " & L18 & ") (Head: " & M18 & ")" & IF(ISBLANK(T18), "", " (Apt#: " & T18 & ")"))))) -> Fund Transfer: From YES MASTER 0264 to x2477 (Ref: ) (Type: Master to Free) (BU: Casa Romana) (Head: Internal) | Y18: 29079.78 | Z18: =Y18-K18 -> 1.78
A19: 218 | B19: =IFERROR("Q"&(INT(MOD(C19-4,12)/3)+1),"") -> Q2 | C19: =IFERROR(MONTH(DATEVALUE(D19)),"") -> 8 | D19: 05-Aug-2026 | E19: 05-Aug-2026 | G19: YIB-TPT-DWARKADHIS PROJECTS PRIVATE LIMITED-INTERNAL-0455632 00000377 | I19: 232344 | K19: =K20+J19-I19 -> 128654 | L19: Casa Romana | M19: Internal | O19: Entry | P19: Master 2 RERA | Q19: Internal transfer | W19: =TRIM(IF(M19="Internal", IF(ISBLANK(G19), IF(LEN(G19)-LEN(SUBSTITUTE(G19,"-",""))>=3, "Fund Transfer: From x" & RIGHT(MID(G19, FIND("|", SUBSTITUTE(G19, "-", "|", 3)) + 1, LEN(G19)), 4) & " to YES MASTER 0264 (Ref: " & H19 & ") (Type: " & P19 & ") (BU: " & L19 & ") (Head: " & M19 & ")", "Fund Transfer: To YES MASTER 0264 (Ref: " & H19 & ") (Type: " & P19 & ") (BU: " & L19 & ") (Head: " & M19 & ")"), IF(LEN(G19)-LEN(SUBSTITUTE(G19,"-",""))>=3, "Fund Transfer: From YES MASTER 0264 to x" & RIGHT(MID(G19, FIND("|", SUBSTITUTE(G19, "-", "|", 3)) + 1, LEN(G19)), 4) & " (Ref: " & H19 & ") (Type: " & P19 & ") (BU: " & L19 & ") (Head: " & M19 & ")", "Fund Transfer: From YES MASTER 0264 (Ref: " & H19 & ") (Type: " & P19 & ") (BU: " & L19 & ") (Head: " & M19 & ")")), IF(NOT(ISBLANK(J19)), IF(P19="Customer Collection", "Receipt: For " & IF(ISBLANK(T19), "", "(Apt#: " & T19 & ") ") & "(Ref: " & H19 & ") (" & IF(ISNUMBER(SEARCH("NEFT",G19)), "NEFT:", IF(ISNUMBER(SEARCH("RTGS",G19)), "RTGS:", IF(ISNUMBER(SEARCH("IMPS",G19)), "IMPS:", ""))) & " " & IF(ISNUMBER(SEARCH("SOHNA ROAD", G19)), "", IFERROR(MID(G19, FIND("-", G19, FIND("-", G19) + 1) + 1, LEN(G19)), SUBSTITUTE(SUBSTITUTE(SUBSTITUTE(G19, "IMPS/", ""), "NEFT/", ""), "RTGS/", ""))) & ") (Type: " & P19 & ") (BU: " & L19 & ")", IF(LEN(G19)-LEN(SUBSTITUTE(G19,"-",""))>=3, "Receipt: From x" & RIGHT(MID(G19, FIND("|", SUBSTITUTE(G19, "-", "|", 3)) + 1, LEN(G19)), 4) & " towards " & IF(ISBLANK(U19), L19, U19) & IF(OR(L19="Cancellation", L19="Collection"), " Apt No " & T19, "") & " (Ref: " & H19 & ") (Type: " & P19 & ") (BU: " & L19 & ") (Head: " & M19 & ")" & IF(ISBLANK(T19), "", " (Apt#: " & T19 & ")"), "Receipt: Against " & IF(ISBLANK(U19), L19, U19) & IF(OR(L19="Cancellation", L19="Collection"), " Apt No " & T19, "") & " (Ref: " & H19 & ") (Type: " & P19 & ") (BU: " & L19 & ") (Head: " & M19 & ")" & IF(ISBLANK(T19), "", " (Apt#: " & T19 & ")"))), IF(LEN(G19)-LEN(SUBSTITUTE(G19,"-",""))>=3, "Payment: To x" & RIGHT(MID(G19, FIND("|", SUBSTITUTE(G19, "-", "|", 3)) + 1, LEN(G19)), 4) & " for " & IF(ISBLANK(U19), L19, U19) & " (Ref: " & H19 & ") (Type: " & P19 & ") (BU: " & L19 & ") (Head: " & M19 & ")" & IF(ISBLANK(T19), "", " (Apt#: " & T19 & ")"), "Payment: Disbursement for " & IF(ISBLANK(U19), "", IF(ISBLANK(U19), "", U19) & " ") & "(Ref: " & H19 & ") (Type: " & P19 & ") (BU: " & L19 & ") (Head: " & M19 & ")" & IF(ISBLANK(T19), "", " (Apt#: " & T19 & ")"))))) -> Fund Transfer: From YES MASTER 0264 to x0377 (Ref: ) (Type: Master 2 RERA) (BU: Casa Romana) (Head: Internal) | Y19: 128655.78 | Z19: =Y19-K19 -> 1.78
A20: 217 | B20: =IFERROR("Q"&(INT(MOD(C20-4,12)/3)+1),"") -> Q2 | C20: =IFERROR(MONTH(DATEVALUE(D20)),"") -> 8 | D20: 05-Aug-2026 | E20: 05-Aug-2026 | G20: NEFT CR-SBIN0003771-VIDYA DEVI -DWARKADHIS PROJECTS PVT L-SBIN526217498424 | J20: 61110 | K20: =K21+J20-I20 -> 360998 | L20: Casa Romana | M20: Collection | O20: Entry | P20: Customer Collection | Q20: Credit- no effect | T20: L-043 | V20: On Account | W20: =TRIM(IF(M20="Internal", IF(ISBLANK(G20), IF(LEN(G20)-LEN(SUBSTITUTE(G20,"-",""))>=3, "Fund Transfer: From x" & RIGHT(MID(G20, FIND("|", SUBSTITUTE(G20, "-", "|", 3)) + 1, LEN(G20)), 4) & " to YES MASTER 0264 (Ref: " & H20 & ") (Type: " & P20 & ") (BU: " & L20 & ") (Head: " & M20 & ")", "Fund Transfer: To YES MASTER 0264 (Ref: " & H20 & ") (Type: " & P20 & ") (BU: " & L20 & ") (Head: " & M20 & ")"), IF(LEN(G20)-LEN(SUBSTITUTE(G20,"-",""))>=3, "Fund Transfer: From YES MASTER 0264 to x" & RIGHT(MID(G20, FIND("|", SUBSTITUTE(G20, "-", "|", 3)) + 1, LEN(G20)), 4) & " (Ref: " & H20 & ") (Type: " & P20 & ") (BU: " & L20 & ") (Head: " & M20 & ")", "Fund Transfer: From YES MASTER 0264 (Ref: " & H20 & ") (Type: " & P20 & ") (BU: " & L20 & ") (Head: " & M20 & ")")), IF(NOT(ISBLANK(J20)), IF(P20="Customer Collection", "Receipt: For " & IF(ISBLANK(T20), "", "(Apt#: " & T20 & ") ") & "(Ref: " & H20 & ") (" & IF(ISNUMBER(SEARCH("NEFT",G20)), "NEFT:", IF(ISNUMBER(SEARCH("RTGS",G20)), "RTGS:", IF(ISNUMBER(SEARCH("IMPS",G20)), "IMPS:", ""))) & " " & IF(ISNUMBER(SEARCH("SOHNA ROAD", G20)), "", IFERROR(MID(G20, FIND("-", G20, FIND("-", G20) + 1) + 1, LEN(G20)), SUBSTITUTE(SUBSTITUTE(SUBSTITUTE(G20, "IMPS/", ""), "NEFT/", ""), "RTGS/", ""))) & ") (Type: " & P20 & ") (BU: " & L20 & ")", IF(LEN(G20)-LEN(SUBSTITUTE(G20,"-",""))>=3, "Receipt: From x" & RIGHT(MID(G20, FIND("|", SUBSTITUTE(G20, "-", "|", 3)) + 1, LEN(G20)), 4) & " towards " & IF(ISBLANK(U20), L20, U20) & IF(OR(L20="Cancellation", L20="Collection"), " Apt No " & T20, "") & " (Ref: " & H20 & ") (Type: " & P20 & ") (BU: " & L20 & ") (Head: " & M20 & ")" & IF(ISBLANK(T20), "", " (Apt#: " & T20 & ")"), "Receipt: Against " & IF(ISBLANK(U20), L20, U20) & IF(OR(L20="Cancellation", L20="Collection"), " Apt No " & T20, "") & " (Ref: " & H20 & ") (Type: " & P20 & ") (BU: " & L20 & ") (Head: " & M20 & ")" & IF(ISBLANK(T20), "", " (Apt#: " & T20 & ")"))), IF(LEN(G20)-LEN(SUBSTITUTE(G20,"-",""))>=3, "Payment: To x" & RIGHT(MID(G20, FIND("|", SUBSTITUTE(G20, "-", "|", 3)) + 1, LEN(G20)), 4) & " for " & IF(ISBLANK(U20), L20, U20) & " (Ref: " & H20 & ") (Type: " & P20 & ") (BU: " & L20 & ") (Head: " & M20 & ")" & IF(ISBLANK(T20), "", " (Apt#: " & T20 & ")"), "Payment: Disbursement for " & IF(ISBLANK(U20), "", IF(ISBLANK(U20), "", U20) & " ") & "(Ref: " & H20 & ") (Type: " & P20 & ") (BU: " & L20 & ") (Head: " & M20 & ")" & IF(ISBLANK(T20), "", " (Apt#: " & T20 & ")"))))) -> Receipt: For (Apt#: L-043) (Ref: ) (NEFT: VIDYA DEVI -DWARKADHIS PROJECTS PVT L-SBIN526217498424) (Type: Customer Collection) (BU: Casa Romana) | X20: 0.05 | Y20: 360999.78 | Z20: =Y20-K20 -> 1.78
A21: 216 | B21: =IFERROR("Q"&(INT(MOD(C21-4,12)/3)+1),"") -> Q2 | C21: =IFERROR(MONTH(DATEVALUE(D21)),"") -> 8 | D21: 05-Aug-2026 | E21: 05-Aug-2026 | G21: YIB-TPT-DWARKADHIS PROJECTS PRIVATE LIMITED-INTERNAL-0455632 00000377 | I21: 159227 | K21: =K22+J21-I21 -> 299888 | L21: Casa Romana | M21: Internal | O21: Entry | P21: Master 2 RERA | Q21: Internal transfer | W21: =TRIM(IF(M21="Internal", IF(ISBLANK(G21), IF(LEN(G21)-LEN(SUBSTITUTE(G21,"-",""))>=3, "Fund Transfer: From x" & RIGHT(MID(G21, FIND("|", SUBSTITUTE(G21, "-", "|", 3)) + 1, LEN(G21)), 4) & " to YES MASTER 0264 (Ref: " & H21 & ") (Type: " & P21 & ") (BU: " & L21 & ") (Head: " & M21 & ")", "Fund Transfer: To YES MASTER 0264 (Ref: " & H21 & ") (Type: " & P21 & ") (BU: " & L21 & ") (Head: " & M21 & ")"), IF(LEN(G21)-LEN(SUBSTITUTE(G21,"-",""))>=3, "Fund Transfer: From YES MASTER 0264 to x" & RIGHT(MID(G21, FIND("|", SUBSTITUTE(G21, "-", "|", 3)) + 1, LEN(G21)), 4) & " (Ref: " & H21 & ") (Type: " & P21 & ") (BU: " & L21 & ") (Head: " & M21 & ")", "Fund Transfer: From YES MASTER 0264 (Ref: " & H21 & ") (Type: " & P21 & ") (BU: " & L21 & ") (Head: " & M21 & ")")), IF(NOT(ISBLANK(J21)), IF(P21="Customer Collection", "Receipt: For " & IF(ISBLANK(T21), "", "(Apt#: " & T21 & ") ") & "(Ref: " & H21 & ") (" & IF(ISNUMBER(SEARCH("NEFT",G21)), "NEFT:", IF(ISNUMBER(SEARCH("RTGS",G21)), "RTGS:", IF(ISNUMBER(SEARCH("IMPS",G21)), "IMPS:", ""))) & " " & IF(ISNUMBER(SEARCH("SOHNA ROAD", G21)), "", IFERROR(MID(G21, FIND("-", G21, FIND("-", G21) + 1) + 1, LEN(G21)), SUBSTITUTE(SUBSTITUTE(SUBSTITUTE(G21, "IMPS/", ""), "NEFT/", ""), "RTGS/", ""))) & ") (Type: " & P21 & ") (BU: " & L21 & ")", IF(LEN(G21)-LEN(SUBSTITUTE(G21,"-",""))>=3, "Receipt: From x" & RIGHT(MID(G21, FIND("|", SUBSTITUTE(G21, "-", "|", 3)) + 1, LEN(G21)), 4) & " towards " & IF(ISBLANK(U21), L21, U21) & IF(OR(L21="Cancellation", L21="Collection"), " Apt No " & T21, "") & " (Ref: " & H21 & ") (Type: " & P21 & ") (BU: " & L21 & ") (Head: " & M21 & ")" & IF(ISBLANK(T21), "", " (Apt#: " & T21 & ")"), "Receipt: Against " & IF(ISBLANK(U21), L21, U21) & IF(OR(L21="Cancellation", L21="Collection"), " Apt No " & T21, "") & " (Ref: " & H21 & ") (Type: " & P21 & ") (BU: " & L21 & ") (Head: " & M21 & ")" & IF(ISBLANK(T21), "", " (Apt#: " & T21 & ")"))), IF(LEN(G21)-LEN(SUBSTITUTE(G21,"-",""))>=3, "Payment: To x" & RIGHT(MID(G21, FIND("|", SUBSTITUTE(G21, "-", "|", 3)) + 1, LEN(G21)), 4) & " for " & IF(ISBLANK(U21), L21, U21) & " (Ref: " & H21 & ") (Type: " & P21 & ") (BU: " & L21 & ") (Head: " & M21 & ")" & IF(ISBLANK(T21), "", " (Apt#: " & T21 & ")"), "Payment: Disbursement for " & IF(ISBLANK(U21), "", IF(ISBLANK(U21), "", U21) & " ") & "(Ref: " & H21 & ") (Type: " & P21 & ") (BU: " & L21 & ") (Head: " & M21 & ")" & IF(ISBLANK(T21), "", " (Apt#: " & T21 & ")"))))) -> Fund Transfer: From YES MASTER 0264 to x0377 (Ref: ) (Type: Master 2 RERA) (BU: Casa Romana) (Head: Internal) | Y21: 299889.78 | Z21: =Y21-K21 -> 1.78
A22: 215 | B22: =IFERROR("Q"&(INT(MOD(C22-4,12)/3)+1),"") -> Q2 | C22: =IFERROR(MONTH(DATEVALUE(D22)),"") -> 8 | D22: 05-Aug-2026 | E22: 05-Aug-2026 | G22: YIB-TPT-DWARKADHIS PROJECTS PVT LT D-INTERNAL-045563400002477 | I22: 68240 | K22: =K23+J22-I22 -> 459115 | L22: Casa Romana | M22: Internal | O22: Entry | P22: Master to Free | Q22: Internal transfer | W22: =TRIM(IF(M22="Internal", IF(ISBLANK(G22), IF(LEN(G22)-LEN(SUBSTITUTE(G22,"-",""))>=3, "Fund Transfer: From x" & RIGHT(MID(G22, FIND("|", SUBSTITUTE(G22, "-", "|", 3)) + 1, LEN(G22)), 4) & " to YES MASTER 0264 (Ref: " & H22 & ") (Type: " & P22 & ") (BU: " & L22 & ") (Head: " & M22 & ")", "Fund Transfer: To YES MASTER 0264 (Ref: " & H22 & ") (Type: " & P22 & ") (BU: " & L22 & ") (Head: " & M22 & ")"), IF(LEN(G22)-LEN(SUBSTITUTE(G22,"-",""))>=3, "Fund Transfer: From YES MASTER 0264 to x" & RIGHT(MID(G22, FIND("|", SUBSTITUTE(G22, "-", "|", 3)) + 1, LEN(G22)), 4) & " (Ref: " & H22 & ") (Type: " & P22 & ") (BU: " & L22 & ") (Head: " & M22 & ")", "Fund Transfer: From YES MASTER 0264 (Ref: " & H22 & ") (Type: " & P22 & ") (BU: " & L22 & ") (Head: " & M22 & ")")), IF(NOT(ISBLANK(J22)), IF(P22="Customer Collection", "Receipt: For " & IF(ISBLANK(T22), "", "(Apt#: " & T22 & ") ") & "(Ref: " & H22 & ") (" & IF(ISNUMBER(SEARCH("NEFT",G22)), "NEFT:", IF(ISNUMBER(SEARCH("RTGS",G22)), "RTGS:", IF(ISNUMBER(SEARCH("IMPS",G22)), "IMPS:", ""))) & " " & IF(ISNUMBER(SEARCH("SOHNA ROAD", G22)), "", IFERROR(MID(G22, FIND("-", G22, FIND("-", G22) + 1) + 1, LEN(G22)), SUBSTITUTE(SUBSTITUTE(SUBSTITUTE(G22, "IMPS/", ""), "NEFT/", ""), "RTGS/", ""))) & ") (Type: " & P22 & ") (BU: " & L22 & ")", IF(LEN(G22)-LEN(SUBSTITUTE(G22,"-",""))>=3, "Receipt: From x" & RIGHT(MID(G22, FIND("|", SUBSTITUTE(G22, "-", "|", 3)) + 1, LEN(G22)), 4) & " towards " & IF(ISBLANK(U22), L22, U22) & IF(OR(L22="Cancellation", L22="Collection"), " Apt No " & T22, "") & " (Ref: " & H22 & ") (Type: " & P22 & ") (BU: " & L22 & ") (Head: " & M22 & ")" & IF(ISBLANK(T22), "", " (Apt#: " & T22 & ")"), "Receipt: Against " & IF(ISBLANK(U22), L22, U22) & IF(OR(L22="Cancellation", L22="Collection"), " Apt No " & T22, "") & " (Ref: " & H22 & ") (Type: " & P22 & ") (BU: " & L22 & ") (Head: " & M22 & ")" & IF(ISBLANK(T22), "", " (Apt#: " & T22 & ")"))), IF(LEN(G22)-LEN(SUBSTITUTE(G22,"-",""))>=3, "Payment: To x" & RIGHT(MID(G22, FIND("|", SUBSTITUTE(G22, "-", "|", 3)) + 1, LEN(G22)), 4) & " for " & IF(ISBLANK(U22), L22, U22) & " (Ref: " & H22 & ") (Type: " & P22 & ") (BU: " & L22 & ") (Head: " & M22 & ")" & IF(ISBLANK(T22), "", " (Apt#: " & T22 & ")"), "Payment: Disbursement for " & IF(ISBLANK(U22), "", IF(ISBLANK(U22), "", U22) & " ") & "(Ref: " & H22 & ") (Type: " & P22 & ") (BU: " & L22 & ") (Head: " & M22 & ")" & IF(ISBLANK(T22), "", " (Apt#: " & T22 & ")"))))) -> Fund Transfer: From YES MASTER 0264 to x2477 (Ref: ) (Type: Master to Free) (BU: Casa Romana) (Head: Internal) | Y22: 459116.78 | Z22: =Y22-K22 -> 1.78
A23: 214 | B23: =IFERROR("Q"&(INT(MOD(C23-4,12)/3)+1),"") -> Q2 | C23: =IFERROR(MONTH(DATEVALUE(D23)),"") -> 8 | D23: 04-Aug-2026 | E23: 04-Aug-2026 | G23: NEFT CR-ICIC0SF0002-POONAM K AUR-DWARKADHIS PROJECTS PRIVA-IN12621649590896 | J23: 100000 | K23: =K24+J23-I23 -> 527355 | L23: Casa Romana | M23: Collection | O23: Entry | P23: Customer Collection | Q23: Credit- no effect | T23: U-092 | V23: Adjust 31,245 On Account 68,755 | W23: =TRIM(IF(M23="Internal", IF(ISBLANK(G23), IF(LEN(G23)-LEN(SUBSTITUTE(G23,"-",""))>=3, "Fund Transfer: From x" & RIGHT(MID(G23, FIND("|", SUBSTITUTE(G23, "-", "|", 3)) + 1, LEN(G23)), 4) & " to YES MASTER 0264 (Ref: " & H23 & ") (Type: " & P23 & ") (BU: " & L23 & ") (Head: " & M23 & ")", "Fund Transfer: To YES MASTER 0264 (Ref: " & H23 & ") (Type: " & P23 & ") (BU: " & L23 & ") (Head: " & M23 & ")"), IF(LEN(G23)-LEN(SUBSTITUTE(G23,"-",""))>=3, "Fund Transfer: From YES MASTER 0264 to x" & RIGHT(MID(G23, FIND("|", SUBSTITUTE(G23, "-", "|", 3)) + 1, LEN(G23)), 4) & " (Ref: " & H23 & ") (Type: " & P23 & ") (BU: " & L23 & ") (Head: " & M23 & ")", "Fund Transfer: From YES MASTER 0264 (Ref: " & H23 & ") (Type: " & P23 & ") (BU: " & L23 & ") (Head: " & M23 & ")")), IF(NOT(ISBLANK(J23)), IF(P23="Customer Collection", "Receipt: For " & IF(ISBLANK(T23), "", "(Apt#: " & T23 & ") ") & "(Ref: " & H23 & ") (" & IF(ISNUMBER(SEARCH("NEFT",G23)), "NEFT:", IF(ISNUMBER(SEARCH("RTGS",G23)), "RTGS:", IF(ISNUMBER(SEARCH("IMPS",G23)), "IMPS:", ""))) & " " & IF(ISNUMBER(SEARCH("SOHNA ROAD", G23)), "", IFERROR(MID(G23, FIND("-", G23, FIND("-", G23) + 1) + 1, LEN(G23)), SUBSTITUTE(SUBSTITUTE(SUBSTITUTE(G23, "IMPS/", ""), "NEFT/", ""), "RTGS/", ""))) & ") (Type: " & P23 & ") (BU: " & L23 & ")", IF(LEN(G23)-LEN(SUBSTITUTE(G23,"-",""))>=3, "Receipt: From x" & RIGHT(MID(G23, FIND("|", SUBSTITUTE(G23, "-", "|", 3)) + 1, LEN(G23)), 4) & " towards " & IF(ISBLANK(U23), L23, U23) & IF(OR(L23="Cancellation", L23="Collection"), " Apt No " & T23, "") & " (Ref: " & H23 & ") (Type: " & P23 & ") (BU: " & L23 & ") (Head: " & M23 & ")" & IF(ISBLANK(T23), "", " (Apt#: " & T23 & ")"), "Receipt: Against " & IF(ISBLANK(U23), L23, U23) & IF(OR(L23="Cancellation", L23="Collection"), " Apt No " & T23, "") & " (Ref: " & H23 & ") (Type: " & P23 & ") (BU: " & L23 & ") (Head: " & M23 & ")" & IF(ISBLANK(T23), "", " (Apt#: " & T23 & ")"))), IF(LEN(G23)-LEN(SUBSTITUTE(G23,"-",""))>=3, "Payment: To x" & RIGHT(MID(G23, FIND("|", SUBSTITUTE(G23, "-", "|", 3)) + 1, LEN(G23)), 4) & " for " & IF(ISBLANK(U23), L23, U23) & " (Ref: " & H23 & ") (Type: " & P23 & ") (BU: " & L23 & ") (Head: " & M23 & ")" & IF(ISBLANK(T23), "", " (Apt#: " & T23 & ")"), "Payment: Disbursement for " & IF(ISBLANK(U23), "", IF(ISBLANK(U23), "", U23) & " ") & "(Ref: " & H23 & ") (Type: " & P23 & ") (BU: " & L23 & ") (Head: " & M23 & ")" & IF(ISBLANK(T23), "", " (Apt#: " & T23 & ")"))))) -> Receipt: For (Apt#: U-092) (Ref: ) (NEFT: POONAM K AUR-DWARKADHIS PROJECTS PRIVA-IN12621649590896) (Type: Customer Collection) (BU: Casa Romana) | Y23: 527356.78 | Z23: =Y23-K23 -> 1.78 | AB23: ok
A24: 213 | B24: =IFERROR("Q"&(INT(MOD(C24-4,12)/3)+1),"") -> Q2 | C24: =IFERROR(MONTH(DATEVALUE(D24)),"") -> 8 | D24: 04-Aug-2026 | E24: 04-Aug-2026 | G24: IMPS/REUBEN MUKHERJEE U/G S OUMEN MUKHERJEE/XXX9384/RRN:621655423714/HDFC BANK | J24: 170820 | K24: =K25+J24-I24 -> 427355 | L24: Casa Romana | M24: Collection | O24: Entry | P24: Customer Collection | Q24: Credit- no effect | T24: T-103 | V24: Adjust 117,160 On Account 53660 As on | W24: =TRIM(IF(M24="Internal", IF(ISBLANK(G24), IF(LEN(G24)-LEN(SUBSTITUTE(G24,"-",""))>=3, "Fund Transfer: From x" & RIGHT(MID(G24, FIND("|", SUBSTITUTE(G24, "-", "|", 3)) + 1, LEN(G24)), 4) & " to YES MASTER 0264 (Ref: " & H24 & ") (Type: " & P24 & ") (BU: " & L24 & ") (Head: " & M24 & ")", "Fund Transfer: To YES MASTER 0264 (Ref: " & H24 & ") (Type: " & P24 & ") (BU: " & L24 & ") (Head: " & M24 & ")"), IF(LEN(G24)-LEN(SUBSTITUTE(G24,"-",""))>=3, "Fund Transfer: From YES MASTER 0264 to x" & RIGHT(MID(G24, FIND("|", SUBSTITUTE(G24, "-", "|", 3)) + 1, LEN(G24)), 4) & " (Ref: " & H24 & ") (Type: " & P24 & ") (BU: " & L24 & ") (Head: " & M24 & ")", "Fund Transfer: From YES MASTER 0264 (Ref: " & H24 & ") (Type: " & P24 & ") (BU: " & L24 & ") (Head: " & M24 & ")")), IF(NOT(ISBLANK(J24)), IF(P24="Customer Collection", "Receipt: For " & IF(ISBLANK(T24), "", "(Apt#: " & T24 & ") ") & "(Ref: " & H24 & ") (" & IF(ISNUMBER(SEARCH("NEFT",G24)), "NEFT:", IF(ISNUMBER(SEARCH("RTGS",G24)), "RTGS:", IF(ISNUMBER(SEARCH("IMPS",G24)), "IMPS:", ""))) & " " & IF(ISNUMBER(SEARCH("SOHNA ROAD", G24)), "", IFERROR(MID(G24, FIND("-", G24, FIND("-", G24) + 1) + 1, LEN(G24)), SUBSTITUTE(SUBSTITUTE(SUBSTITUTE(G24, "IMPS/", ""), "NEFT/", ""), "RTGS/", ""))) & ") (Type: " & P24 & ") (BU: " & L24 & ")", IF(LEN(G24)-LEN(SUBSTITUTE(G24,"-",""))>=3, "Receipt: From x" & RIGHT(MID(G24, FIND("|", SUBSTITUTE(G24, "-", "|", 3)) + 1, LEN(G24)), 4) & " towards " & IF(ISBLANK(U24), L24, U24) & IF(OR(L24="Cancellation", L24="Collection"), " Apt No " & T24, "") & " (Ref: " & H24 & ") (Type: " & P24 & ") (BU: " & L24 & ") (Head: " & M24 & ")" & IF(ISBLANK(T24), "", " (Apt#: " & T24 & ")"), "Receipt: Against " & IF(ISBLANK(U24), L24, U24) & IF(OR(L24="Cancellation", L24="Collection"), " Apt No " & T24, "") & " (Ref: " & H24 & ") (Type: " & P24 & ") (BU: " & L24 & ") (Head: " & M24 & ")" & IF(ISBLANK(T24), "", " (Apt#: " & T24 & ")"))), IF(LEN(G24)-LEN(SUBSTITUTE(G24,"-",""))>=3, "Payment: To x" & RIGHT(MID(G24, FIND("|", SUBSTITUTE(G24, "-", "|", 3)) + 1, LEN(G24)), 4) & " for " & IF(ISBLANK(U24), L24, U24) & " (Ref: " & H24 & ") (Type: " & P24 & ") (BU: " & L24 & ") (Head: " & M24 & ")" & IF(ISBLANK(T24), "", " (Apt#: " & T24 & ")"), "Payment: Disbursement for " & IF(ISBLANK(U24), "", IF(ISBLANK(U24), "", U24) & " ") & "(Ref: " & H24 & ") (Type: " & P24 & ") (BU: " & L24 & ") (Head: " & M24 & ")" & IF(ISBLANK(T24), "", " (Apt#: " & T24 & ")"))))) -> Receipt: For (Apt#: T-103) (Ref: ) (IMPS: REUBEN MUKHERJEE U/G S OUMEN MUKHERJEE/XXX9384/RRN:621655423714/HDFC BANK) (Type: Customer Collection) (BU: Casa Romana) | Y24: 427356.78 | Z24: =Y24-K24 -> 1.78 | AB24: ok
A25: 212 | B25: =IFERROR("Q"&(INT(MOD(C25-4,12)/3)+1),"") -> Q2 | C25: =IFERROR(MONTH(DATEVALUE(D25)),"") -> 8 | D25: 04-Aug-2026 | E25: 04-Aug-2026 | G25: NEFT CR-ICIC0SF0002- SANJAY YADAV-DWAR KADHIS PROJECTS IVA-IN12621649540991 | H25: YES0N6216966268000 | J25: 100000 | K25: =K26+J25-I25 -> 256535 | L25: Casa Romana | M25: Collection | O25: Entry | P25: Customer Collection | Q25: Credit- no effect | T25: P-054 | V25: On Account | W25: =TRIM(IF(M25="Internal", IF(ISBLANK(G25), IF(LEN(G25)-LEN(SUBSTITUTE(G25,"-",""))>=3, "Fund Transfer: From x" & RIGHT(MID(G25, FIND("|", SUBSTITUTE(G25, "-", "|", 3)) + 1, LEN(G25)), 4) & " to YES MASTER 0264 (Ref: " & H25 & ") (Type: " & P25 & ") (BU: " & L25 & ") (Head: " & M25 & ")", "Fund Transfer: To YES MASTER 0264 (Ref: " & H25 & ") (Type: " & P25 & ") (BU: " & L25 & ") (Head: " & M25 & ")"), IF(LEN(G25)-LEN(SUBSTITUTE(G25,"-",""))>=3, "Fund Transfer: From YES MASTER 0264 to x" & RIGHT(MID(G25, FIND("|", SUBSTITUTE(G25, "-", "|", 3)) + 1, LEN(G25)), 4) & " (Ref: " & H25 & ") (Type: " & P25 & ") (BU: " & L25 & ") (Head: " & M25 & ")", "Fund Transfer: From YES MASTER 0264 (Ref: " & H25 & ") (Type: " & P25 & ") (BU: " & L25 & ") (Head: " & M25 & ")")), IF(NOT(ISBLANK(J25)), IF(P25="Customer Collection", "Receipt: For " & IF(ISBLANK(T25), "", "(Apt#: " & T25 & ") ") & "(Ref: " & H25 & ") (" & IF(ISNUMBER(SEARCH("NEFT",G25)), "NEFT:", IF(ISNUMBER(SEARCH("RTGS",G25)), "RTGS:", IF(ISNUMBER(SEARCH("IMPS",G25)), "IMPS:", ""))) & " " & IF(ISNUMBER(SEARCH("SOHNA ROAD", G25)), "", IFERROR(MID(G25, FIND("-", G25, FIND("-", G25) + 1) + 1, LEN(G25)), SUBSTITUTE(SUBSTITUTE(SUBSTITUTE(G25, "IMPS/", ""), "NEFT/", ""), "RTGS/", ""))) & ") (Type: " & P25 & ") (BU: " & L25 & ")", IF(LEN(G25)-LEN(SUBSTITUTE(G25,"-",""))>=3, "Receipt: From x" & RIGHT(MID(G25, FIND("|", SUBSTITUTE(G25, "-", "|", 3)) + 1, LEN(G25)), 4) & " towards " & IF(ISBLANK(U25), L25, U25) & IF(OR(L25="Cancellation", L25="Collection"), " Apt No " & T25, "") & " (Ref: " & H25 & ") (Type: " & P25 & ") (BU: " & L25 & ") (Head: " & M25 & ")" & IF(ISBLANK(T25), "", " (Apt#: " & T25 & ")"), "Receipt: Against " & IF(ISBLANK(U25), L25, U25) & IF(OR(L25="Cancellation", L25="Collection"), " Apt No " & T25, "") & " (Ref: " & H25 & ") (Type: " & P25 & ") (BU: " & L25 & ") (Head: " & M25 & ")" & IF(ISBLANK(T25), "", " (Apt#: " & T25 & ")"))), IF(LEN(G25)-LEN(SUBSTITUTE(G25,"-",""))>=3, "Payment: To x" & RIGHT(MID(G25, FIND("|", SUBSTITUTE(G25, "-", "|", 3)) + 1, LEN(G25)), 4) & " for " & IF(ISBLANK(U25), L25, U25) & " (Ref: " & H25 & ") (Type: " & P25 & ") (BU: " & L25 & ") (Head: " & M25 & ")" & IF(ISBLANK(T25), "", " (Apt#: " & T25 & ")"), "Payment: Disbursement for " & IF(ISBLANK(U25), "", IF(ISBLANK(U25), "", U25) & " ") & "(Ref: " & H25 & ") (Type: " & P25 & ") (BU: " & L25 & ") (Head: " & M25 & ")" & IF(ISBLANK(T25), "", " (Apt#: " & T25 & ")"))))) -> Receipt: For (Apt#: P-054) (Ref: YES0N6216966268000) (NEFT: SANJAY YADAV-DWAR KADHIS PROJECTS IVA-IN12621649540991) (Type: Customer Collection) (BU: Casa Romana) | X25: 0.05 | Y25: 256536.78 | Z25: =Y25-K25 -> 1.78 | AB25: ok
A26: 211 | B26: =IFERROR("Q"&(INT(MOD(C26-4,12)/3)+1),"") -> Q2 | C26: =IFERROR(MONTH(DATEVALUE(D26)),"") -> 8 | D26: 04-Aug-2026 | E26: 04-Aug-2026 | G26: IMPS/AMITKUMAR/X XX3986/RRN:62161 4493753/AXIS BANK | H26: YBP6216640374289 | J26: 10600 | K26: =K27+J26-I26 -> 156535 | L26: Casa Romana | M26: Collection | O26: Entry | P26: Customer Collection | Q26: Credit- no effect | T26: R-064 | V26: On Account | W26: =TRIM(IF(M26="Internal", IF(ISBLANK(G26), IF(LEN(G26)-LEN(SUBSTITUTE(G26,"-",""))>=3, "Fund Transfer: From x" & RIGHT(MID(G26, FIND("|", SUBSTITUTE(G26, "-", "|", 3)) + 1, LEN(G26)), 4) & " to YES MASTER 0264 (Ref: " & H26 & ") (Type: " & P26 & ") (BU: " & L26 & ") (Head: " & M26 & ")", "Fund Transfer: To YES MASTER 0264 (Ref: " & H26 & ") (Type: " & P26 & ") (BU: " & L26 & ") (Head: " & M26 & ")"), IF(LEN(G26)-LEN(SUBSTITUTE(G26,"-",""))>=3, "Fund Transfer: From YES MASTER 0264 to x" & RIGHT(MID(G26, FIND("|", SUBSTITUTE(G26, "-", "|", 3)) + 1, LEN(G26)), 4) & " (Ref: " & H26 & ") (Type: " & P26 & ") (BU: " & L26 & ") (Head: " & M26 & ")", "Fund Transfer: From YES MASTER 0264 (Ref: " & H26 & ") (Type: " & P26 & ") (BU: " & L26 & ") (Head: " & M26 & ")")), IF(NOT(ISBLANK(J26)), IF(P26="Customer Collection", "Receipt: For " & IF(ISBLANK(T26), "", "(Apt#: " & T26 & ") ") & "(Ref: " & H26 & ") (" & IF(ISNUMBER(SEARCH("NEFT",G26)), "NEFT:", IF(ISNUMBER(SEARCH("RTGS",G26)), "RTGS:", IF(ISNUMBER(SEARCH("IMPS",G26)), "IMPS:", ""))) & " " & IF(ISNUMBER(SEARCH("SOHNA ROAD", G26)), "", IFERROR(MID(G26, FIND("-", G26, FIND("-", G26) + 1) + 1, LEN(G26)), SUBSTITUTE(SUBSTITUTE(SUBSTITUTE(G26, "IMPS/", ""), "NEFT/", ""), "RTGS/", ""))) & ") (Type: " & P26 & ") (BU: " & L26 & ")", IF(LEN(G26)-LEN(SUBSTITUTE(G26,"-",""))>=3, "Receipt: From x" & RIGHT(MID(G26, FIND("|", SUBSTITUTE(G26, "-", "|", 3)) + 1, LEN(G26)), 4) & " towards " & IF(ISBLANK(U26), L26, U26) & IF(OR(L26="Cancellation", L26="Collection"), " Apt No " & T26, "") & " (Ref: " & H26 & ") (Type: " & P26 & ") (BU: " & L26 & ") (Head: " & M26 & ")" & IF(ISBLANK(T26), "", " (Apt#: " & T26 & ")"), "Receipt: Against " & IF(ISBLANK(U26), L26, U26) & IF(OR(L26="Cancellation", L26="Collection"), " Apt No " & T26, "") & " (Ref: " & H26 & ") (Type: " & P26 & ") (BU: " & L26 & ") (Head: " & M26 & ")" & IF(ISBLANK(T26), "", " (Apt#: " & T26 & ")"))), IF(LEN(G26)-LEN(SUBSTITUTE(G26,"-",""))>=3, "Payment: To x" & RIGHT(MID(G26, FIND("|", SUBSTITUTE(G26, "-", "|", 3)) + 1, LEN(G26)), 4) & " for " & IF(ISBLANK(U26), L26, U26) & " (Ref: " & H26 & ") (Type: " & P26 & ") (BU: " & L26 & ") (Head: " & M26 & ")" & IF(ISBLANK(T26), "", " (Apt#: " & T26 & ")"), "Payment: Disbursement for " & IF(ISBLANK(U26), "", IF(ISBLANK(U26), "", U26) & " ") & "(Ref: " & H26 & ") (Type: " & P26 & ") (BU: " & L26 & ") (Head: " & M26 & ")" & IF(ISBLANK(T26), "", " (Apt#: " & T26 & ")"))))) -> Receipt: For (Apt#: R-064) (Ref: YBP6216640374289) (IMPS: AMITKUMAR/X XX3986/RRN:62161 4493753/AXIS BANK) (Type: Customer Collection) (BU: Casa Romana) | X26: 0.01 | Y26: 156536.78 | Z26: =Y26-K26 -> 1.78 | AB26: ok
A27: 210 | B27: =IFERROR("Q"&(INT(MOD(C27-4,12)/3)+1),"") -> Q2 | C27: =IFERROR(MONTH(DATEVALUE(D27)),"") -> 8 | D27: 04-Aug-2026 | E27: 04-Aug-2026 | G27: NEFT CR-HDFC000000 1-LT JITENDRA KUMAR AGARWAL-DWARKA DHIS PROJECTS PRIV A-HDFCH01168958353 | H27: YES0N6216953371600 | J27: 91867 | K27: =K28+J27-I27 -> 145935 | L27: Casa Romana | M27: Collection | O27: Entry | P27: Customer Collection | Q27: Credit- no effect | T27: T-101 | V27: Adjust | W27: =TRIM(IF(M27="Internal", IF(ISBLANK(G27), IF(LEN(G27)-LEN(SUBSTITUTE(G27,"-",""))>=3, "Fund Transfer: From x" & RIGHT(MID(G27, FIND("|", SUBSTITUTE(G27, "-", "|", 3)) + 1, LEN(G27)), 4) & " to YES MASTER 0264 (Ref: " & H27 & ") (Type: " & P27 & ") (BU: " & L27 & ") (Head: " & M27 & ")", "Fund Transfer: To YES MASTER 0264 (Ref: " & H27 & ") (Type: " & P27 & ") (BU: " & L27 & ") (Head: " & M27 & ")"), IF(LEN(G27)-LEN(SUBSTITUTE(G27,"-",""))>=3, "Fund Transfer: From YES MASTER 0264 to x" & RIGHT(MID(G27, FIND("|", SUBSTITUTE(G27, "-", "|", 3)) + 1, LEN(G27)), 4) & " (Ref: " & H27 & ") (Type: " & P27 & ") (BU: " & L27 & ") (Head: " & M27 & ")", "Fund Transfer: From YES MASTER 0264 (Ref: " & H27 & ") (Type: " & P27 & ") (BU: " & L27 & ") (Head: " & M27 & ")")), IF(NOT(ISBLANK(J27)), IF(P27="Customer Collection", "Receipt: For " & IF(ISBLANK(T27), "", "(Apt#: " & T27 & ") ") & "(Ref: " & H27 & ") (" & IF(ISNUMBER(SEARCH("NEFT",G27)), "NEFT:", IF(ISNUMBER(SEARCH("RTGS",G27)), "RTGS:", IF(ISNUMBER(SEARCH("IMPS",G27)), "IMPS:", ""))) & " " & IF(ISNUMBER(SEARCH("SOHNA ROAD", G27)), "", IFERROR(MID(G27, FIND("-", G27, FIND("-", G27) + 1) + 1, LEN(G27)), SUBSTITUTE(SUBSTITUTE(SUBSTITUTE(G27, "IMPS/", ""), "NEFT/", ""), "RTGS/", ""))) & ") (Type: " & P27 & ") (BU: " & L27 & ")", IF(LEN(G27)-LEN(SUBSTITUTE(G27,"-",""))>=3, "Receipt: From x" & RIGHT(MID(G27, FIND("|", SUBSTITUTE(G27, "-", "|", 3)) + 1, LEN(G27)), 4) & " towards " & IF(ISBLANK(U27), L27, U27) & IF(OR(L27="Cancellation", L27="Collection"), " Apt No " & T27, "") & " (Ref: " & H27 & ") (Type: " & P27 & ") (BU: " & L27 & ") (Head: " & M27 & ")" & IF(ISBLANK(T27), "", " (Apt#: " & T27 & ")"), "Receipt: Against " & IF(ISBLANK(U27), L27, U27) & IF(OR(L27="Cancellation", L27="Collection"), " Apt No " & T27, "") & " (Ref: " & H27 & ") (Type: " & P27 & ") (BU: " & L27 & ") (Head: " & M27 & ")" & IF(ISBLANK(T27), "", " (Apt#: " & T27 & ")"))), IF(LEN(G27)-LEN(SUBSTITUTE(G27,"-",""))>=3, "Payment: To x" & RIGHT(MID(G27, FIND("|", SUBSTITUTE(G27, "-", "|", 3)) + 1, LEN(G27)), 4) & " for " & IF(ISBLANK(U27), L27, U27) & " (Ref: " & H27 & ") (Type: " & P27 & ") (BU: " & L27 & ") (Head: " & M27 & ")" & IF(ISBLANK(T27), "", " (Apt#: " & T27 & ")"), "Payment: Disbursement for " & IF(ISBLANK(U27), "", IF(ISBLANK(U27), "", U27) & " ") & "(Ref: " & H27 & ") (Type: " & P27 & ") (BU: " & L27 & ") (Head: " & M27 & ")" & IF(ISBLANK(T27), "", " (Apt#: " & T27 & ")"))))) -> Receipt: For (Apt#: T-101) (Ref: YES0N6216953371600) (NEFT: LT JITENDRA KUMAR AGARWAL-DWARKA DHIS PROJECTS PRIV A-HDFCH01168958353) (Type: Customer Collection) (BU: Casa Romana) | Y27: 145936.78 | Z27: =Y27-K27 -> 1.78 | AB27: ok
A28: 209 | B28: =IFERROR("Q"&(INT(MOD(C28-4,12)/3)+1),"") -> Q2 | C28: =IFERROR(MONTH(DATEVALUE(D28)),"") -> 8 | D28: 04-Aug-2026 | E28: 04-Aug-2026 | G28: YIB-TPT-DWARKADHIS PROJECTS PVT LTD-INTERN AL-045563400002477 | H28: YESME6216001852600 | I28: 103199 | K28: =K29+J28-I28 -> 54068 | L28: Casa Romana | M28: Internal | O28: Entry | P28: Master to Free | Q28: Internal transfer | W28: =TRIM(IF(M28="Internal", IF(ISBLANK(G28), IF(LEN(G28)-LEN(SUBSTITUTE(G28,"-",""))>=3, "Fund Transfer: From x" & RIGHT(MID(G28, FIND("|", SUBSTITUTE(G28, "-", "|", 3)) + 1, LEN(G28)), 4) & " to YES MASTER 0264 (Ref: " & H28 & ") (Type: " & P28 & ") (BU: " & L28 & ") (Head: " & M28 & ")", "Fund Transfer: To YES MASTER 0264 (Ref: " & H28 & ") (Type: " & P28 & ") (BU: " & L28 & ") (Head: " & M28 & ")"), IF(LEN(G28)-LEN(SUBSTITUTE(G28,"-",""))>=3, "Fund Transfer: From YES MASTER 0264 to x" & RIGHT(MID(G28, FIND("|", SUBSTITUTE(G28, "-", "|", 3)) + 1, LEN(G28)), 4) & " (Ref: " & H28 & ") (Type: " & P28 & ") (BU: " & L28 & ") (Head: " & M28 & ")", "Fund Transfer: From YES MASTER 0264 (Ref: " & H28 & ") (Type: " & P28 & ") (BU: " & L28 & ") (Head: " & M28 & ")")), IF(NOT(ISBLANK(J28)), IF(P28="Customer Collection", "Receipt: For " & IF(ISBLANK(T28), "", "(Apt#: " & T28 & ") ") & "(Ref: " & H28 & ") (" & IF(ISNUMBER(SEARCH("NEFT",G28)), "NEFT:", IF(ISNUMBER(SEARCH("RTGS",G28)), "RTGS:", IF(ISNUMBER(SEARCH("IMPS",G28)), "IMPS:", ""))) & " " & IF(ISNUMBER(SEARCH("SOHNA ROAD", G28)), "", IFERROR(MID(G28, FIND("-", G28, FIND("-", G28) + 1) + 1, LEN(G28)), SUBSTITUTE(SUBSTITUTE(SUBSTITUTE(G28, "IMPS/", ""), "NEFT/", ""), "RTGS/", ""))) & ") (Type: " & P28 & ") (BU: " & L28 & ")", IF(LEN(G28)-LEN(SUBSTITUTE(G28,"-",""))>=3, "Receipt: From x" & RIGHT(MID(G28, FIND("|", SUBSTITUTE(G28, "-", "|", 3)) + 1, LEN(G28)), 4) & " towards " & IF(ISBLANK(U28), L28, U28) & IF(OR(L28="Cancellation", L28="Collection"), " Apt No " & T28, "") & " (Ref: " & H28 & ") (Type: " & P28 & ") (BU: " & L28 & ") (Head: " & M28 & ")" & IF(ISBLANK(T28), "", " (Apt#: " & T28 & ")"), "Receipt: Against " & IF(ISBLANK(U28), L28, U28) & IF(OR(L28="Cancellation", L28="Collection"), " Apt No " & T28, "") & " (Ref: " & H28 & ") (Type: " & P28 & ") (BU: " & L28 & ") (Head: " & M28 & ")" & IF(ISBLANK(T28), "", " (Apt#: " & T28 & ")"))), IF(LEN(G28)-LEN(SUBSTITUTE(G28,"-",""))>=3, "Payment: To x" & RIGHT(MID(G28, FIND("|", SUBSTITUTE(G28, "-", "|", 3)) + 1, LEN(G28)), 4) & " for " & IF(ISBLANK(U28), L28, U28) & " (Ref: " & H28 & ") (Type: " & P28 & ") (BU: " & L28 & ") (Head: " & M28 & ")" & IF(ISBLANK(T28), "", " (Apt#: " & T28 & ")"), "Payment: Disbursement for " & IF(ISBLANK(U28), "", IF(ISBLANK(U28), "", U28) & " ") & "(Ref: " & H28 & ") (Type: " & P28 & ") (BU: " & L28 & ") (Head: " & M28 & ")" & IF(ISBLANK(T28), "", " (Apt#: " & T28 & ")"))))) -> Fund Transfer: From YES MASTER 0264 to x2477 (Ref: YESME6216001852600) (Type: Master to Free) (BU: Casa Romana) (Head: Internal) | Y28: 54069.78 | Z28: =Y28-K28 -> 1.78 | AB28: ok
A29: 208 | B29: =IFERROR("Q"&(INT(MOD(C29-4,12)/3)+1),"") -> Q2 | C29: =IFERROR(MONTH(DATEVALUE(D29)),"") -> 8 | D29: 04-Aug-2026 | E29: 04-Aug-2026 | G29: YIB-TPT-DWARKADHIS OJECTS PRIVATE LIMITED -INTERNAL-045563200000377 | H29: YESME6216001852500 | I29: 240798 | K29: =K30+J29-I29 -> 157267 | L29: Casa Romana | M29: Internal | O29: Entry | P29: Master 2 RERA | Q29: Internal transfer | W29: =TRIM(IF(M29="Internal", IF(ISBLANK(G29), IF(LEN(G29)-LEN(SUBSTITUTE(G29,"-",""))>=3, "Fund Transfer: From x" & RIGHT(MID(G29, FIND("|", SUBSTITUTE(G29, "-", "|", 3)) + 1, LEN(G29)), 4) & " to YES MASTER 0264 (Ref: " & H29 & ") (Type: " & P29 & ") (BU: " & L29 & ") (Head: " & M29 & ")", "Fund Transfer: To YES MASTER 0264 (Ref: " & H29 & ") (Type: " & P29 & ") (BU: " & L29 & ") (Head: " & M29 & ")"), IF(LEN(G29)-LEN(SUBSTITUTE(G29,"-",""))>=3, "Fund Transfer: From YES MASTER 0264 to x" & RIGHT(MID(G29, FIND("|", SUBSTITUTE(G29, "-", "|", 3)) + 1, LEN(G29)), 4) & " (Ref: " & H29 & ") (Type: " & P29 & ") (BU: " & L29 & ") (Head: " & M29 & ")", "Fund Transfer: From YES MASTER 0264 (Ref: " & H29 & ") (Type: " & P29 & ") (BU: " & L29 & ") (Head: " & M29 & ")")), IF(NOT(ISBLANK(J29)), IF(P29="Customer Collection", "Receipt: For " & IF(ISBLANK(T29), "", "(Apt#: " & T29 & ") ") & "(Ref: " & H29 & ") (" & IF(ISNUMBER(SEARCH("NEFT",G29)), "NEFT:", IF(ISNUMBER(SEARCH("RTGS",G29)), "RTGS:", IF(ISNUMBER(SEARCH("IMPS",G29)), "IMPS:", ""))) & " " & IF(ISNUMBER(SEARCH("SOHNA ROAD", G29)), "", IFERROR(MID(G29, FIND("-", G29, FIND("-", G29) + 1) + 1, LEN(G29)), SUBSTITUTE(SUBSTITUTE(SUBSTITUTE(G29, "IMPS/", ""), "NEFT/", ""), "RTGS/", ""))) & ") (Type: " & P29 & ") (BU: " & L29 & ")", IF(LEN(G29)-LEN(SUBSTITUTE(G29,"-",""))>=3, "Receipt: From x" & RIGHT(MID(G29, FIND("|", SUBSTITUTE(G29, "-", "|", 3)) + 1, LEN(G29)), 4) & " towards " & IF(ISBLANK(U29), L29, U29) & IF(OR(L29="Cancellation", L29="Collection"), " Apt No " & T29, "") & " (Ref: " & H29 & ") (Type: " & P29 & ") (BU: " & L29 & ") (Head: " & M29 & ")" & IF(ISBLANK(T29), "", " (Apt#: " & T29 & ")"), "Receipt: Against " & IF(ISBLANK(U29), L29, U29) & IF(OR(L29="Cancellation", L29="Collection"), " Apt No " & T29, "") & " (Ref: " & H29 & ") (Type: " & P29 & ") (BU: " & L29 & ") (Head: " & M29 & ")" & IF(ISBLANK(T29), "", " (Apt#: " & T29 & ")"))), IF(LEN(G29)-LEN(SUBSTITUTE(G29,"-",""))>=3, "Payment: To x" & RIGHT(MID(G29, FIND("|", SUBSTITUTE(G29, "-", "|", 3)) + 1, LEN(G29)), 4) & " for " & IF(ISBLANK(U29), L29, U29) & " (Ref: " & H29 & ") (Type: " & P29 & ") (BU: " & L29 & ") (Head: " & M29 & ")" & IF(ISBLANK(T29), "", " (Apt#: " & T29 & ")"), "Payment: Disbursement for " & IF(ISBLANK(U29), "", IF(ISBLANK(U29), "", U29) & " ") & "(Ref: " & H29 & ") (Type: " & P29 & ") (BU: " & L29 & ") (Head: " & M29 & ")" & IF(ISBLANK(T29), "", " (Apt#: " & T29 & ")"))))) -> Fund Transfer: From YES MASTER 0264 to x0377 (Ref: YESME6216001852500) (Type: Master 2 RERA) (BU: Casa Romana) (Head: Internal) | Y29: 157268.78 | Z29: =Y29-K29 -> 1.78 | AB29: ok
A30: 207 | B30: =IFERROR("Q"&(INT(MOD(C30-4,12)/3)+1),"") -> Q2 | C30: =IFERROR(MONTH(DATEVALUE(D30)),"") -> 8 | D30: 04-Aug-2026 | E30: 04-Aug-2026 | G30: IMPS/ANJANJEET SINGH HAL/XXX5487/RRN:6216097 90512/ICICI BANK LIMITED | H30: YBP6216639920533 | J30: 25000 | K30: =K31+J30-I30 -> 398065 | L30: Casa Romana | M30: Collection | O30: Entry | P30: Customer Collection | Q30: Credit- no effect | T30: N-104 | V30: On Account | W30: =TRIM(IF(M30="Internal", IF(ISBLANK(G30), IF(LEN(G30)-LEN(SUBSTITUTE(G30,"-",""))>=3, "Fund Transfer: From x" & RIGHT(MID(G30, FIND("|", SUBSTITUTE(G30, "-", "|", 3)) + 1, LEN(G30)), 4) & " to YES MASTER 0264 (Ref: " & H30 & ") (Type: " & P30 & ") (BU: " & L30 & ") (Head: " & M30 & ")", "Fund Transfer: To YES MASTER 0264 (Ref: " & H30 & ") (Type: " & P30 & ") (BU: " & L30 & ") (Head: " & M30 & ")"), IF(LEN(G30)-LEN(SUBSTITUTE(G30,"-",""))>=3, "Fund Transfer: From YES MASTER 0264 to x" & RIGHT(MID(G30, FIND("|", SUBSTITUTE(G30, "-", "|", 3)) + 1, LEN(G30)), 4) & " (Ref: " & H30 & ") (Type: " & P30 & ") (BU: " & L30 & ") (Head: " & M30 & ")", "Fund Transfer: From YES MASTER 0264 (Ref: " & H30 & ") (Type: " & P30 & ") (BU: " & L30 & ") (Head: " & M30 & ")")), IF(NOT(ISBLANK(J30)), IF(P30="Customer Collection", "Receipt: For " & IF(ISBLANK(T30), "", "(Apt#: " & T30 & ") ") & "(Ref: " & H30 & ") (" & IF(ISNUMBER(SEARCH("NEFT",G30)), "NEFT:", IF(ISNUMBER(SEARCH("RTGS",G30)), "RTGS:", IF(ISNUMBER(SEARCH("IMPS",G30)), "IMPS:", ""))) & " " & IF(ISNUMBER(SEARCH("SOHNA ROAD", G30)), "", IFERROR(MID(G30, FIND("-", G30, FIND("-", G30) + 1) + 1, LEN(G30)), SUBSTITUTE(SUBSTITUTE(SUBSTITUTE(G30, "IMPS/", ""), "NEFT/", ""), "RTGS/", ""))) & ") (Type: " & P30 & ") (BU: " & L30 & ")", IF(LEN(G30)-LEN(SUBSTITUTE(G30,"-",""))>=3, "Receipt: From x" & RIGHT(MID(G30, FIND("|", SUBSTITUTE(G30, "-", "|", 3)) + 1, LEN(G30)), 4) & " towards " & IF(ISBLANK(U30), L30, U30) & IF(OR(L30="Cancellation", L30="Collection"), " Apt No " & T30, "") & " (Ref: " & H30 & ") (Type: " & P30 & ") (BU: " & L30 & ") (Head: " & M30 & ")" & IF(ISBLANK(T30), "", " (Apt#: " & T30 & ")"), "Receipt: Against " & IF(ISBLANK(U30), L30, U30) & IF(OR(L30="Cancellation", L30="Collection"), " Apt No " & T30, "") & " (Ref: " & H30 & ") (Type: " & P30 & ") (BU: " & L30 & ") (Head: " & M30 & ")" & IF(ISBLANK(T30), "", " (Apt#: " & T30 & ")"))), IF(LEN(G30)-LEN(SUBSTITUTE(G30,"-",""))>=3, "Payment: To x" & RIGHT(MID(G30, FIND("|", SUBSTITUTE(G30, "-", "|", 3)) + 1, LEN(G30)), 4) & " for " & IF(ISBLANK(U30), L30, U30) & " (Ref: " & H30 & ") (Type: " & P30 & ") (BU: " & L30 & ") (Head: " & M30 & ")" & IF(ISBLANK(T30), "", " (Apt#: " & T30 & ")"), "Payment: Disbursement for " & IF(ISBLANK(U30), "", IF(ISBLANK(U30), "", U30) & " ") & "(Ref: " & H30 & ") (Type: " & P30 & ") (BU: " & L30 & ") (Head: " & M30 & ")" & IF(ISBLANK(T30), "", " (Apt#: " & T30 & ")"))))) -> Receipt: For (Apt#: N-104) (Ref: YBP6216639920533) (IMPS: ANJANJEET SINGH HAL/XXX5487/RRN:6216097 90512/ICICI BANK LIMITED) (Type: Customer Collection) (BU: Casa Romana) | X30: 0.01 | Y30: 398066.78 | Z30: =Y30-K30 -> 1.78 | AB30: ok
A31: 206 | B31: =IFERROR("Q"&(INT(MOD(C31-4,12)/3)+1),"") -> Q2 | C31: =IFERROR(MONTH(DATEVALUE(D31)),"") -> 8 | D31: 03-Aug-2026 | E31: 03-Aug-2026 | G31: NEFT CR-HDFC000000 1-ARUNABH SINGH-D A-HDFCH01166052298 | H31: YES0N6215790227400 | J31: 35200 | K31: =K32+J31-I31 -> 373065 | L31: Casa Romana | M31: Collection | O31: Entry | P31: Customer Collection | Q31: Credit- no effect | T31: M-118 | V31: On Account | W31: =TRIM(IF(M31="Internal", IF(ISBLANK(G31), IF(LEN(G31)-LEN(SUBSTITUTE(G31,"-",""))>=3, "Fund Transfer: From x" & RIGHT(MID(G31, FIND("|", SUBSTITUTE(G31, "-", "|", 3)) + 1, LEN(G31)), 4) & " to YES MASTER 0264 (Ref: " & H31 & ") (Type: " & P31 & ") (BU: " & L31 & ") (Head: " & M31 & ")", "Fund Transfer: To YES MASTER 0264 (Ref: " & H31 & ") (Type: " & P31 & ") (BU: " & L31 & ") (Head: " & M31 & ")"), IF(LEN(G31)-LEN(SUBSTITUTE(G31,"-",""))>=3, "Fund Transfer: From YES MASTER 0264 to x" & RIGHT(MID(G31, FIND("|", SUBSTITUTE(G31, "-", "|", 3)) + 1, LEN(G31)), 4) & " (Ref: " & H31 & ") (Type: " & P31 & ") (BU: " & L31 & ") (Head: " & M31 & ")", "Fund Transfer: From YES MASTER 0264 (Ref: " & H31 & ") (Type: " & P31 & ") (BU: " & L31 & ") (Head: " & M31 & ")")), IF(NOT(ISBLANK(J31)), IF(P31="Customer Collection", "Receipt: For " & IF(ISBLANK(T31), "", "(Apt#: " & T31 & ") ") & "(Ref: " & H31 & ") (" & IF(ISNUMBER(SEARCH("NEFT",G31)), "NEFT:", IF(ISNUMBER(SEARCH("RTGS",G31)), "RTGS:", IF(ISNUMBER(SEARCH("IMPS",G31)), "IMPS:", ""))) & " " & IF(ISNUMBER(SEARCH("SOHNA ROAD", G31)), "", IFERROR(MID(G31, FIND("-", G31, FIND("-", G31) + 1) + 1, LEN(G31)), SUBSTITUTE(SUBSTITUTE(SUBSTITUTE(G31, "IMPS/", ""), "NEFT/", ""), "RTGS/", ""))) & ") (Type: " & P31 & ") (BU: " & L31 & ")", IF(LEN(G31)-LEN(SUBSTITUTE(G31,"-",""))>=3, "Receipt: From x" & RIGHT(MID(G31, FIND("|", SUBSTITUTE(G31, "-", "|", 3)) + 1, LEN(G31)), 4) & " towards " & IF(ISBLANK(U31), L31, U31) & IF(OR(L31="Cancellation", L31="Collection"), " Apt No " & T31, "") & " (Ref: " & H31 & ") (Type: " & P31 & ") (BU: " & L31 & ") (Head: " & M31 & ")" & IF(ISBLANK(T31), "", " (Apt#: " & T31 & ")"), "Receipt: Against " & IF(ISBLANK(U31), L31, U31) & IF(OR(L31="Cancellation", L31="Collection"), " Apt No " & T31, "") & " (Ref: " & H31 & ") (Type: " & P31 & ") (BU: " & L31 & ") (Head: " & M31 & ")" & IF(ISBLANK(T31), "", " (Apt#: " & T31 & ")"))), IF(LEN(G31)-LEN(SUBSTITUTE(G31,"-",""))>=3, "Payment: To x" & RIGHT(MID(G31, FIND("|", SUBSTITUTE(G31, "-", "|", 3)) + 1, LEN(G31)), 4) & " for " & IF(ISBLANK(U31), L31, U31) & " (Ref: " & H31 & ") (Type: " & P31 & ") (BU: " & L31 & ") (Head: " & M31 & ")" & IF(ISBLANK(T31), "", " (Apt#: " & T31 & ")"), "Payment: Disbursement for " & IF(ISBLANK(U31), "", IF(ISBLANK(U31), "", U31) & " ") & "(Ref: " & H31 & ") (Type: " & P31 & ") (BU: " & L31 & ") (Head: " & M31 & ")" & IF(ISBLANK(T31), "", " (Apt#: " & T31 & ")"))))) -> Receipt: For (Apt#: M-118) (Ref: YES0N6215790227400) (NEFT: ARUNABH SINGH-D A-HDFCH01166052298) (Type: Customer Collection) (BU: Casa Romana) | X31: 0.01 | Y31: 373066.78 | Z31: =Y31-K31 -> 1.78 | AB31: ok
A32: 205 | B32: =IFERROR("Q"&(INT(MOD(C32-4,12)/3)+1),"") -> Q2 | C32: =IFERROR(MONTH(DATEVALUE(D32)),"") -> 8 | D32: 03-Aug-2026 | E32: 03-Aug-2026 | G32: DWARKADHIS PROJECTS PRIV NEFT CR-HDFC000000 1-ARUNABH SINGH-D WARKADHIS PROJECTS PRIV A-HDFCH01166050774 | H32: YES0N6215789866800 | J32: 63740 | K32: =K33+J32-I32 -> 337865 | L32: Casa Romana | M32: Collection | O32: Entry | P32: Customer Collection | Q32: Credit- no effect | T32: M-118 | V32: On Account | W32: =TRIM(IF(M32="Internal", IF(ISBLANK(G32), IF(LEN(G32)-LEN(SUBSTITUTE(G32,"-",""))>=3, "Fund Transfer: From x" & RIGHT(MID(G32, FIND("|", SUBSTITUTE(G32, "-", "|", 3)) + 1, LEN(G32)), 4) & " to YES MASTER 0264 (Ref: " & H32 & ") (Type: " & P32 & ") (BU: " & L32 & ") (Head: " & M32 & ")", "Fund Transfer: To YES MASTER 0264 (Ref: " & H32 & ") (Type: " & P32 & ") (BU: " & L32 & ") (Head: " & M32 & ")"), IF(LEN(G32)-LEN(SUBSTITUTE(G32,"-",""))>=3, "Fund Transfer: From YES MASTER 0264 to x" & RIGHT(MID(G32, FIND("|", SUBSTITUTE(G32, "-", "|", 3)) + 1, LEN(G32)), 4) & " (Ref: " & H32 & ") (Type: " & P32 & ") (BU: " & L32 & ") (Head: " & M32 & ")", "Fund Transfer: From YES MASTER 0264 (Ref: " & H32 & ") (Type: " & P32 & ") (BU: " & L32 & ") (Head: " & M32 & ")")), IF(NOT(ISBLANK(J32)), IF(P32="Customer Collection", "Receipt: For " & IF(ISBLANK(T32), "", "(Apt#: " & T32 & ") ") & "(Ref: " & H32 & ") (" & IF(ISNUMBER(SEARCH("NEFT",G32)), "NEFT:", IF(ISNUMBER(SEARCH("RTGS",G32)), "RTGS:", IF(ISNUMBER(SEARCH("IMPS",G32)), "IMPS:", ""))) & " " & IF(ISNUMBER(SEARCH("SOHNA ROAD", G32)), "", IFERROR(MID(G32, FIND("-", G32, FIND("-", G32) + 1) + 1, LEN(G32)), SUBSTITUTE(SUBSTITUTE(SUBSTITUTE(G32, "IMPS/", ""), "NEFT/", ""), "RTGS/", ""))) & ") (Type: " & P32 & ") (BU: " & L32 & ")", IF(LEN(G32)-LEN(SUBSTITUTE(G32,"-",""))>=3, "Receipt: From x" & RIGHT(MID(G32, FIND("|", SUBSTITUTE(G32, "-", "|", 3)) + 1, LEN(G32)), 4) & " towards " & IF(ISBLANK(U32), L32, U32) & IF(OR(L32="Cancellation", L32="Collection"), " Apt No " & T32, "") & " (Ref: " & H32 & ") (Type: " & P32 & ") (BU: " & L32 & ") (Head: " & M32 & ")" & IF(ISBLANK(T32), "", " (Apt#: " & T32 & ")"), "Receipt: Against " & IF(ISBLANK(U32), L32, U32) & IF(OR(L32="Cancellation", L32="Collection"), " Apt No " & T32, "") & " (Ref: " & H32 & ") (Type: " & P32 & ") (BU: " & L32 & ") (Head: " & M32 & ")" & IF(ISBLANK(T32), "", " (Apt#: " & T32 & ")"))), IF(LEN(G32)-LEN(SUBSTITUTE(G32,"-",""))>=3, "Payment: To x" & RIGHT(MID(G32, FIND("|", SUBSTITUTE(G32, "-", "|", 3)) + 1, LEN(G32)), 4) & " for " & IF(ISBLANK(U32), L32, U32) & " (Ref: " & H32 & ") (Type: " & P32 & ") (BU: " & L32 & ") (Head: " & M32 & ")" & IF(ISBLANK(T32), "", " (Apt#: " & T32 & ")"), "Payment: Disbursement for " & IF(ISBLANK(U32), "", IF(ISBLANK(U32), "", U32) & " ") & "(Ref: " & H32 & ") (Type: " & P32 & ") (BU: " & L32 & ") (Head: " & M32 & ")" & IF(ISBLANK(T32), "", " (Apt#: " & T32 & ")"))))) -> Receipt: For (Apt#: M-118) (Ref: YES0N6215789866800) (NEFT: ARUNABH SINGH-D WARKADHIS PROJECTS PRIV A-HDFCH01166050774) (Type: Customer Collection) (BU: Casa Romana) | X32: 0.01 | Y32: 337866.78 | Z32: =Y32-K32 -> 1.78 | AB32: ok
A33: 204 | B33: =IFERROR("Q"&(INT(MOD(C33-4,12)/3)+1),"") -> Q2 | C33: =IFERROR(MONTH(DATEVALUE(D33)),"") -> 8 | D33: 02-Aug-2026 | E33: 02-Aug-2026 | G33: IMPS/MRS BHAVNA MAHIPAL/XX X6701/RRN:621411185223/ CANADA: 18334910559 | H33: YBP6214637582965 | J33: 145057 | K33: =K34+J33-I33 -> 274125 | L33: Casa Romana | M33: Collection | O33: Entry | P33: Customer Collection | Q33: Credit- no effect | T33: R-052 | V33: Adjust | W33: =TRIM(IF(M33="Internal", IF(ISBLANK(G33), IF(LEN(G33)-LEN(SUBSTITUTE(G33,"-",""))>=3, "Fund Transfer: From x" & RIGHT(MID(G33, FIND("|", SUBSTITUTE(G33, "-", "|", 3)) + 1, LEN(G33)), 4) & " to YES MASTER 0264 (Ref: " & H33 & ") (Type: " & P33 & ") (BU: " & L33 & ") (Head: " & M33 & ")", "Fund Transfer: To YES MASTER 0264 (Ref: " & H33 & ") (Type: " & P33 & ") (BU: " & L33 & ") (Head: " & M33 & ")"), IF(LEN(G33)-LEN(SUBSTITUTE(G33,"-",""))>=3, "Fund Transfer: From YES MASTER 0264 to x" & RIGHT(MID(G33, FIND("|", SUBSTITUTE(G33, "-", "|", 3)) + 1, LEN(G33)), 4) & " (Ref: " & H33 & ") (Type: " & P33 & ") (BU: " & L33 & ") (Head: " & M33 & ")", "Fund Transfer: From YES MASTER 0264 (Ref: " & H33 & ") (Type: " & P33 & ") (BU: " & L33 & ") (Head: " & M33 & ")")), IF(NOT(ISBLANK(J33)), IF(P33="Customer Collection", "Receipt: For " & IF(ISBLANK(T33), "", "(Apt#: " & T33 & ") ") & "(Ref: " & H33 & ") (" & IF(ISNUMBER(SEARCH("NEFT",G33)), "NEFT:", IF(ISNUMBER(SEARCH("RTGS",G33)), "RTGS:", IF(ISNUMBER(SEARCH("IMPS",G33)), "IMPS:", ""))) & " " & IF(ISNUMBER(SEARCH("SOHNA ROAD", G33)), "", IFERROR(MID(G33, FIND("-", G33, FIND("-", G33) + 1) + 1, LEN(G33)), SUBSTITUTE(SUBSTITUTE(SUBSTITUTE(G33, "IMPS/", ""), "NEFT/", ""), "RTGS/", ""))) & ") (Type: " & P33 & ") (BU: " & L33 & ")", IF(LEN(G33)-LEN(SUBSTITUTE(G33,"-",""))>=3, "Receipt: From x" & RIGHT(MID(G33, FIND("|", SUBSTITUTE(G33, "-", "|", 3)) + 1, LEN(G33)), 4) & " towards " & IF(ISBLANK(U33), L33, U33) & IF(OR(L33="Cancellation", L33="Collection"), " Apt No " & T33, "") & " (Ref: " & H33 & ") (Type: " & P33 & ") (BU: " & L33 & ") (Head: " & M33 & ")" & IF(ISBLANK(T33), "", " (Apt#: " & T33 & ")"), "Receipt: Against " & IF(ISBLANK(U33), L33, U33) & IF(OR(L33="Cancellation", L33="Collection"), " Apt No " & T33, "") & " (Ref: " & H33 & ") (Type: " & P33 & ") (BU: " & L33 & ") (Head: " & M33 & ")" & IF(ISBLANK(T33), "", " (Apt#: " & T33 & ")"))), IF(LEN(G33)-LEN(SUBSTITUTE(G33,"-",""))>=3, "Payment: To x" & RIGHT(MID(G33, FIND("|", SUBSTITUTE(G33, "-", "|", 3)) + 1, LEN(G33)), 4) & " for " & IF(ISBLANK(U33), L33, U33) & " (Ref: " & H33 & ") (Type: " & P33 & ") (BU: " & L33 & ") (Head: " & M33 & ")" & IF(ISBLANK(T33), "", " (Apt#: " & T33 & ")"), "Payment: Disbursement for " & IF(ISBLANK(U33), "", IF(ISBLANK(U33), "", U33) & " ") & "(Ref: " & H33 & ") (Type: " & P33 & ") (BU: " & L33 & ") (Head: " & M33 & ")" & IF(ISBLANK(T33), "", " (Apt#: " & T33 & ")"))))) -> Receipt: For (Apt#: R-052) (Ref: YBP6214637582965) (IMPS: MRS BHAVNA MAHIPAL/XX X6701/RRN:621411185223/ CANADA: 18334910559) (Type: Customer Collection) (BU: Casa Romana) | Y33: 274127 | Z33: =Y33-K33 -> 2 | AB33: ok
A34: 203 | B34: =IFERROR("Q"&(INT(MOD(C34-4,12)/3)+1),"") -> Q2 | C34: =IFERROR(MONTH(DATEVALUE(D34)),"") -> 8 | D34: 02-Aug-2026 | E34: 02-Aug-2026 | G34: NEFT CR-HDFC0000001-VIJAY AV-DWARKADHIS PROJECTS PVT H01164625739 | H34: YES0N6214629693100 | J34: 100000 | K34: =K35+J34-I34 -> 129068 | L34: Casa Romana | M34: Collection | O34: Entry | P34: Customer Collection | Q34: Credit- no effect | T34: P-022 | V34: Adjust | W34: =TRIM(IF(M34="Internal", IF(ISBLANK(G34), IF(LEN(G34)-LEN(SUBSTITUTE(G34,"-",""))>=3, "Fund Transfer: From x" & RIGHT(MID(G34, FIND("|", SUBSTITUTE(G34, "-", "|", 3)) + 1, LEN(G34)), 4) & " to YES MASTER 0264 (Ref: " & H34 & ") (Type: " & P34 & ") (BU: " & L34 & ") (Head: " & M34 & ")", "Fund Transfer: To YES MASTER 0264 (Ref: " & H34 & ") (Type: " & P34 & ") (BU: " & L34 & ") (Head: " & M34 & ")"), IF(LEN(G34)-LEN(SUBSTITUTE(G34,"-",""))>=3, "Fund Transfer: From YES MASTER 0264 to x" & RIGHT(MID(G34, FIND("|", SUBSTITUTE(G34, "-", "|", 3)) + 1, LEN(G34)), 4) & " (Ref: " & H34 & ") (Type: " & P34 & ") (BU: " & L34 & ") (Head: " & M34 & ")", "Fund Transfer: From YES MASTER 0264 (Ref: " & H34 & ") (Type: " & P34 & ") (BU: " & L34 & ") (Head: " & M34 & ")")), IF(NOT(ISBLANK(J34)), IF(P34="Customer Collection", "Receipt: For " & IF(ISBLANK(T34), "", "(Apt#: " & T34 & ") ") & "(Ref: " & H34 & ") (" & IF(ISNUMBER(SEARCH("NEFT",G34)), "NEFT:", IF(ISNUMBER(SEARCH("RTGS",G34)), "RTGS:", IF(ISNUMBER(SEARCH("IMPS",G34)), "IMPS:", ""))) & " " & IF(ISNUMBER(SEARCH("SOHNA ROAD", G34)), "", IFERROR(MID(G34, FIND("-", G34, FIND("-", G34) + 1) + 1, LEN(G34)), SUBSTITUTE(SUBSTITUTE(SUBSTITUTE(G34, "IMPS/", ""), "NEFT/", ""), "RTGS/", ""))) & ") (Type: " & P34 & ") (BU: " & L34 & ")", IF(LEN(G34)-LEN(SUBSTITUTE(G34,"-",""))>=3, "Receipt: From x" & RIGHT(MID(G34, FIND("|", SUBSTITUTE(G34, "-", "|", 3)) + 1, LEN(G34)), 4) & " towards " & IF(ISBLANK(U34), L34, U34) & IF(OR(L34="Cancellation", L34="Collection"), " Apt No " & T34, "") & " (Ref: " & H34 & ") (Type: " & P34 & ") (BU: " & L34 & ") (Head: " & M34 & ")" & IF(ISBLANK(T34), "", " (Apt#: " & T34 & ")"), "Receipt: Against " & IF(ISBLANK(U34), L34, U34) & IF(OR(L34="Cancellation", L34="Collection"), " Apt No " & T34, "") & " (Ref: " & H34 & ") (Type: " & P34 & ") (BU: " & L34 & ") (Head: " & M34 & ")" & IF(ISBLANK(T34), "", " (Apt#: " & T34 & ")"))), IF(LEN(G34)-LEN(SUBSTITUTE(G34,"-",""))>=3, "Payment: To x" & RIGHT(MID(G34, FIND("|", SUBSTITUTE(G34, "-", "|", 3)) + 1, LEN(G34)), 4) & " for " & IF(ISBLANK(U34), L34, U34) & " (Ref: " & H34 & ") (Type: " & P34 & ") (BU: " & L34 & ") (Head: " & M34 & ")" & IF(ISBLANK(T34), "", " (Apt#: " & T34 & ")"), "Payment: Disbursement for " & IF(ISBLANK(U34), "", IF(ISBLANK(U34), "", U34) & " ") & "(Ref: " & H34 & ") (Type: " & P34 & ") (BU: " & L34 & ") (Head: " & M34 & ")" & IF(ISBLANK(T34), "", " (Apt#: " & T34 & ")"))))) -> Receipt: For (Apt#: P-022) (Ref: YES0N6214629693100) (NEFT: VIJAY AV-DWARKADHIS PROJECTS PVT H01164625739) (Type: Customer Collection) (BU: Casa Romana) | Y34: 129070 | Z34: =Y34-K34 -> 2 | AB34: ok
A35: 202 | B35: =IFERROR("Q"&(INT(MOD(C35-4,12)/3)+1),"") -> Q2 | C35: =IFERROR(MONTH(DATEVALUE(D35)),"") -> 8 | D35: 01-Aug-2026 | E35: 01-Aug-2026 | G35: YIB-TPT-DWARKADHIS PROJECTS D-INTERNAL-045563400002477 | H35: YESME6213006789000 | I35: 20479 | K35: =K36+J35-I35 -> 29068 | L35: Casa Romana | M35: Internal | O35: Entry | P35: Master to Free | Q35: Internal transfer | W35: =TRIM(IF(M35="Internal", IF(ISBLANK(G35), IF(LEN(G35)-LEN(SUBSTITUTE(G35,"-",""))>=3, "Fund Transfer: From x" & RIGHT(MID(G35, FIND("|", SUBSTITUTE(G35, "-", "|", 3)) + 1, LEN(G35)), 4) & " to YES MASTER 0264 (Ref: " & H35 & ") (Type: " & P35 & ") (BU: " & L35 & ") (Head: " & M35 & ")", "Fund Transfer: To YES MASTER 0264 (Ref: " & H35 & ") (Type: " & P35 & ") (BU: " & L35 & ") (Head: " & M35 & ")"), IF(LEN(G35)-LEN(SUBSTITUTE(G35,"-",""))>=3, "Fund Transfer: From YES MASTER 0264 to x" & RIGHT(MID(G35, FIND("|", SUBSTITUTE(G35, "-", "|", 3)) + 1, LEN(G35)), 4) & " (Ref: " & H35 & ") (Type: " & P35 & ") (BU: " & L35 & ") (Head: " & M35 & ")", "Fund Transfer: From YES MASTER 0264 (Ref: " & H35 & ") (Type: " & P35 & ") (BU: " & L35 & ") (Head: " & M35 & ")")), IF(NOT(ISBLANK(J35)), IF(P35="Customer Collection", "Receipt: For " & IF(ISBLANK(T35), "", "(Apt#: " & T35 & ") ") & "(Ref: " & H35 & ") (" & IF(ISNUMBER(SEARCH("NEFT",G35)), "NEFT:", IF(ISNUMBER(SEARCH("RTGS",G35)), "RTGS:", IF(ISNUMBER(SEARCH("IMPS",G35)), "IMPS:", ""))) & " " & IF(ISNUMBER(SEARCH("SOHNA ROAD", G35)), "", IFERROR(MID(G35, FIND("-", G35, FIND("-", G35) + 1) + 1, LEN(G35)), SUBSTITUTE(SUBSTITUTE(SUBSTITUTE(G35, "IMPS/", ""), "NEFT/", ""), "RTGS/", ""))) & ") (Type: " & P35 & ") (BU: " & L35 & ")", IF(LEN(G35)-LEN(SUBSTITUTE(G35,"-",""))>=3, "Receipt: From x" & RIGHT(MID(G35, FIND("|", SUBSTITUTE(G35, "-", "|", 3)) + 1, LEN(G35)), 4) & " towards " & IF(ISBLANK(U35), L35, U35) & IF(OR(L35="Cancellation", L35="Collection"), " Apt No " & T35, "") & " (Ref: " & H35 & ") (Type: " & P35 & ") (BU: " & L35 & ") (Head: " & M35 & ")" & IF(ISBLANK(T35), "", " (Apt#: " & T35 & ")"), "Receipt: Against " & IF(ISBLANK(U35), L35, U35) & IF(OR(L35="Cancellation", L35="Collection"), " Apt No " & T35, "") & " (Ref: " & H35 & ") (Type: " & P35 & ") (BU: " & L35 & ") (Head: " & M35 & ")" & IF(ISBLANK(T35), "", " (Apt#: " & T35 & ")"))), IF(LEN(G35)-LEN(SUBSTITUTE(G35,"-",""))>=3, "Payment: To x" & RIGHT(MID(G35, FIND("|", SUBSTITUTE(G35, "-", "|", 3)) + 1, LEN(G35)), 4) & " for " & IF(ISBLANK(U35), L35, U35) & " (Ref: " & H35 & ") (Type: " & P35 & ") (BU: " & L35 & ") (Head: " & M35 & ")" & IF(ISBLANK(T35), "", " (Apt#: " & T35 & ")"), "Payment: Disbursement for " & IF(ISBLANK(U35), "", IF(ISBLANK(U35), "", U35) & " ") & "(Ref: " & H35 & ") (Type: " & P35 & ") (BU: " & L35 & ") (Head: " & M35 & ")" & IF(ISBLANK(T35), "", " (Apt#: " & T35 & ")"))))) -> Fund Transfer: From YES MASTER 0264 to x2477 (Ref: YESME6213006789000) (Type: Master to Free) (BU: Casa Romana) (Head: Internal) | Y35: 29070 | Z35: =Y35-K35 -> 2 | AB35: ok
A36: 201 | B36: =IFERROR("Q"&(INT(MOD(C36-4,12)/3)+1),"") -> Q2 | C36: =IFERROR(MONTH(DATEVALUE(D36)),"") -> 8 | D36: 01-Aug-2026 | E36: 01-Aug-2026 | G36: YIB-TPT-DWARKADHIS PROJECTS PRIVATE LIMITED-INTERNAL-0455632 00000377 | H36: YESME6213006852400 | I36: 47785 | K36: =K37+J36-I36 -> 49547 | L36: Casa Romana | M36: Internal | O36: Entry | P36: Master 2 RERA | Q36: Internal transfer | W36: =TRIM(IF(M36="Internal", IF(ISBLANK(G36), IF(LEN(G36)-LEN(SUBSTITUTE(G36,"-",""))>=3, "Fund Transfer: From x" & RIGHT(MID(G36, FIND("|", SUBSTITUTE(G36, "-", "|", 3)) + 1, LEN(G36)), 4) & " to YES MASTER 0264 (Ref: " & H36 & ") (Type: " & P36 & ") (BU: " & L36 & ") (Head: " & M36 & ")", "Fund Transfer: To YES MASTER 0264 (Ref: " & H36 & ") (Type: " & P36 & ") (BU: " & L36 & ") (Head: " & M36 & ")"), IF(LEN(G36)-LEN(SUBSTITUTE(G36,"-",""))>=3, "Fund Transfer: From YES MASTER 0264 to x" & RIGHT(MID(G36, FIND("|", SUBSTITUTE(G36, "-", "|", 3)) + 1, LEN(G36)), 4) & " (Ref: " & H36 & ") (Type: " & P36 & ") (BU: " & L36 & ") (Head: " & M36 & ")", "Fund Transfer: From YES MASTER 0264 (Ref: " & H36 & ") (Type: " & P36 & ") (BU: " & L36 & ") (Head: " & M36 & ")")), IF(NOT(ISBLANK(J36)), IF(P36="Customer Collection", "Receipt: For " & IF(ISBLANK(T36), "", "(Apt#: " & T36 & ") ") & "(Ref: " & H36 & ") (" & IF(ISNUMBER(SEARCH("NEFT",G36)), "NEFT:", IF(ISNUMBER(SEARCH("RTGS",G36)), "RTGS:", IF(ISNUMBER(SEARCH("IMPS",G36)), "IMPS:", ""))) & " " & IF(ISNUMBER(SEARCH("SOHNA ROAD", G36)), "", IFERROR(MID(G36, FIND("-", G36, FIND("-", G36) + 1) + 1, LEN(G36)), SUBSTITUTE(SUBSTITUTE(SUBSTITUTE(G36, "IMPS/", ""), "NEFT/", ""), "RTGS/", ""))) & ") (Type: " & P36 & ") (BU: " & L36 & ")", IF(LEN(G36)-LEN(SUBSTITUTE(G36,"-",""))>=3, "Receipt: From x" & RIGHT(MID(G36, FIND("|", SUBSTITUTE(G36, "-", "|", 3)) + 1, LEN(G36)), 4) & " towards " & IF(ISBLANK(U36), L36, U36) & IF(OR(L36="Cancellation", L36="Collection"), " Apt No " & T36, "") & " (Ref: " & H36 & ") (Type: " & P36 & ") (BU: " & L36 & ") (Head: " & M36 & ")" & IF(ISBLANK(T36), "", " (Apt#: " & T36 & ")"), "Receipt: Against " & IF(ISBLANK(U36), L36, U36) & IF(OR(L36="Cancellation", L36="Collection"), " Apt No " & T36, "") & " (Ref: " & H36 & ") (Type: " & P36 & ") (BU: " & L36 & ") (Head: " & M36 & ")" & IF(ISBLANK(T36), "", " (Apt#: " & T36 & ")"))), IF(LEN(G36)-LEN(SUBSTITUTE(G36,"-",""))>=3, "Payment: To x" & RIGHT(MID(G36, FIND("|", SUBSTITUTE(G36, "-", "|", 3)) + 1, LEN(G36)), 4) & " for " & IF(ISBLANK(U36), L36, U36) & " (Ref: " & H36 & ") (Type: " & P36 & ") (BU: " & L36 & ") (Head: " & M36 & ")" & IF(ISBLANK(T36), "", " (Apt#: " & T36 & ")"), "Payment: Disbursement for " & IF(ISBLANK(U36), "", IF(ISBLANK(U36), "", U36) & " ") & "(Ref: " & H36 & ") (Type: " & P36 & ") (BU: " & L36 & ") (Head: " & M36 & ")" & IF(ISBLANK(T36), "", " (Apt#: " & T36 & ")"))))) -> Fund Transfer: From YES MASTER 0264 to x0377 (Ref: YESME6213006852400) (Type: Master 2 RERA) (BU: Casa Romana) (Head: Internal) | Y36: 49549 | Z36: =Y36-K36 -> 2 | AB36: ok
A37: 200 | B37: =IFERROR("Q"&(INT(MOD(C37-4,12)/3)+1),"") -> Q2 | C37: =IFERROR(MONTH(DATEVALUE(D37)),"") -> 8 | D37: 01-Aug-2026 | E37: 01-Aug-2026 | G37: NEFT CR-UTIB0000057-ANKIT AR-DWARKADHIS PROJECTS A-AXOMB21302010445 | H37: YES0N6213471971500 | J37: 68264 | K37: =K38+J37-I37 -> 97332 | L37: Casa Romana | M37: Collection | O37: Entry | P37: Customer Collection | Q37: Credit- no effect | T37: R-123 | V37: Adjust | W37: =TRIM(IF(M37="Internal", IF(ISBLANK(G37), IF(LEN(G37)-LEN(SUBSTITUTE(G37,"-",""))>=3, "Fund Transfer: From x" & RIGHT(MID(G37, FIND("|", SUBSTITUTE(G37, "-", "|", 3)) + 1, LEN(G37)), 4) & " to YES MASTER 0264 (Ref: " & H37 & ") (Type: " & P37 & ") (BU: " & L37 & ") (Head: " & M37 & ")", "Fund Transfer: To YES MASTER 0264 (Ref: " & H37 & ") (Type: " & P37 & ") (BU: " & L37 & ") (Head: " & M37 & ")"), IF(LEN(G37)-LEN(SUBSTITUTE(G37,"-",""))>=3, "Fund Transfer: From YES MASTER 0264 to x" & RIGHT(MID(G37, FIND("|", SUBSTITUTE(G37, "-", "|", 3)) + 1, LEN(G37)), 4) & " (Ref: " & H37 & ") (Type: " & P37 & ") (BU: " & L37 & ") (Head: " & M37 & ")", "Fund Transfer: From YES MASTER 0264 (Ref: " & H37 & ") (Type: " & P37 & ") (BU: " & L37 & ") (Head: " & M37 & ")")), IF(NOT(ISBLANK(J37)), IF(P37="Customer Collection", "Receipt: For " & IF(ISBLANK(T37), "", "(Apt#: " & T37 & ") ") & "(Ref: " & H37 & ") (" & IF(ISNUMBER(SEARCH("NEFT",G37)), "NEFT:", IF(ISNUMBER(SEARCH("RTGS",G37)), "RTGS:", IF(ISNUMBER(SEARCH("IMPS",G37)), "IMPS:", ""))) & " " & IF(ISNUMBER(SEARCH("SOHNA ROAD", G37)), "", IFERROR(MID(G37, FIND("-", G37, FIND("-", G37) + 1) + 1, LEN(G37)), SUBSTITUTE(SUBSTITUTE(SUBSTITUTE(G37, "IMPS/", ""), "NEFT/", ""), "RTGS/", ""))) & ") (Type: " & P37 & ") (BU: " & L37 & ")", IF(LEN(G37)-LEN(SUBSTITUTE(G37,"-",""))>=3, "Receipt: From x" & RIGHT(MID(G37, FIND("|", SUBSTITUTE(G37, "-", "|", 3)) + 1, LEN(G37)), 4) & " towards " & IF(ISBLANK(U37), L37, U37) & IF(OR(L37="Cancellation", L37="Collection"), " Apt No " & T37, "") & " (Ref: " & H37 & ") (Type: " & P37 & ") (BU: " & L37 & ") (Head: " & M37 & ")" & IF(ISBLANK(T37), "", " (Apt#: " & T37 & ")"), "Receipt: Against " & IF(ISBLANK(U37), L37, U37) & IF(OR(L37="Cancellation", L37="Collection"), " Apt No " & T37, "") & " (Ref: " & H37 & ") (Type: " & P37 & ") (BU: " & L37 & ") (Head: " & M37 & ")" & IF(ISBLANK(T37), "", " (Apt#: " & T37 & ")"))), IF(LEN(G37)-LEN(SUBSTITUTE(G37,"-",""))>=3, "Payment: To x" & RIGHT(MID(G37, FIND("|", SUBSTITUTE(G37, "-", "|", 3)) + 1, LEN(G37)), 4) & " for " & IF(ISBLANK(U37), L37, U37) & " (Ref: " & H37 & ") (Type: " & P37 & ") (BU: " & L37 & ") (Head: " & M37 & ")" & IF(ISBLANK(T37), "", " (Apt#: " & T37 & ")"), "Payment: Disbursement for " & IF(ISBLANK(U37), "", IF(ISBLANK(U37), "", U37) & " ") & "(Ref: " & H37 & ") (Type: " & P37 & ") (BU: " & L37 & ") (Head: " & M37 & ")" & IF(ISBLANK(T37), "", " (Apt#: " & T37 & ")"))))) -> Receipt: For (Apt#: R-123) (Ref: YES0N6213471971500) (NEFT: ANKIT AR-DWARKADHIS PROJECTS A-AXOMB21302010445) (Type: Customer Collection) (BU: Casa Romana) | Y37: 97334 | Z37: =Y37-K37 -> 2 | AB37: ok
A38: 199 | B38: =IF(D38="","?",_xludf.IFS( MONTH(D38)<=3,"Q4", MONTH(D38)<=6,"Q1", MONTH(D38)<=9,"Q2", TRUE,"Q3" )) -> #NAME? | C38: =MONTH(D38) -> 7 | D38: 46233 | E38: 46233 | G38: YIB-TPT-Dwarkadhis Projects Pvt Ltd-internal-045563400002477 | H38: YESME6211004463500 | I38: 30000 | K38: =K39+J38-I38 -> 29068 | L38: Casa Romana | M38: Internal | O38: Entry | P38: Master to Free | Q38: Internal transfer | W38: =TRIM(IF(M38="Internal", IF(ISBLANK(G38), IF(LEN(G38)-LEN(SUBSTITUTE(G38,"-",""))>=3, "Fund Transfer: From x" & RIGHT(MID(G38, FIND("|", SUBSTITUTE(G38, "-", "|", 3)) + 1, LEN(G38)), 4) & " to YES MASTER 0264 (Ref: " & H38 & ") (Type: " & P38 & ") (BU: " & L38 & ") (Head: " & M38 & ")", "Fund Transfer: To YES MASTER 0264 (Ref: " & H38 & ") (Type: " & P38 & ") (BU: " & L38 & ") (Head: " & M38 & ")"), IF(LEN(G38)-LEN(SUBSTITUTE(G38,"-",""))>=3, "Fund Transfer: From YES MASTER 0264 to x" & RIGHT(MID(G38, FIND("|", SUBSTITUTE(G38, "-", "|", 3)) + 1, LEN(G38)), 4) & " (Ref: " & H38 & ") (Type: " & P38 & ") (BU: " & L38 & ") (Head: " & M38 & ")", "Fund Transfer: From YES MASTER 0264 (Ref: " & H38 & ") (Type: " & P38 & ") (BU: " & L38 & ") (Head: " & M38 & ")")), IF(NOT(ISBLANK(J38)), IF(P38="Customer Collection", "Receipt: For " & IF(ISBLANK(T38), "", "(Apt#: " & T38 & ") ") & "(Ref: " & H38 & ") (" & IF(ISNUMBER(SEARCH("NEFT",G38)), "NEFT:", IF(ISNUMBER(SEARCH("RTGS",G38)), "RTGS:", IF(ISNUMBER(SEARCH("IMPS",G38)), "IMPS:", ""))) & " " & IF(ISNUMBER(SEARCH("SOHNA ROAD", G38)), "", IFERROR(MID(G38, FIND("-", G38, FIND("-", G38) + 1) + 1, LEN(G38)), SUBSTITUTE(SUBSTITUTE(SUBSTITUTE(G38, "IMPS/", ""), "NEFT/", ""), "RTGS/", ""))) & ") (Type: " & P38 & ") (BU: " & L38 & ")", IF(LEN(G38)-LEN(SUBSTITUTE(G38,"-",""))>=3, "Receipt: From x" & RIGHT(MID(G38, FIND("|", SUBSTITUTE(G38, "-", "|", 3)) + 1, LEN(G38)), 4) & " towards " & IF(ISBLANK(U38), L38, U38) & IF(OR(L38="Cancellation", L38="Collection"), " Apt No " & T38, "") & " (Ref: " & H38 & ") (Type: " & P38 & ") (BU: " & L38 & ") (Head: " & M38 & ")" & IF(ISBLANK(T38), "", " (Apt#: " & T38 & ")"), "Receipt: Against " & IF(ISBLANK(U38), L38, U38) & IF(OR(L38="Cancellation", L38="Collection"), " Apt No " & T38, "") & " (Ref: " & H38 & ") (Type: " & P38 & ") (BU: " & L38 & ") (Head: " & M38 & ")" & IF(ISBLANK(T38), "", " (Apt#: " & T38 & ")"))), IF(LEN(G38)-LEN(SUBSTITUTE(G38,"-",""))>=3, "Payment: To x" & RIGHT(MID(G38, FIND("|", SUBSTITUTE(G38, "-", "|", 3)) + 1, LEN(G38)), 4) & " for " & IF(ISBLANK(U38), L38, U38) & " (Ref: " & H38 & ") (Type: " & P38 & ") (BU: " & L38 & ") (Head: " & M38 & ")" & IF(ISBLANK(T38), "", " (Apt#: " & T38 & ")"), "Payment: Disbursement for " & IF(ISBLANK(U38), "", IF(ISBLANK(U38), "", U38) & " ") & "(Ref: " & H38 & ") (Type: " & P38 & ") (BU: " & L38 & ") (Head: " & M38 & ")" & IF(ISBLANK(T38), "", " (Apt#: " & T38 & ")"))))) -> Fund Transfer: From YES MASTER 0264 to x2477 (Ref: YESME6211004463500) (Type: Master to Free) (BU: Casa Romana) (Head: Internal)
A39: 198 | B39: =IF(D39="","?",_xludf.IFS( MONTH(D39)<=3,"Q4", MONTH(D39)<=6,"Q1", MONTH(D39)<=9,"Q2", TRUE,"Q3" )) -> #NAME? | C39: =MONTH(D39) -> 7 | D39: 46233 | E39: 46233 | G39: YIB-TPT-DWARKADHIS PROJECTS PRIVATE LIMITED-internal-045563200000377 | H39: YESME6211004335200 | I39: 70000 | K39: =K40+J39-I39 -> 59068 | L39: Casa Romana | M39: Internal | O39: Entry | P39: Master 2 RERA | Q39: Internal transfer | W39: =TRIM(IF(M39="Internal", IF(ISBLANK(G39), IF(LEN(G39)-LEN(SUBSTITUTE(G39,"-",""))>=3, "Fund Transfer: From x" & RIGHT(MID(G39, FIND("|", SUBSTITUTE(G39, "-", "|", 3)) + 1, LEN(G39)), 4) & " to YES MASTER 0264 (Ref: " & H39 & ") (Type: " & P39 & ") (BU: " & L39 & ") (Head: " & M39 & ")", "Fund Transfer: To YES MASTER 0264 (Ref: " & H39 & ") (Type: " & P39 & ") (BU: " & L39 & ") (Head: " & M39 & ")"), IF(LEN(G39)-LEN(SUBSTITUTE(G39,"-",""))>=3, "Fund Transfer: From YES MASTER 0264 to x" & RIGHT(MID(G39, FIND("|", SUBSTITUTE(G39, "-", "|", 3)) + 1, LEN(G39)), 4) & " (Ref: " & H39 & ") (Type: " & P39 & ") (BU: " & L39 & ") (Head: " & M39 & ")", "Fund Transfer: From YES MASTER 0264 (Ref: " & H39 & ") (Type: " & P39 & ") (BU: " & L39 & ") (Head: " & M39 & ")")), IF(NOT(ISBLANK(J39)), IF(P39="Customer Collection", "Receipt: For " & IF(ISBLANK(T39), "", "(Apt#: " & T39 & ") ") & "(Ref: " & H39 & ") (" & IF(ISNUMBER(SEARCH("NEFT",G39)), "NEFT:", IF(ISNUMBER(SEARCH("RTGS",G39)), "RTGS:", IF(ISNUMBER(SEARCH("IMPS",G39)), "IMPS:", ""))) & " " & IF(ISNUMBER(SEARCH("SOHNA ROAD", G39)), "", IFERROR(MID(G39, FIND("-", G39, FIND("-", G39) + 1) + 1, LEN(G39)), SUBSTITUTE(SUBSTITUTE(SUBSTITUTE(G39, "IMPS/", ""), "NEFT/", ""), "RTGS/", ""))) & ") (Type: " & P39 & ") (BU: " & L39 & ")", IF(LEN(G39)-LEN(SUBSTITUTE(G39,"-",""))>=3, "Receipt: From x" & RIGHT(MID(G39, FIND("|", SUBSTITUTE(G39, "-", "|", 3)) + 1, LEN(G39)), 4) & " towards " & IF(ISBLANK(U39), L39, U39) & IF(OR(L39="Cancellation", L39="Collection"), " Apt No " & T39, "") & " (Ref: " & H39 & ") (Type: " & P39 & ") (BU: " & L39 & ") (Head: " & M39 & ")" & IF(ISBLANK(T39), "", " (Apt#: " & T39 & ")"), "Receipt: Against " & IF(ISBLANK(U39), L39, U39) & IF(OR(L39="Cancellation", L39="Collection"), " Apt No " & T39, "") & " (Ref: " & H39 & ") (Type: " & P39 & ") (BU: " & L39 & ") (Head: " & M39 & ")" & IF(ISBLANK(T39), "", " (Apt#: " & T39 & ")"))), IF(LEN(G39)-LEN(SUBSTITUTE(G39,"-",""))>=3, "Payment: To x" & RIGHT(MID(G39, FIND("|", SUBSTITUTE(G39, "-", "|", 3)) + 1, LEN(G39)), 4) & " for " & IF(ISBLANK(U39), L39, U39) & " (Ref: " & H39 & ") (Type: " & P39 & ") (BU: " & L39 & ") (Head: " & M39 & ")" & IF(ISBLANK(T39), "", " (Apt#: " & T39 & ")"), "Payment: Disbursement for " & IF(ISBLANK(U39), "", IF(ISBLANK(U39), "", U39) & " ") & "(Ref: " & H39 & ") (Type: " & P39 & ") (BU: " & L39 & ") (Head: " & M39 & ")" & IF(ISBLANK(T39), "", " (Apt#: " & T39 & ")"))))) -> Fund Transfer: From YES MASTER 0264 to x0377 (Ref: YESME6211004335200) (Type: Master 2 RERA) (BU: Casa Romana) (Head: Internal)
A40: 197 | B40: =IF(D40="","?",_xludf.IFS( MONTH(D40)<=3,"Q4", MONTH(D40)<=6,"Q1", MONTH(D40)<=9,"Q2", TRUE,"Q3" )) -> #NAME? | C40: =MONTH(D40) -> 7 | D40: 46233 | E40: 46233 | G40: POS GST | H40: SCREF01284574169 | I40: 22.5 | K40: =K41+J40-I40 -> 129068 | L40: Casa Romana | M40: Bank Charges | O40: Entry | P40: HO - Admin | Q40: Other- Others | U40: GST On Bank Charges | W40: =TRIM(IF(M40="Internal", IF(ISBLANK(G40), IF(LEN(G40)-LEN(SUBSTITUTE(G40,"-",""))>=3, "Fund Transfer: From x" & RIGHT(MID(G40, FIND("|", SUBSTITUTE(G40, "-", "|", 3)) + 1, LEN(G40)), 4) & " to YES MASTER 0264 (Ref: " & H40 & ") (Type: " & P40 & ") (BU: " & L40 & ") (Head: " & M40 & ")", "Fund Transfer: To YES MASTER 0264 (Ref: " & H40 & ") (Type: " & P40 & ") (BU: " & L40 & ") (Head: " & M40 & ")"), IF(LEN(G40)-LEN(SUBSTITUTE(G40,"-",""))>=3, "Fund Transfer: From YES MASTER 0264 to x" & RIGHT(MID(G40, FIND("|", SUBSTITUTE(G40, "-", "|", 3)) + 1, LEN(G40)), 4) & " (Ref: " & H40 & ") (Type: " & P40 & ") (BU: " & L40 & ") (Head: " & M40 & ")", "Fund Transfer: From YES MASTER 0264 (Ref: " & H40 & ") (Type: " & P40 & ") (BU: " & L40 & ") (Head: " & M40 & ")")), IF(NOT(ISBLANK(J40)), IF(P40="Customer Collection", "Receipt: For " & IF(ISBLANK(T40), "", "(Apt#: " & T40 & ") ") & "(Ref: " & H40 & ") (" & IF(ISNUMBER(SEARCH("NEFT",G40)), "NEFT:", IF(ISNUMBER(SEARCH("RTGS",G40)), "RTGS:", IF(ISNUMBER(SEARCH("IMPS",G40)), "IMPS:", ""))) & " " & IF(ISNUMBER(SEARCH("SOHNA ROAD", G40)), "", IFERROR(MID(G40, FIND("-", G40, FIND("-", G40) + 1) + 1, LEN(G40)), SUBSTITUTE(SUBSTITUTE(SUBSTITUTE(G40, "IMPS/", ""), "NEFT/", ""), "RTGS/", ""))) & ") (Type: " & P40 & ") (BU: " & L40 & ")", IF(LEN(G40)-LEN(SUBSTITUTE(G40,"-",""))>=3, "Receipt: From x" & RIGHT(MID(G40, FIND("|", SUBSTITUTE(G40, "-", "|", 3)) + 1, LEN(G40)), 4) & " towards " & IF(ISBLANK(U40), L40, U40) & IF(OR(L40="Cancellation", L40="Collection"), " Apt No " & T40, "") & " (Ref: " & H40 & ") (Type: " & P40 & ") (BU: " & L40 & ") (Head: " & M40 & ")" & IF(ISBLANK(T40), "", " (Apt#: " & T40 & ")"), "Receipt: Against " & IF(ISBLANK(U40), L40, U40) & IF(OR(L40="Cancellation", L40="Collection"), " Apt No " & T40, "") & " (Ref: " & H40 & ") (Type: " & P40 & ") (BU: " & L40 & ") (Head: " & M40 & ")" & IF(ISBLANK(T40), "", " (Apt#: " & T40 & ")"))), IF(LEN(G40)-LEN(SUBSTITUTE(G40,"-",""))>=3, "Payment: To x" & RIGHT(MID(G40, FIND("|", SUBSTITUTE(G40, "-", "|", 3)) + 1, LEN(G40)), 4) & " for " & IF(ISBLANK(U40), L40, U40) & " (Ref: " & H40 & ") (Type: " & P40 & ") (BU: " & L40 & ") (Head: " & M40 & ")" & IF(ISBLANK(T40), "", " (Apt#: " & T40 & ")"), "Payment: Disbursement for " & IF(ISBLANK(U40), "", IF(ISBLANK(U40), "", U40) & " ") & "(Ref: " & H40 & ") (Type: " & P40 & ") (BU: " & L40 & ") (Head: " & M40 & ")" & IF(ISBLANK(T40), "", " (Apt#: " & T40 & ")"))))) -> Payment: Disbursement for GST On Bank Charges (Ref: SCREF01284574169) (Type: HO - Admin) (BU: Casa Romana) (Head: Bank Charges)
A41: 196 | B41: =IF(D41="","?",_xludf.IFS( MONTH(D41)<=3,"Q4", MONTH(D41)<=6,"Q1", MONTH(D41)<=9,"Q2", TRUE,"Q3" )) -> #NAME? | C41: =MONTH(D41) -> 7 | D41: 46233 | E41: 46233 | G41: M_Jun26_SBOX_pay.ypbsm000006435_37002065 | H41: SCREF01284574169 | I41: 125 | K41: =K42+J41-I41 -> 129090.5 | L41: Casa Romana | M41: Bank Charges | O41: Entry | P41: HO - Admin | Q41: Other- Others | U41: Bank Charges Debited | W41: =TRIM(IF(M41="Internal", IF(ISBLANK(G41), IF(LEN(G41)-LEN(SUBSTITUTE(G41,"-",""))>=3, "Fund Transfer: From x" & RIGHT(MID(G41, FIND("|", SUBSTITUTE(G41, "-", "|", 3)) + 1, LEN(G41)), 4) & " to YES MASTER 0264 (Ref: " & H41 & ") (Type: " & P41 & ") (BU: " & L41 & ") (Head: " & M41 & ")", "Fund Transfer: To YES MASTER 0264 (Ref: " & H41 & ") (Type: " & P41 & ") (BU: " & L41 & ") (Head: " & M41 & ")"), IF(LEN(G41)-LEN(SUBSTITUTE(G41,"-",""))>=3, "Fund Transfer: From YES MASTER 0264 to x" & RIGHT(MID(G41, FIND("|", SUBSTITUTE(G41, "-", "|", 3)) + 1, LEN(G41)), 4) & " (Ref: " & H41 & ") (Type: " & P41 & ") (BU: " & L41 & ") (Head: " & M41 & ")", "Fund Transfer: From YES MASTER 0264 (Ref: " & H41 & ") (Type: " & P41 & ") (BU: " & L41 & ") (Head: " & M41 & ")")), IF(NOT(ISBLANK(J41)), IF(P41="Customer Collection", "Receipt: For " & IF(ISBLANK(T41), "", "(Apt#: " & T41 & ") ") & "(Ref: " & H41 & ") (" & IF(ISNUMBER(SEARCH("NEFT",G41)), "NEFT:", IF(ISNUMBER(SEARCH("RTGS",G41)), "RTGS:", IF(ISNUMBER(SEARCH("IMPS",G41)), "IMPS:", ""))) & " " & IF(ISNUMBER(SEARCH("SOHNA ROAD", G41)), "", IFERROR(MID(G41, FIND("-", G41, FIND("-", G41) + 1) + 1, LEN(G41)), SUBSTITUTE(SUBSTITUTE(SUBSTITUTE(G41, "IMPS/", ""), "NEFT/", ""), "RTGS/", ""))) & ") (Type: " & P41 & ") (BU: " & L41 & ")", IF(LEN(G41)-LEN(SUBSTITUTE(G41,"-",""))>=3, "Receipt: From x" & RIGHT(MID(G41, FIND("|", SUBSTITUTE(G41, "-", "|", 3)) + 1, LEN(G41)), 4) & " towards " & IF(ISBLANK(U41), L41, U41) & IF(OR(L41="Cancellation", L41="Collection"), " Apt No " & T41, "") & " (Ref: " & H41 & ") (Type: " & P41 & ") (BU: " & L41 & ") (Head: " & M41 & ")" & IF(ISBLANK(T41), "", " (Apt#: " & T41 & ")"), "Receipt: Against " & IF(ISBLANK(U41), L41, U41) & IF(OR(L41="Cancellation", L41="Collection"), " Apt No " & T41, "") & " (Ref: " & H41 & ") (Type: " & P41 & ") (BU: " & L41 & ") (Head: " & M41 & ")" & IF(ISBLANK(T41), "", " (Apt#: " & T41 & ")"))), IF(LEN(G41)-LEN(SUBSTITUTE(G41,"-",""))>=3, "Payment: To x" & RIGHT(MID(G41, FIND("|", SUBSTITUTE(G41, "-", "|", 3)) + 1, LEN(G41)), 4) & " for " & IF(ISBLANK(U41), L41, U41) & " (Ref: " & H41 & ") (Type: " & P41 & ") (BU: " & L41 & ") (Head: " & M41 & ")" & IF(ISBLANK(T41), "", " (Apt#: " & T41 & ")"), "Payment: Disbursement for " & IF(ISBLANK(U41), "", IF(ISBLANK(U41), "", U41) & " ") & "(Ref: " & H41 & ") (Type: " & P41 & ") (BU: " & L41 & ") (Head: " & M41 & ")" & IF(ISBLANK(T41), "", " (Apt#: " & T41 & ")"))))) -> Payment: Disbursement for Bank Charges Debited (Ref: SCREF01284574169) (Type: HO - Admin) (BU: Casa Romana) (Head: Bank Charges)
A42: 195 | B42: =IF(D42="","?",_xludf.IFS( MONTH(D42)<=3,"Q4", MONTH(D42)<=6,"Q1", MONTH(D42)<=9,"Q2", TRUE,"Q3" )) -> #NAME? | C42: =MONTH(D42) -> 7 | D42: 46232 | E42: 46232 | G42: CHQ DEP HDB 29-JUL-26 SOHNA ROAD | H42: 63 | J42: 100000 | K42: =K43+J42-I42 -> 129215.5 | L42: Casa Romana | M42: Collection | O42: Entry | P42: Customer Collection | Q42: Credit- no effect | T42: R-063 | U42: Mr. AMARJEET SINGH DAYMA | V42: Adjust | W42: =TRIM(IF(M42="Internal", IF(ISBLANK(G42), IF(LEN(G42)-LEN(SUBSTITUTE(G42,"-",""))>=3, "Fund Transfer: From x" & RIGHT(MID(G42, FIND("|", SUBSTITUTE(G42, "-", "|", 3)) + 1, LEN(G42)), 4) & " to YES MASTER 0264 (Ref: " & H42 & ") (Type: " & P42 & ") (BU: " & L42 & ") (Head: " & M42 & ")", "Fund Transfer: To YES MASTER 0264 (Ref: " & H42 & ") (Type: " & P42 & ") (BU: " & L42 & ") (Head: " & M42 & ")"), IF(LEN(G42)-LEN(SUBSTITUTE(G42,"-",""))>=3, "Fund Transfer: From YES MASTER 0264 to x" & RIGHT(MID(G42, FIND("|", SUBSTITUTE(G42, "-", "|", 3)) + 1, LEN(G42)), 4) & " (Ref: " & H42 & ") (Type: " & P42 & ") (BU: " & L42 & ") (Head: " & M42 & ")", "Fund Transfer: From YES MASTER 0264 (Ref: " & H42 & ") (Type: " & P42 & ") (BU: " & L42 & ") (Head: " & M42 & ")")), IF(NOT(ISBLANK(J42)), IF(P42="Customer Collection", "Receipt: For " & IF(ISBLANK(T42), "", "(Apt#: " & T42 & ") ") & "(Ref: " & H42 & ") (" & IF(ISNUMBER(SEARCH("NEFT",G42)), "NEFT:", IF(ISNUMBER(SEARCH("RTGS",G42)), "RTGS:", IF(ISNUMBER(SEARCH("IMPS",G42)), "IMPS:", ""))) & " " & IF(ISNUMBER(SEARCH("SOHNA ROAD", G42)), "", IFERROR(MID(G42, FIND("-", G42, FIND("-", G42) + 1) + 1, LEN(G42)), SUBSTITUTE(SUBSTITUTE(SUBSTITUTE(G42, "IMPS/", ""), "NEFT/", ""), "RTGS/", ""))) & ") (Type: " & P42 & ") (BU: " & L42 & ")", IF(LEN(G42)-LEN(SUBSTITUTE(G42,"-",""))>=3, "Receipt: From x" & RIGHT(MID(G42, FIND("|", SUBSTITUTE(G42, "-", "|", 3)) + 1, LEN(G42)), 4) & " towards " & IF(ISBLANK(U42), L42, U42) & IF(OR(L42="Cancellation", L42="Collection"), " Apt No " & T42, "") & " (Ref: " & H42 & ") (Type: " & P42 & ") (BU: " & L42 & ") (Head: " & M42 & ")" & IF(ISBLANK(T42), "", " (Apt#: " & T42 & ")"), "Receipt: Against " & IF(ISBLANK(U42), L42, U42) & IF(OR(L42="Cancellation", L42="Collection"), " Apt No " & T42, "") & " (Ref: " & H42 & ") (Type: " & P42 & ") (BU: " & L42 & ") (Head: " & M42 & ")" & IF(ISBLANK(T42), "", " (Apt#: " & T42 & ")"))), IF(LEN(G42)-LEN(SUBSTITUTE(G42,"-",""))>=3, "Payment: To x" & RIGHT(MID(G42, FIND("|", SUBSTITUTE(G42, "-", "|", 3)) + 1, LEN(G42)), 4) & " for " & IF(ISBLANK(U42), L42, U42) & " (Ref: " & H42 & ") (Type: " & P42 & ") (BU: " & L42 & ") (Head: " & M42 & ")" & IF(ISBLANK(T42), "", " (Apt#: " & T42 & ")"), "Payment: Disbursement for " & IF(ISBLANK(U42), "", IF(ISBLANK(U42), "", U42) & " ") & "(Ref: " & H42 & ") (Type: " & P42 & ") (BU: " & L42 & ") (Head: " & M42 & ")" & IF(ISBLANK(T42), "", " (Apt#: " & T42 & ")"))))) -> Receipt: For (Apt#: R-063) (Ref: 63) ( ) (Type: Customer Collection) (BU: Casa Romana)
A43: 194 | B43: =IF(D43="","?",_xludf.IFS( MONTH(D43)<=3,"Q4", MONTH(D43)<=6,"Q1", MONTH(D43)<=9,"Q2", TRUE,"Q3" )) -> #NAME? | C43: =MONTH(D43) -> 7 | D43: 46226 | E43: 46226 | G43: YIB-TPT-Dwarkadhis Projects Pvt Ltd-Internal-045563400002477 | H43: YESME6204005383700 | I43: 14700 | K43: =K44+J43-I43 -> 29215.5 | L43: Casa Romana | M43: Internal | O43: Entry | P43: Master to Free | Q43: Internal transfer | W43: =TRIM(IF(M43="Internal", IF(ISBLANK(G43), IF(LEN(G43)-LEN(SUBSTITUTE(G43,"-",""))>=3, "Fund Transfer: From x" & RIGHT(MID(G43, FIND("|", SUBSTITUTE(G43, "-", "|", 3)) + 1, LEN(G43)), 4) & " to YES MASTER 0264 (Ref: " & H43 & ") (Type: " & P43 & ") (BU: " & L43 & ") (Head: " & M43 & ")", "Fund Transfer: To YES MASTER 0264 (Ref: " & H43 & ") (Type: " & P43 & ") (BU: " & L43 & ") (Head: " & M43 & ")"), IF(LEN(G43)-LEN(SUBSTITUTE(G43,"-",""))>=3, "Fund Transfer: From YES MASTER 0264 to x" & RIGHT(MID(G43, FIND("|", SUBSTITUTE(G43, "-", "|", 3)) + 1, LEN(G43)), 4) & " (Ref: " & H43 & ") (Type: " & P43 & ") (BU: " & L43 & ") (Head: " & M43 & ")", "Fund Transfer: From YES MASTER 0264 (Ref: " & H43 & ") (Type: " & P43 & ") (BU: " & L43 & ") (Head: " & M43 & ")")), IF(NOT(ISBLANK(J43)), IF(P43="Customer Collection", "Receipt: For " & IF(ISBLANK(T43), "", "(Apt#: " & T43 & ") ") & "(Ref: " & H43 & ") (" & IF(ISNUMBER(SEARCH("NEFT",G43)), "NEFT:", IF(ISNUMBER(SEARCH("RTGS",G43)), "RTGS:", IF(ISNUMBER(SEARCH("IMPS",G43)), "IMPS:", ""))) & " " & IF(ISNUMBER(SEARCH("SOHNA ROAD", G43)), "", IFERROR(MID(G43, FIND("-", G43, FIND("-", G43) + 1) + 1, LEN(G43)), SUBSTITUTE(SUBSTITUTE(SUBSTITUTE(G43, "IMPS/", ""), "NEFT/", ""), "RTGS/", ""))) & ") (Type: " & P43 & ") (BU: " & L43 & ")", IF(LEN(G43)-LEN(SUBSTITUTE(G43,"-",""))>=3, "Receipt: From x" & RIGHT(MID(G43, FIND("|", SUBSTITUTE(G43, "-", "|", 3)) + 1, LEN(G43)), 4) & " towards " & IF(ISBLANK(U43), L43, U43) & IF(OR(L43="Cancellation", L43="Collection"), " Apt No " & T43, "") & " (Ref: " & H43 & ") (Type: " & P43 & ") (BU: " & L43 & ") (Head: " & M43 & ")" & IF(ISBLANK(T43), "", " (Apt#: " & T43 & ")"), "Receipt: Against " & IF(ISBLANK(U43), L43, U43) & IF(OR(L43="Cancellation", L43="Collection"), " Apt No " & T43, "") & " (Ref: " & H43 & ") (Type: " & P43 & ") (BU: " & L43 & ") (Head: " & M43 & ")" & IF(ISBLANK(T43), "", " (Apt#: " & T43 & ")"))), IF(LEN(G43)-LEN(SUBSTITUTE(G43,"-",""))>=3, "Payment: To x" & RIGHT(MID(G43, FIND("|", SUBSTITUTE(G43, "-", "|", 3)) + 1, LEN(G43)), 4) & " for " & IF(ISBLANK(U43), L43, U43) & " (Ref: " & H43 & ") (Type: " & P43 & ") (BU: " & L43 & ") (Head: " & M43 & ")" & IF(ISBLANK(T43), "", " (Apt#: " & T43 & ")"), "Payment: Disbursement for " & IF(ISBLANK(U43), "", IF(ISBLANK(U43), "", U43) & " ") & "(Ref: " & H43 & ") (Type: " & P43 & ") (BU: " & L43 & ") (Head: " & M43 & ")" & IF(ISBLANK(T43), "", " (Apt#: " & T43 & ")"))))) -> Fund Transfer: From YES MASTER 0264 to x2477 (Ref: YESME6204005383700) (Type: Master to Free) (BU: Casa Romana) (Head: Internal)
A44: 193 | B44: =IF(D44="","?",_xludf.IFS( MONTH(D44)<=3,"Q4", MONTH(D44)<=6,"Q1", MONTH(D44)<=9,"Q2", TRUE,"Q3" )) -> #NAME? | C44: =MONTH(D44) -> 7 | D44: 46226 | E44: 46226 | G44: YIB-TPT-DWARKADHIS PROJECTS PRIVATE LIMITED-Internal-045563200000377 | H44: YESME6204005383600 | I44: 34300 | K44: =K45+J44-I44 -> 43915.5 | L44: Casa Romana | M44: Internal | O44: Entry | P44: Master 2 RERA | Q44: Internal transfer | W44: =TRIM(IF(M44="Internal", IF(ISBLANK(G44), IF(LEN(G44)-LEN(SUBSTITUTE(G44,"-",""))>=3, "Fund Transfer: From x" & RIGHT(MID(G44, FIND("|", SUBSTITUTE(G44, "-", "|", 3)) + 1, LEN(G44)), 4) & " to YES MASTER 0264 (Ref: " & H44 & ") (Type: " & P44 & ") (BU: " & L44 & ") (Head: " & M44 & ")", "Fund Transfer: To YES MASTER 0264 (Ref: " & H44 & ") (Type: " & P44 & ") (BU: " & L44 & ") (Head: " & M44 & ")"), IF(LEN(G44)-LEN(SUBSTITUTE(G44,"-",""))>=3, "Fund Transfer: From YES MASTER 0264 to x" & RIGHT(MID(G44, FIND("|", SUBSTITUTE(G44, "-", "|", 3)) + 1, LEN(G44)), 4) & " (Ref: " & H44 & ") (Type: " & P44 & ") (BU: " & L44 & ") (Head: " & M44 & ")", "Fund Transfer: From YES MASTER 0264 (Ref: " & H44 & ") (Type: " & P44 & ") (BU: " & L44 & ") (Head: " & M44 & ")")), IF(NOT(ISBLANK(J44)), IF(P44="Customer Collection", "Receipt: For " & IF(ISBLANK(T44), "", "(Apt#: " & T44 & ") ") & "(Ref: " & H44 & ") (" & IF(ISNUMBER(SEARCH("NEFT",G44)), "NEFT:", IF(ISNUMBER(SEARCH("RTGS",G44)), "RTGS:", IF(ISNUMBER(SEARCH("IMPS",G44)), "IMPS:", ""))) & " " & IF(ISNUMBER(SEARCH("SOHNA ROAD", G44)), "", IFERROR(MID(G44, FIND("-", G44, FIND("-", G44) + 1) + 1, LEN(G44)), SUBSTITUTE(SUBSTITUTE(SUBSTITUTE(G44, "IMPS/", ""), "NEFT/", ""), "RTGS/", ""))) & ") (Type: " & P44 & ") (BU: " & L44 & ")", IF(LEN(G44)-LEN(SUBSTITUTE(G44,"-",""))>=3, "Receipt: From x" & RIGHT(MID(G44, FIND("|", SUBSTITUTE(G44, "-", "|", 3)) + 1, LEN(G44)), 4) & " towards " & IF(ISBLANK(U44), L44, U44) & IF(OR(L44="Cancellation", L44="Collection"), " Apt No " & T44, "") & " (Ref: " & H44 & ") (Type: " & P44 & ") (BU: " & L44 & ") (Head: " & M44 & ")" & IF(ISBLANK(T44), "", " (Apt#: " & T44 & ")"), "Receipt: Against " & IF(ISBLANK(U44), L44, U44) & IF(OR(L44="Cancellation", L44="Collection"), " Apt No " & T44, "") & " (Ref: " & H44 & ") (Type: " & P44 & ") (BU: " & L44 & ") (Head: " & M44 & ")" & IF(ISBLANK(T44), "", " (Apt#: " & T44 & ")"))), IF(LEN(G44)-LEN(SUBSTITUTE(G44,"-",""))>=3, "Payment: To x" & RIGHT(MID(G44, FIND("|", SUBSTITUTE(G44, "-", "|", 3)) + 1, LEN(G44)), 4) & " for " & IF(ISBLANK(U44), L44, U44) & " (Ref: " & H44 & ") (Type: " & P44 & ") (BU: " & L44 & ") (Head: " & M44 & ")" & IF(ISBLANK(T44), "", " (Apt#: " & T44 & ")"), "Payment: Disbursement for " & IF(ISBLANK(U44), "", IF(ISBLANK(U44), "", U44) & " ") & "(Ref: " & H44 & ") (Type: " & P44 & ") (BU: " & L44 & ") (Head: " & M44 & ")" & IF(ISBLANK(T44), "", " (Apt#: " & T44 & ")"))))) -> Fund Transfer: From YES MASTER 0264 to x0377 (Ref: YESME6204005383600) (Type: Master 2 RERA) (BU: Casa Romana) (Head: Internal)
A45: 192 | B45: =IF(D45="","?",_xludf.IFS( MONTH(D45)<=3,"Q4", MONTH(D45)<=6,"Q1", MONTH(D45)<=9,"Q2", TRUE,"Q3" )) -> #NAME? | C45: =MONTH(D45) -> 7 | D45: 46226 | E45: 46226 | G45: CASH DEP-SELF-DWARKADHIS PROJECTS PRIVATE LIMITED IN C-SHAMSHABAD | H45: 10004875420260723006900000009 | J45: 49000 | K45: =K46+J45-I45 -> 78215.5 | L45: Casa Romana | M45: Collection | O45: Entry | P45: Customer Collection | Q45: Credit- no effect | T45: T-101 | U45: Ms. KAMAL JEET AGARWAL | V45: Adjust | W45: =TRIM(IF(M45="Internal", IF(ISBLANK(G45), IF(LEN(G45)-LEN(SUBSTITUTE(G45,"-",""))>=3, "Fund Transfer: From x" & RIGHT(MID(G45, FIND("|", SUBSTITUTE(G45, "-", "|", 3)) + 1, LEN(G45)), 4) & " to YES MASTER 0264 (Ref: " & H45 & ") (Type: " & P45 & ") (BU: " & L45 & ") (Head: " & M45 & ")", "Fund Transfer: To YES MASTER 0264 (Ref: " & H45 & ") (Type: " & P45 & ") (BU: " & L45 & ") (Head: " & M45 & ")"), IF(LEN(G45)-LEN(SUBSTITUTE(G45,"-",""))>=3, "Fund Transfer: From YES MASTER 0264 to x" & RIGHT(MID(G45, FIND("|", SUBSTITUTE(G45, "-", "|", 3)) + 1, LEN(G45)), 4) & " (Ref: " & H45 & ") (Type: " & P45 & ") (BU: " & L45 & ") (Head: " & M45 & ")", "Fund Transfer: From YES MASTER 0264 (Ref: " & H45 & ") (Type: " & P45 & ") (BU: " & L45 & ") (Head: " & M45 & ")")), IF(NOT(ISBLANK(J45)), IF(P45="Customer Collection", "Receipt: For " & IF(ISBLANK(T45), "", "(Apt#: " & T45 & ") ") & "(Ref: " & H45 & ") (" & IF(ISNUMBER(SEARCH("NEFT",G45)), "NEFT:", IF(ISNUMBER(SEARCH("RTGS",G45)), "RTGS:", IF(ISNUMBER(SEARCH("IMPS",G45)), "IMPS:", ""))) & " " & IF(ISNUMBER(SEARCH("SOHNA ROAD", G45)), "", IFERROR(MID(G45, FIND("-", G45, FIND("-", G45) + 1) + 1, LEN(G45)), SUBSTITUTE(SUBSTITUTE(SUBSTITUTE(G45, "IMPS/", ""), "NEFT/", ""), "RTGS/", ""))) & ") (Type: " & P45 & ") (BU: " & L45 & ")", IF(LEN(G45)-LEN(SUBSTITUTE(G45,"-",""))>=3, "Receipt: From x" & RIGHT(MID(G45, FIND("|", SUBSTITUTE(G45, "-", "|", 3)) + 1, LEN(G45)), 4) & " towards " & IF(ISBLANK(U45), L45, U45) & IF(OR(L45="Cancellation", L45="Collection"), " Apt No " & T45, "") & " (Ref: " & H45 & ") (Type: " & P45 & ") (BU: " & L45 & ") (Head: " & M45 & ")" & IF(ISBLANK(T45), "", " (Apt#: " & T45 & ")"), "Receipt: Against " & IF(ISBLANK(U45), L45, U45) & IF(OR(L45="Cancellation", L45="Collection"), " Apt No " & T45, "") & " (Ref: " & H45 & ") (Type: " & P45 & ") (BU: " & L45 & ") (Head: " & M45 & ")" & IF(ISBLANK(T45), "", " (Apt#: " & T45 & ")"))), IF(LEN(G45)-LEN(SUBSTITUTE(G45,"-",""))>=3, "Payment: To x" & RIGHT(MID(G45, FIND("|", SUBSTITUTE(G45, "-", "|", 3)) + 1, LEN(G45)), 4) & " for " & IF(ISBLANK(U45), L45, U45) & " (Ref: " & H45 & ") (Type: " & P45 & ") (BU: " & L45 & ") (Head: " & M45 & ")" & IF(ISBLANK(T45), "", " (Apt#: " & T45 & ")"), "Payment: Disbursement for " & IF(ISBLANK(U45), "", IF(ISBLANK(U45), "", U45) & " ") & "(Ref: " & H45 & ") (Type: " & P45 & ") (BU: " & L45 & ") (Head: " & M45 & ")" & IF(ISBLANK(T45), "", " (Apt#: " & T45 & ")"))))) -> Receipt: For (Apt#: T-101) (Ref: 10004875420260723006900000009) ( DWARKADHIS PROJECTS PRIVATE LIMITED IN C-SHAMSHABAD) (Type: Customer Collection) (BU: Casa Romana)
A46: 191 | B46: =IF(D46="","?",_xludf.IFS( MONTH(D46)<=3,"Q4", MONTH(D46)<=6,"Q1", MONTH(D46)<=9,"Q2", TRUE,"Q3" )) -> #NAME? | C46: =MONTH(D46) -> 7 | D46: 46225 | E46: 46225 | G46: YIB-TPT-DWARKADHIS PROJECTS PRIVATE LIMITED-Internal-045563200000377 | H46: YESME6203005228700 | I46: 64015 | K46: =K47+J46-I46 -> 29215.5 | L46: Casa Romana | M46: Internal | O46: Entry | P46: Master 2 RERA | Q46: Internal transfer | W46: =TRIM(IF(M46="Internal", IF(ISBLANK(G46), IF(LEN(G46)-LEN(SUBSTITUTE(G46,"-",""))>=3, "Fund Transfer: From x" & RIGHT(MID(G46, FIND("|", SUBSTITUTE(G46, "-", "|", 3)) + 1, LEN(G46)), 4) & " to YES MASTER 0264 (Ref: " & H46 & ") (Type: " & P46 & ") (BU: " & L46 & ") (Head: " & M46 & ")", "Fund Transfer: To YES MASTER 0264 (Ref: " & H46 & ") (Type: " & P46 & ") (BU: " & L46 & ") (Head: " & M46 & ")"), IF(LEN(G46)-LEN(SUBSTITUTE(G46,"-",""))>=3, "Fund Transfer: From YES MASTER 0264 to x" & RIGHT(MID(G46, FIND("|", SUBSTITUTE(G46, "-", "|", 3)) + 1, LEN(G46)), 4) & " (Ref: " & H46 & ") (Type: " & P46 & ") (BU: " & L46 & ") (Head: " & M46 & ")", "Fund Transfer: From YES MASTER 0264 (Ref: " & H46 & ") (Type: " & P46 & ") (BU: " & L46 & ") (Head: " & M46 & ")")), IF(NOT(ISBLANK(J46)), IF(P46="Customer Collection", "Receipt: For " & IF(ISBLANK(T46), "", "(Apt#: " & T46 & ") ") & "(Ref: " & H46 & ") (" & IF(ISNUMBER(SEARCH("NEFT",G46)), "NEFT:", IF(ISNUMBER(SEARCH("RTGS",G46)), "RTGS:", IF(ISNUMBER(SEARCH("IMPS",G46)), "IMPS:", ""))) & " " & IF(ISNUMBER(SEARCH("SOHNA ROAD", G46)), "", IFERROR(MID(G46, FIND("-", G46, FIND("-", G46) + 1) + 1, LEN(G46)), SUBSTITUTE(SUBSTITUTE(SUBSTITUTE(G46, "IMPS/", ""), "NEFT/", ""), "RTGS/", ""))) & ") (Type: " & P46 & ") (BU: " & L46 & ")", IF(LEN(G46)-LEN(SUBSTITUTE(G46,"-",""))>=3, "Receipt: From x" & RIGHT(MID(G46, FIND("|", SUBSTITUTE(G46, "-", "|", 3)) + 1, LEN(G46)), 4) & " towards " & IF(ISBLANK(U46), L46, U46) & IF(OR(L46="Cancellation", L46="Collection"), " Apt No " & T46, "") & " (Ref: " & H46 & ") (Type: " & P46 & ") (BU: " & L46 & ") (Head: " & M46 & ")" & IF(ISBLANK(T46), "", " (Apt#: " & T46 & ")"), "Receipt: Against " & IF(ISBLANK(U46), L46, U46) & IF(OR(L46="Cancellation", L46="Collection"), " Apt No " & T46, "") & " (Ref: " & H46 & ") (Type: " & P46 & ") (BU: " & L46 & ") (Head: " & M46 & ")" & IF(ISBLANK(T46), "", " (Apt#: " & T46 & ")"))), IF(LEN(G46)-LEN(SUBSTITUTE(G46,"-",""))>=3, "Payment: To x" & RIGHT(MID(G46, FIND("|", SUBSTITUTE(G46, "-", "|", 3)) + 1, LEN(G46)), 4) & " for " & IF(ISBLANK(U46), L46, U46) & " (Ref: " & H46 & ") (Type: " & P46 & ") (BU: " & L46 & ") (Head: " & M46 & ")" & IF(ISBLANK(T46), "", " (Apt#: " & T46 & ")"), "Payment: Disbursement for " & IF(ISBLANK(U46), "", IF(ISBLANK(U46), "", U46) & " ") & "(Ref: " & H46 & ") (Type: " & P46 & ") (BU: " & L46 & ") (Head: " & M46 & ")" & IF(ISBLANK(T46), "", " (Apt#: " & T46 & ")"))))) -> Fund Transfer: From YES MASTER 0264 to x0377 (Ref: YESME6203005228700) (Type: Master 2 RERA) (BU: Casa Romana) (Head: Internal)
A47: 190 | B47: =IF(D47="","?",_xludf.IFS( MONTH(D47)<=3,"Q4", MONTH(D47)<=6,"Q1", MONTH(D47)<=9,"Q2", TRUE,"Q3" )) -> #NAME? | C47: =MONTH(D47) -> 7 | D47: 46225 | E47: 46225 | G47: YIB-TPT-Dwarkadhis Projects Pvt Ltd-Internal-045563400002477 | H47: YESME6203005190700 | I47: 27435 | K47: =K48+J47-I47 -> 93230.5 | L47: Casa Romana | M47: Internal | O47: Entry | P47: Master to Free | Q47: Internal transfer | W47: =TRIM(IF(M47="Internal", IF(ISBLANK(G47), IF(LEN(G47)-LEN(SUBSTITUTE(G47,"-",""))>=3, "Fund Transfer: From x" & RIGHT(MID(G47, FIND("|", SUBSTITUTE(G47, "-", "|", 3)) + 1, LEN(G47)), 4) & " to YES MASTER 0264 (Ref: " & H47 & ") (Type: " & P47 & ") (BU: " & L47 & ") (Head: " & M47 & ")", "Fund Transfer: To YES MASTER 0264 (Ref: " & H47 & ") (Type: " & P47 & ") (BU: " & L47 & ") (Head: " & M47 & ")"), IF(LEN(G47)-LEN(SUBSTITUTE(G47,"-",""))>=3, "Fund Transfer: From YES MASTER 0264 to x" & RIGHT(MID(G47, FIND("|", SUBSTITUTE(G47, "-", "|", 3)) + 1, LEN(G47)), 4) & " (Ref: " & H47 & ") (Type: " & P47 & ") (BU: " & L47 & ") (Head: " & M47 & ")", "Fund Transfer: From YES MASTER 0264 (Ref: " & H47 & ") (Type: " & P47 & ") (BU: " & L47 & ") (Head: " & M47 & ")")), IF(NOT(ISBLANK(J47)), IF(P47="Customer Collection", "Receipt: For " & IF(ISBLANK(T47), "", "(Apt#: " & T47 & ") ") & "(Ref: " & H47 & ") (" & IF(ISNUMBER(SEARCH("NEFT",G47)), "NEFT:", IF(ISNUMBER(SEARCH("RTGS",G47)), "RTGS:", IF(ISNUMBER(SEARCH("IMPS",G47)), "IMPS:", ""))) & " " & IF(ISNUMBER(SEARCH("SOHNA ROAD", G47)), "", IFERROR(MID(G47, FIND("-", G47, FIND("-", G47) + 1) + 1, LEN(G47)), SUBSTITUTE(SUBSTITUTE(SUBSTITUTE(G47, "IMPS/", ""), "NEFT/", ""), "RTGS/", ""))) & ") (Type: " & P47 & ") (BU: " & L47 & ")", IF(LEN(G47)-LEN(SUBSTITUTE(G47,"-",""))>=3, "Receipt: From x" & RIGHT(MID(G47, FIND("|", SUBSTITUTE(G47, "-", "|", 3)) + 1, LEN(G47)), 4) & " towards " & IF(ISBLANK(U47), L47, U47) & IF(OR(L47="Cancellation", L47="Collection"), " Apt No " & T47, "") & " (Ref: " & H47 & ") (Type: " & P47 & ") (BU: " & L47 & ") (Head: " & M47 & ")" & IF(ISBLANK(T47), "", " (Apt#: " & T47 & ")"), "Receipt: Against " & IF(ISBLANK(U47), L47, U47) & IF(OR(L47="Cancellation", L47="Collection"), " Apt No " & T47, "") & " (Ref: " & H47 & ") (Type: " & P47 & ") (BU: " & L47 & ") (Head: " & M47 & ")" & IF(ISBLANK(T47), "", " (Apt#: " & T47 & ")"))), IF(LEN(G47)-LEN(SUBSTITUTE(G47,"-",""))>=3, "Payment: To x" & RIGHT(MID(G47, FIND("|", SUBSTITUTE(G47, "-", "|", 3)) + 1, LEN(G47)), 4) & " for " & IF(ISBLANK(U47), L47, U47) & " (Ref: " & H47 & ") (Type: " & P47 & ") (BU: " & L47 & ") (Head: " & M47 & ")" & IF(ISBLANK(T47), "", " (Apt#: " & T47 & ")"), "Payment: Disbursement for " & IF(ISBLANK(U47), "", IF(ISBLANK(U47), "", U47) & " ") & "(Ref: " & H47 & ") (Type: " & P47 & ") (BU: " & L47 & ") (Head: " & M47 & ")" & IF(ISBLANK(T47), "", " (Apt#: " & T47 & ")"))))) -> Fund Transfer: From YES MASTER 0264 to x2477 (Ref: YESME6203005190700) (Type: Master to Free) (BU: Casa Romana) (Head: Internal)
A48: 189 | B48: =IF(D48="","?",_xludf.IFS( MONTH(D48)<=3,"Q4", MONTH(D48)<=6,"Q1", MONTH(D48)<=9,"Q2", TRUE,"Q3" )) -> #NAME? | C48: =MONTH(D48) -> 7 | D48: 46224 | E48: 46224 | G48: NEFT Cr-ICIC0SF0002-HARI KISHAN-DWARKADHIS PROJECTS PRIVA-IN12620247274271 | H48: YES0N6202072677900 | J48: 70000 | K48: =K49+J48-I48 -> 120665.5 | L48: Casa Romana | M48: Collection | O48: Entry | P48: Customer Collection | Q48: Credit- no effect | T48: N-054 | V48: Adjust | W48: =TRIM(IF(M48="Internal", IF(ISBLANK(G48), IF(LEN(G48)-LEN(SUBSTITUTE(G48,"-",""))>=3, "Fund Transfer: From x" & RIGHT(MID(G48, FIND("|", SUBSTITUTE(G48, "-", "|", 3)) + 1, LEN(G48)), 4) & " to YES MASTER 0264 (Ref: " & H48 & ") (Type: " & P48 & ") (BU: " & L48 & ") (Head: " & M48 & ")", "Fund Transfer: To YES MASTER 0264 (Ref: " & H48 & ") (Type: " & P48 & ") (BU: " & L48 & ") (Head: " & M48 & ")"), IF(LEN(G48)-LEN(SUBSTITUTE(G48,"-",""))>=3, "Fund Transfer: From YES MASTER 0264 to x" & RIGHT(MID(G48, FIND("|", SUBSTITUTE(G48, "-", "|", 3)) + 1, LEN(G48)), 4) & " (Ref: " & H48 & ") (Type: " & P48 & ") (BU: " & L48 & ") (Head: " & M48 & ")", "Fund Transfer: From YES MASTER 0264 (Ref: " & H48 & ") (Type: " & P48 & ") (BU: " & L48 & ") (Head: " & M48 & ")")), IF(NOT(ISBLANK(J48)), IF(P48="Customer Collection", "Receipt: For " & IF(ISBLANK(T48), "", "(Apt#: " & T48 & ") ") & "(Ref: " & H48 & ") (" & IF(ISNUMBER(SEARCH("NEFT",G48)), "NEFT:", IF(ISNUMBER(SEARCH("RTGS",G48)), "RTGS:", IF(ISNUMBER(SEARCH("IMPS",G48)), "IMPS:", ""))) & " " & IF(ISNUMBER(SEARCH("SOHNA ROAD", G48)), "", IFERROR(MID(G48, FIND("-", G48, FIND("-", G48) + 1) + 1, LEN(G48)), SUBSTITUTE(SUBSTITUTE(SUBSTITUTE(G48, "IMPS/", ""), "NEFT/", ""), "RTGS/", ""))) & ") (Type: " & P48 & ") (BU: " & L48 & ")", IF(LEN(G48)-LEN(SUBSTITUTE(G48,"-",""))>=3, "Receipt: From x" & RIGHT(MID(G48, FIND("|", SUBSTITUTE(G48, "-", "|", 3)) + 1, LEN(G48)), 4) & " towards " & IF(ISBLANK(U48), L48, U48) & IF(OR(L48="Cancellation", L48="Collection"), " Apt No " & T48, "") & " (Ref: " & H48 & ") (Type: " & P48 & ") (BU: " & L48 & ") (Head: " & M48 & ")" & IF(ISBLANK(T48), "", " (Apt#: " & T48 & ")"), "Receipt: Against " & IF(ISBLANK(U48), L48, U48) & IF(OR(L48="Cancellation", L48="Collection"), " Apt No " & T48, "") & " (Ref: " & H48 & ") (Type: " & P48 & ") (BU: " & L48 & ") (Head: " & M48 & ")" & IF(ISBLANK(T48), "", " (Apt#: " & T48 & ")"))), IF(LEN(G48)-LEN(SUBSTITUTE(G48,"-",""))>=3, "Payment: To x" & RIGHT(MID(G48, FIND("|", SUBSTITUTE(G48, "-", "|", 3)) + 1, LEN(G48)), 4) & " for " & IF(ISBLANK(U48), L48, U48) & " (Ref: " & H48 & ") (Type: " & P48 & ") (BU: " & L48 & ") (Head: " & M48 & ")" & IF(ISBLANK(T48), "", " (Apt#: " & T48 & ")"), "Payment: Disbursement for " & IF(ISBLANK(U48), "", IF(ISBLANK(U48), "", U48) & " ") & "(Ref: " & H48 & ") (Type: " & P48 & ") (BU: " & L48 & ") (Head: " & M48 & ")" & IF(ISBLANK(T48), "", " (Apt#: " & T48 & ")"))))) -> Receipt: For (Apt#: N-054) (Ref: YES0N6202072677900) (NEFT: HARI KISHAN-DWARKADHIS PROJECTS PRIVA-IN12620247274271) (Type: Customer Collection) (BU: Casa Romana)
A49: 188 | B49: =IF(D49="","?",_xludf.IFS( MONTH(D49)<=3,"Q4", MONTH(D49)<=6,"Q1", MONTH(D49)<=9,"Q2", TRUE,"Q3" )) -> #NAME? | C49: =MONTH(D49) -> 7 | D49: 46224 | E49: 46224 | G49: NEFT Cr-KKBK0000958-PRAVEEN KUMAR PAUR-DWARKADHIS PROJECTS PRIVA-KKBKH26202867090 | H49: YES0N6202046781100 | J49: 21450 | K49: =K50+J49-I49 -> 50665.5 | L49: Casa Romana | M49: Collection | O49: Entry | P49: Customer Collection | Q49: Credit- no effect | T49: M-087 | V49: Adjust | W49: =TRIM(IF(M49="Internal", IF(ISBLANK(G49), IF(LEN(G49)-LEN(SUBSTITUTE(G49,"-",""))>=3, "Fund Transfer: From x" & RIGHT(MID(G49, FIND("|", SUBSTITUTE(G49, "-", "|", 3)) + 1, LEN(G49)), 4) & " to YES MASTER 0264 (Ref: " & H49 & ") (Type: " & P49 & ") (BU: " & L49 & ") (Head: " & M49 & ")", "Fund Transfer: To YES MASTER 0264 (Ref: " & H49 & ") (Type: " & P49 & ") (BU: " & L49 & ") (Head: " & M49 & ")"), IF(LEN(G49)-LEN(SUBSTITUTE(G49,"-",""))>=3, "Fund Transfer: From YES MASTER 0264 to x" & RIGHT(MID(G49, FIND("|", SUBSTITUTE(G49, "-", "|", 3)) + 1, LEN(G49)), 4) & " (Ref: " & H49 & ") (Type: " & P49 & ") (BU: " & L49 & ") (Head: " & M49 & ")", "Fund Transfer: From YES MASTER 0264 (Ref: " & H49 & ") (Type: " & P49 & ") (BU: " & L49 & ") (Head: " & M49 & ")")), IF(NOT(ISBLANK(J49)), IF(P49="Customer Collection", "Receipt: For " & IF(ISBLANK(T49), "", "(Apt#: " & T49 & ") ") & "(Ref: " & H49 & ") (" & IF(ISNUMBER(SEARCH("NEFT",G49)), "NEFT:", IF(ISNUMBER(SEARCH("RTGS",G49)), "RTGS:", IF(ISNUMBER(SEARCH("IMPS",G49)), "IMPS:", ""))) & " " & IF(ISNUMBER(SEARCH("SOHNA ROAD", G49)), "", IFERROR(MID(G49, FIND("-", G49, FIND("-", G49) + 1) + 1, LEN(G49)), SUBSTITUTE(SUBSTITUTE(SUBSTITUTE(G49, "IMPS/", ""), "NEFT/", ""), "RTGS/", ""))) & ") (Type: " & P49 & ") (BU: " & L49 & ")", IF(LEN(G49)-LEN(SUBSTITUTE(G49,"-",""))>=3, "Receipt: From x" & RIGHT(MID(G49, FIND("|", SUBSTITUTE(G49, "-", "|", 3)) + 1, LEN(G49)), 4) & " towards " & IF(ISBLANK(U49), L49, U49) & IF(OR(L49="Cancellation", L49="Collection"), " Apt No " & T49, "") & " (Ref: " & H49 & ") (Type: " & P49 & ") (BU: " & L49 & ") (Head: " & M49 & ")" & IF(ISBLANK(T49), "", " (Apt#: " & T49 & ")"), "Receipt: Against " & IF(ISBLANK(U49), L49, U49) & IF(OR(L49="Cancellation", L49="Collection"), " Apt No " & T49, "") & " (Ref: " & H49 & ") (Type: " & P49 & ") (BU: " & L49 & ") (Head: " & M49 & ")" & IF(ISBLANK(T49), "", " (Apt#: " & T49 & ")"))), IF(LEN(G49)-LEN(SUBSTITUTE(G49,"-",""))>=3, "Payment: To x" & RIGHT(MID(G49, FIND("|", SUBSTITUTE(G49, "-", "|", 3)) + 1, LEN(G49)), 4) & " for " & IF(ISBLANK(U49), L49, U49) & " (Ref: " & H49 & ") (Type: " & P49 & ") (BU: " & L49 & ") (Head: " & M49 & ")" & IF(ISBLANK(T49), "", " (Apt#: " & T49 & ")"), "Payment: Disbursement for " & IF(ISBLANK(U49), "", IF(ISBLANK(U49), "", U49) & " ") & "(Ref: " & H49 & ") (Type: " & P49 & ") (BU: " & L49 & ") (Head: " & M49 & ")" & IF(ISBLANK(T49), "", " (Apt#: " & T49 & ")"))))) -> Receipt: For (Apt#: M-087) (Ref: YES0N6202046781100) (NEFT: PRAVEEN KUMAR PAUR-DWARKADHIS PROJECTS PRIVA-KKBKH26202867090) (Type: Customer Collection) (BU: Casa Romana)
A50: 187 | B50: =IF(D50="","?",_xludf.IFS( MONTH(D50)<=3,"Q4", MONTH(D50)<=6,"Q1", MONTH(D50)<=9,"Q2", TRUE,"Q3" )) -> #NAME? | C50: =MONTH(D50) -> 7 | D50: 46221 | E50: 46221 | G50: YIB-TPT-Dwarkadhis Projects Pvt Ltd-Internal-045563400002477 | H50: YESME6199005117700 | I50: 7500 | K50: =K51+J50-I50 -> 29215.5 | L50: Casa Romana | M50: Internal | O50: Entry | P50: Master to Free | Q50: Internal transfer | W50: =TRIM(IF(M50="Internal", IF(ISBLANK(G50), IF(LEN(G50)-LEN(SUBSTITUTE(G50,"-",""))>=3, "Fund Transfer: From x" & RIGHT(MID(G50, FIND("|", SUBSTITUTE(G50, "-", "|", 3)) + 1, LEN(G50)), 4) & " to YES MASTER 0264 (Ref: " & H50 & ") (Type: " & P50 & ") (BU: " & L50 & ") (Head: " & M50 & ")", "Fund Transfer: To YES MASTER 0264 (Ref: " & H50 & ") (Type: " & P50 & ") (BU: " & L50 & ") (Head: " & M50 & ")"), IF(LEN(G50)-LEN(SUBSTITUTE(G50,"-",""))>=3, "Fund Transfer: From YES MASTER 0264 to x" & RIGHT(MID(G50, FIND("|", SUBSTITUTE(G50, "-", "|", 3)) + 1, LEN(G50)), 4) & " (Ref: " & H50 & ") (Type: " & P50 & ") (BU: " & L50 & ") (Head: " & M50 & ")", "Fund Transfer: From YES MASTER 0264 (Ref: " & H50 & ") (Type: " & P50 & ") (BU: " & L50 & ") (Head: " & M50 & ")")), IF(NOT(ISBLANK(J50)), IF(P50="Customer Collection", "Receipt: For " & IF(ISBLANK(T50), "", "(Apt#: " & T50 & ") ") & "(Ref: " & H50 & ") (" & IF(ISNUMBER(SEARCH("NEFT",G50)), "NEFT:", IF(ISNUMBER(SEARCH("RTGS",G50)), "RTGS:", IF(ISNUMBER(SEARCH("IMPS",G50)), "IMPS:", ""))) & " " & IF(ISNUMBER(SEARCH("SOHNA ROAD", G50)), "", IFERROR(MID(G50, FIND("-", G50, FIND("-", G50) + 1) + 1, LEN(G50)), SUBSTITUTE(SUBSTITUTE(SUBSTITUTE(G50, "IMPS/", ""), "NEFT/", ""), "RTGS/", ""))) & ") (Type: " & P50 & ") (BU: " & L50 & ")", IF(LEN(G50)-LEN(SUBSTITUTE(G50,"-",""))>=3, "Receipt: From x" & RIGHT(MID(G50, FIND("|", SUBSTITUTE(G50, "-", "|", 3)) + 1, LEN(G50)), 4) & " towards " & IF(ISBLANK(U50), L50, U50) & IF(OR(L50="Cancellation", L50="Collection"), " Apt No " & T50, "") & " (Ref: " & H50 & ") (Type: " & P50 & ") (BU: " & L50 & ") (Head: " & M50 & ")" & IF(ISBLANK(T50), "", " (Apt#: " & T50 & ")"), "Receipt: Against " & IF(ISBLANK(U50), L50, U50) & IF(OR(L50="Cancellation", L50="Collection"), " Apt No " & T50, "") & " (Ref: " & H50 & ") (Type: " & P50 & ") (BU: " & L50 & ") (Head: " & M50 & ")" & IF(ISBLANK(T50), "", " (Apt#: " & T50 & ")"))), IF(LEN(G50)-LEN(SUBSTITUTE(G50,"-",""))>=3, "Payment: To x" & RIGHT(MID(G50, FIND("|", SUBSTITUTE(G50, "-", "|", 3)) + 1, LEN(G50)), 4) & " for " & IF(ISBLANK(U50), L50, U50) & " (Ref: " & H50 & ") (Type: " & P50 & ") (BU: " & L50 & ") (Head: " & M50 & ")" & IF(ISBLANK(T50), "", " (Apt#: " & T50 & ")"), "Payment: Disbursement for " & IF(ISBLANK(U50), "", IF(ISBLANK(U50), "", U50) & " ") & "(Ref: " & H50 & ") (Type: " & P50 & ") (BU: " & L50 & ") (Head: " & M50 & ")" & IF(ISBLANK(T50), "", " (Apt#: " & T50 & ")"))))) -> Fund Transfer: From YES MASTER 0264 to x2477 (Ref: YESME6199005117700) (Type: Master to Free) (BU: Casa Romana) (Head: Internal)
A51: 186 | B51: =IF(D51="","?",_xludf.IFS( MONTH(D51)<=3,"Q4", MONTH(D51)<=6,"Q1", MONTH(D51)<=9,"Q2", TRUE,"Q3" )) -> #NAME? | C51: =MONTH(D51) -> 7 | D51: 46221 | E51: 46221 | G51: YIB-TPT-DWARKADHIS PROJECTS PRIVATE LIMITED-internal-045563200000377 | H51: YESME6199005217500 | I51: 17500 | K51: =K52+J51-I51 -> 36715.5 | L51: Casa Romana | M51: Internal | O51: Entry | P51: Master 2 RERA | Q51: Internal transfer | W51: =TRIM(IF(M51="Internal", IF(ISBLANK(G51), IF(LEN(G51)-LEN(SUBSTITUTE(G51,"-",""))>=3, "Fund Transfer: From x" & RIGHT(MID(G51, FIND("|", SUBSTITUTE(G51, "-", "|", 3)) + 1, LEN(G51)), 4) & " to YES MASTER 0264 (Ref: " & H51 & ") (Type: " & P51 & ") (BU: " & L51 & ") (Head: " & M51 & ")", "Fund Transfer: To YES MASTER 0264 (Ref: " & H51 & ") (Type: " & P51 & ") (BU: " & L51 & ") (Head: " & M51 & ")"), IF(LEN(G51)-LEN(SUBSTITUTE(G51,"-",""))>=3, "Fund Transfer: From YES MASTER 0264 to x" & RIGHT(MID(G51, FIND("|", SUBSTITUTE(G51, "-", "|", 3)) + 1, LEN(G51)), 4) & " (Ref: " & H51 & ") (Type: " & P51 & ") (BU: " & L51 & ") (Head: " & M51 & ")", "Fund Transfer: From YES MASTER 0264 (Ref: " & H51 & ") (Type: " & P51 & ") (BU: " & L51 & ") (Head: " & M51 & ")")), IF(NOT(ISBLANK(J51)), IF(P51="Customer Collection", "Receipt: For " & IF(ISBLANK(T51), "", "(Apt#: " & T51 & ") ") & "(Ref: " & H51 & ") (" & IF(ISNUMBER(SEARCH("NEFT",G51)), "NEFT:", IF(ISNUMBER(SEARCH("RTGS",G51)), "RTGS:", IF(ISNUMBER(SEARCH("IMPS",G51)), "IMPS:", ""))) & " " & IF(ISNUMBER(SEARCH("SOHNA ROAD", G51)), "", IFERROR(MID(G51, FIND("-", G51, FIND("-", G51) + 1) + 1, LEN(G51)), SUBSTITUTE(SUBSTITUTE(SUBSTITUTE(G51, "IMPS/", ""), "NEFT/", ""), "RTGS/", ""))) & ") (Type: " & P51 & ") (BU: " & L51 & ")", IF(LEN(G51)-LEN(SUBSTITUTE(G51,"-",""))>=3, "Receipt: From x" & RIGHT(MID(G51, FIND("|", SUBSTITUTE(G51, "-", "|", 3)) + 1, LEN(G51)), 4) & " towards " & IF(ISBLANK(U51), L51, U51) & IF(OR(L51="Cancellation", L51="Collection"), " Apt No " & T51, "") & " (Ref: " & H51 & ") (Type: " & P51 & ") (BU: " & L51 & ") (Head: " & M51 & ")" & IF(ISBLANK(T51), "", " (Apt#: " & T51 & ")"), "Receipt: Against " & IF(ISBLANK(U51), L51, U51) & IF(OR(L51="Cancellation", L51="Collection"), " Apt No " & T51, "") & " (Ref: " & H51 & ") (Type: " & P51 & ") (BU: " & L51 & ") (Head: " & M51 & ")" & IF(ISBLANK(T51), "", " (Apt#: " & T51 & ")"))), IF(LEN(G51)-LEN(SUBSTITUTE(G51,"-",""))>=3, "Payment: To x" & RIGHT(MID(G51, FIND("|", SUBSTITUTE(G51, "-", "|", 3)) + 1, LEN(G51)), 4) & " for " & IF(ISBLANK(U51), L51, U51) & " (Ref: " & H51 & ") (Type: " & P51 & ") (BU: " & L51 & ") (Head: " & M51 & ")" & IF(ISBLANK(T51), "", " (Apt#: " & T51 & ")"), "Payment: Disbursement for " & IF(ISBLANK(U51), "", IF(ISBLANK(U51), "", U51) & " ") & "(Ref: " & H51 & ") (Type: " & P51 & ") (BU: " & L51 & ") (Head: " & M51 & ")" & IF(ISBLANK(T51), "", " (Apt#: " & T51 & ")"))))) -> Fund Transfer: From YES MASTER 0264 to x0377 (Ref: YESME6199005217500) (Type: Master 2 RERA) (BU: Casa Romana) (Head: Internal)
A52: 185 | B52: =IF(D52="","?",_xludf.IFS( MONTH(D52)<=3,"Q4", MONTH(D52)<=6,"Q1", MONTH(D52)<=9,"Q2", TRUE,"Q3" )) -> #NAME? | C52: =MONTH(D52) -> 7 | D52: 46219 | E52: 46219 | G52: NEFT Cr-ICIC0SF0002-POONAM KAUR-DWARKADHIS PROJECTS PRIVA-IN12619746786146 | H52: YES0N6197493849800 | J52: 25000 | K52: =K53+J52-I52 -> 54215.5 | L52: Casa Romana | M52: Collection | O52: Entry | P52: Customer Collection | Q52: Credit- no effect | T52: U-092 | V52: adjust | W52: =TRIM(IF(M52="Internal", IF(ISBLANK(G52), IF(LEN(G52)-LEN(SUBSTITUTE(G52,"-",""))>=3, "Fund Transfer: From x" & RIGHT(MID(G52, FIND("|", SUBSTITUTE(G52, "-", "|", 3)) + 1, LEN(G52)), 4) & " to YES MASTER 0264 (Ref: " & H52 & ") (Type: " & P52 & ") (BU: " & L52 & ") (Head: " & M52 & ")", "Fund Transfer: To YES MASTER 0264 (Ref: " & H52 & ") (Type: " & P52 & ") (BU: " & L52 & ") (Head: " & M52 & ")"), IF(LEN(G52)-LEN(SUBSTITUTE(G52,"-",""))>=3, "Fund Transfer: From YES MASTER 0264 to x" & RIGHT(MID(G52, FIND("|", SUBSTITUTE(G52, "-", "|", 3)) + 1, LEN(G52)), 4) & " (Ref: " & H52 & ") (Type: " & P52 & ") (BU: " & L52 & ") (Head: " & M52 & ")", "Fund Transfer: From YES MASTER 0264 (Ref: " & H52 & ") (Type: " & P52 & ") (BU: " & L52 & ") (Head: " & M52 & ")")), IF(NOT(ISBLANK(J52)), IF(P52="Customer Collection", "Receipt: For " & IF(ISBLANK(T52), "", "(Apt#: " & T52 & ") ") & "(Ref: " & H52 & ") (" & IF(ISNUMBER(SEARCH("NEFT",G52)), "NEFT:", IF(ISNUMBER(SEARCH("RTGS",G52)), "RTGS:", IF(ISNUMBER(SEARCH("IMPS",G52)), "IMPS:", ""))) & " " & IF(ISNUMBER(SEARCH("SOHNA ROAD", G52)), "", IFERROR(MID(G52, FIND("-", G52, FIND("-", G52) + 1) + 1, LEN(G52)), SUBSTITUTE(SUBSTITUTE(SUBSTITUTE(G52, "IMPS/", ""), "NEFT/", ""), "RTGS/", ""))) & ") (Type: " & P52 & ") (BU: " & L52 & ")", IF(LEN(G52)-LEN(SUBSTITUTE(G52,"-",""))>=3, "Receipt: From x" & RIGHT(MID(G52, FIND("|", SUBSTITUTE(G52, "-", "|", 3)) + 1, LEN(G52)), 4) & " towards " & IF(ISBLANK(U52), L52, U52) & IF(OR(L52="Cancellation", L52="Collection"), " Apt No " & T52, "") & " (Ref: " & H52 & ") (Type: " & P52 & ") (BU: " & L52 & ") (Head: " & M52 & ")" & IF(ISBLANK(T52), "", " (Apt#: " & T52 & ")"), "Receipt: Against " & IF(ISBLANK(U52), L52, U52) & IF(OR(L52="Cancellation", L52="Collection"), " Apt No " & T52, "") & " (Ref: " & H52 & ") (Type: " & P52 & ") (BU: " & L52 & ") (Head: " & M52 & ")" & IF(ISBLANK(T52), "", " (Apt#: " & T52 & ")"))), IF(LEN(G52)-LEN(SUBSTITUTE(G52,"-",""))>=3, "Payment: To x" & RIGHT(MID(G52, FIND("|", SUBSTITUTE(G52, "-", "|", 3)) + 1, LEN(G52)), 4) & " for " & IF(ISBLANK(U52), L52, U52) & " (Ref: " & H52 & ") (Type: " & P52 & ") (BU: " & L52 & ") (Head: " & M52 & ")" & IF(ISBLANK(T52), "", " (Apt#: " & T52 & ")"), "Payment: Disbursement for " & IF(ISBLANK(U52), "", IF(ISBLANK(U52), "", U52) & " ") & "(Ref: " & H52 & ") (Type: " & P52 & ") (BU: " & L52 & ") (Head: " & M52 & ")" & IF(ISBLANK(T52), "", " (Apt#: " & T52 & ")"))))) -> Receipt: For (Apt#: U-092) (Ref: YES0N6197493849800) (NEFT: POONAM KAUR-DWARKADHIS PROJECTS PRIVA-IN12619746786146) (Type: Customer Collection) (BU: Casa Romana)
A53: 184 | B53: =IF(D53="","?",_xludf.IFS( MONTH(D53)<=3,"Q4", MONTH(D53)<=6,"Q1", MONTH(D53)<=9,"Q2", TRUE,"Q3" )) -> #NAME? | C53: =MONTH(D53) -> 7 | D53: 46218 | E53: 46218 | G53: YIB-TPT-DWARKADHIS PROJECTS PRIVATE LIMITED-Internal-045563200000377 | H53: YESME6196003720000 | I53: 239841 | K53: =K54+J53-I53 -> 29215.5 | L53: Casa Romana | M53: Internal | O53: Entry | P53: Master 2 RERA | Q53: Internal transfer | W53: =TRIM(IF(M53="Internal", IF(ISBLANK(G53), IF(LEN(G53)-LEN(SUBSTITUTE(G53,"-",""))>=3, "Fund Transfer: From x" & RIGHT(MID(G53, FIND("|", SUBSTITUTE(G53, "-", "|", 3)) + 1, LEN(G53)), 4) & " to YES MASTER 0264 (Ref: " & H53 & ") (Type: " & P53 & ") (BU: " & L53 & ") (Head: " & M53 & ")", "Fund Transfer: To YES MASTER 0264 (Ref: " & H53 & ") (Type: " & P53 & ") (BU: " & L53 & ") (Head: " & M53 & ")"), IF(LEN(G53)-LEN(SUBSTITUTE(G53,"-",""))>=3, "Fund Transfer: From YES MASTER 0264 to x" & RIGHT(MID(G53, FIND("|", SUBSTITUTE(G53, "-", "|", 3)) + 1, LEN(G53)), 4) & " (Ref: " & H53 & ") (Type: " & P53 & ") (BU: " & L53 & ") (Head: " & M53 & ")", "Fund Transfer: From YES MASTER 0264 (Ref: " & H53 & ") (Type: " & P53 & ") (BU: " & L53 & ") (Head: " & M53 & ")")), IF(NOT(ISBLANK(J53)), IF(P53="Customer Collection", "Receipt: For " & IF(ISBLANK(T53), "", "(Apt#: " & T53 & ") ") & "(Ref: " & H53 & ") (" & IF(ISNUMBER(SEARCH("NEFT",G53)), "NEFT:", IF(ISNUMBER(SEARCH("RTGS",G53)), "RTGS:", IF(ISNUMBER(SEARCH("IMPS",G53)), "IMPS:", ""))) & " " & IF(ISNUMBER(SEARCH("SOHNA ROAD", G53)), "", IFERROR(MID(G53, FIND("-", G53, FIND("-", G53) + 1) + 1, LEN(G53)), SUBSTITUTE(SUBSTITUTE(SUBSTITUTE(G53, "IMPS/", ""), "NEFT/", ""), "RTGS/", ""))) & ") (Type: " & P53 & ") (BU: " & L53 & ")", IF(LEN(G53)-LEN(SUBSTITUTE(G53,"-",""))>=3, "Receipt: From x" & RIGHT(MID(G53, FIND("|", SUBSTITUTE(G53, "-", "|", 3)) + 1, LEN(G53)), 4) & " towards " & IF(ISBLANK(U53), L53, U53) & IF(OR(L53="Cancellation", L53="Collection"), " Apt No " & T53, "") & " (Ref: " & H53 & ") (Type: " & P53 & ") (BU: " & L53 & ") (Head: " & M53 & ")" & IF(ISBLANK(T53), "", " (Apt#: " & T53 & ")"), "Receipt: Against " & IF(ISBLANK(U53), L53, U53) & IF(OR(L53="Cancellation", L53="Collection"), " Apt No " & T53, "") & " (Ref: " & H53 & ") (Type: " & P53 & ") (BU: " & L53 & ") (Head: " & M53 & ")" & IF(ISBLANK(T53), "", " (Apt#: " & T53 & ")"))), IF(LEN(G53)-LEN(SUBSTITUTE(G53,"-",""))>=3, "Payment: To x" & RIGHT(MID(G53, FIND("|", SUBSTITUTE(G53, "-", "|", 3)) + 1, LEN(G53)), 4) & " for " & IF(ISBLANK(U53), L53, U53) & " (Ref: " & H53 & ") (Type: " & P53 & ") (BU: " & L53 & ") (Head: " & M53 & ")" & IF(ISBLANK(T53), "", " (Apt#: " & T53 & ")"), "Payment: Disbursement for " & IF(ISBLANK(U53), "", IF(ISBLANK(U53), "", U53) & " ") & "(Ref: " & H53 & ") (Type: " & P53 & ") (BU: " & L53 & ") (Head: " & M53 & ")" & IF(ISBLANK(T53), "", " (Apt#: " & T53 & ")"))))) -> Fund Transfer: From YES MASTER 0264 to x0377 (Ref: YESME6196003720000) (Type: Master 2 RERA) (BU: Casa Romana) (Head: Internal)
A54: 183 | B54: =IF(D54="","?",_xludf.IFS( MONTH(D54)<=3,"Q4", MONTH(D54)<=6,"Q1", MONTH(D54)<=9,"Q2", TRUE,"Q3" )) -> #NAME? | C54: =MONTH(D54) -> 7 | D54: 46218 | E54: 46218 | G54: YIB-TPT-Dwarkadhis Projects Pvt Ltd-Internal-045563400002477 | H54: YESME6196003934400 | I54: 102789 | K54: =K55+J54-I54 -> 269056.5 | L54: Casa Romana | M54: Internal | O54: Entry | P54: Master to Free | Q54: Internal transfer | W54: =TRIM(IF(M54="Internal", IF(ISBLANK(G54), IF(LEN(G54)-LEN(SUBSTITUTE(G54,"-",""))>=3, "Fund Transfer: From x" & RIGHT(MID(G54, FIND("|", SUBSTITUTE(G54, "-", "|", 3)) + 1, LEN(G54)), 4) & " to YES MASTER 0264 (Ref: " & H54 & ") (Type: " & P54 & ") (BU: " & L54 & ") (Head: " & M54 & ")", "Fund Transfer: To YES MASTER 0264 (Ref: " & H54 & ") (Type: " & P54 & ") (BU: " & L54 & ") (Head: " & M54 & ")"), IF(LEN(G54)-LEN(SUBSTITUTE(G54,"-",""))>=3, "Fund Transfer: From YES MASTER 0264 to x" & RIGHT(MID(G54, FIND("|", SUBSTITUTE(G54, "-", "|", 3)) + 1, LEN(G54)), 4) & " (Ref: " & H54 & ") (Type: " & P54 & ") (BU: " & L54 & ") (Head: " & M54 & ")", "Fund Transfer: From YES MASTER 0264 (Ref: " & H54 & ") (Type: " & P54 & ") (BU: " & L54 & ") (Head: " & M54 & ")")), IF(NOT(ISBLANK(J54)), IF(P54="Customer Collection", "Receipt: For " & IF(ISBLANK(T54), "", "(Apt#: " & T54 & ") ") & "(Ref: " & H54 & ") (" & IF(ISNUMBER(SEARCH("NEFT",G54)), "NEFT:", IF(ISNUMBER(SEARCH("RTGS",G54)), "RTGS:", IF(ISNUMBER(SEARCH("IMPS",G54)), "IMPS:", ""))) & " " & IF(ISNUMBER(SEARCH("SOHNA ROAD", G54)), "", IFERROR(MID(G54, FIND("-", G54, FIND("-", G54) + 1) + 1, LEN(G54)), SUBSTITUTE(SUBSTITUTE(SUBSTITUTE(G54, "IMPS/", ""), "NEFT/", ""), "RTGS/", ""))) & ") (Type: " & P54 & ") (BU: " & L54 & ")", IF(LEN(G54)-LEN(SUBSTITUTE(G54,"-",""))>=3, "Receipt: From x" & RIGHT(MID(G54, FIND("|", SUBSTITUTE(G54, "-", "|", 3)) + 1, LEN(G54)), 4) & " towards " & IF(ISBLANK(U54), L54, U54) & IF(OR(L54="Cancellation", L54="Collection"), " Apt No " & T54, "") & " (Ref: " & H54 & ") (Type: " & P54 & ") (BU: " & L54 & ") (Head: " & M54 & ")" & IF(ISBLANK(T54), "", " (Apt#: " & T54 & ")"), "Receipt: Against " & IF(ISBLANK(U54), L54, U54) & IF(OR(L54="Cancellation", L54="Collection"), " Apt No " & T54, "") & " (Ref: " & H54 & ") (Type: " & P54 & ") (BU: " & L54 & ") (Head: " & M54 & ")" & IF(ISBLANK(T54), "", " (Apt#: " & T54 & ")"))), IF(LEN(G54)-LEN(SUBSTITUTE(G54,"-",""))>=3, "Payment: To x" & RIGHT(MID(G54, FIND("|", SUBSTITUTE(G54, "-", "|", 3)) + 1, LEN(G54)), 4) & " for " & IF(ISBLANK(U54), L54, U54) & " (Ref: " & H54 & ") (Type: " & P54 & ") (BU: " & L54 & ") (Head: " & M54 & ")" & IF(ISBLANK(T54), "", " (Apt#: " & T54 & ")"), "Payment: Disbursement for " & IF(ISBLANK(U54), "", IF(ISBLANK(U54), "", U54) & " ") & "(Ref: " & H54 & ") (Type: " & P54 & ") (BU: " & L54 & ") (Head: " & M54 & ")" & IF(ISBLANK(T54), "", " (Apt#: " & T54 & ")"))))) -> Fund Transfer: From YES MASTER 0264 to x2477 (Ref: YESME6196003934400) (Type: Master to Free) (BU: Casa Romana) (Head: Internal)
A55: 182 | B55: =IF(D55="","?",_xludf.IFS( MONTH(D55)<=3,"Q4", MONTH(D55)<=6,"Q1", MONTH(D55)<=9,"Q2", TRUE,"Q3" )) -> #NAME? | C55: =MONTH(D55) -> 7 | D55: 46218 | E55: 46218 | G55: IMPS/SUNITA SUNITA/XXX8258/RRN:619612512425/STATE BANK OF INDIA | H55: YBP6196616883455 | J55: 194258 | K55: =K56+J55-I55 -> 371845.5 | L55: Casa Romana | M55: Collection | O55: Entry | P55: Customer Collection | Q55: Credit- no effect | T55: P-064 | V55: Adjust | W55: =TRIM(IF(M55="Internal", IF(ISBLANK(G55), IF(LEN(G55)-LEN(SUBSTITUTE(G55,"-",""))>=3, "Fund Transfer: From x" & RIGHT(MID(G55, FIND("|", SUBSTITUTE(G55, "-", "|", 3)) + 1, LEN(G55)), 4) & " to YES MASTER 0264 (Ref: " & H55 & ") (Type: " & P55 & ") (BU: " & L55 & ") (Head: " & M55 & ")", "Fund Transfer: To YES MASTER 0264 (Ref: " & H55 & ") (Type: " & P55 & ") (BU: " & L55 & ") (Head: " & M55 & ")"), IF(LEN(G55)-LEN(SUBSTITUTE(G55,"-",""))>=3, "Fund Transfer: From YES MASTER 0264 to x" & RIGHT(MID(G55, FIND("|", SUBSTITUTE(G55, "-", "|", 3)) + 1, LEN(G55)), 4) & " (Ref: " & H55 & ") (Type: " & P55 & ") (BU: " & L55 & ") (Head: " & M55 & ")", "Fund Transfer: From YES MASTER 0264 (Ref: " & H55 & ") (Type: " & P55 & ") (BU: " & L55 & ") (Head: " & M55 & ")")), IF(NOT(ISBLANK(J55)), IF(P55="Customer Collection", "Receipt: For " & IF(ISBLANK(T55), "", "(Apt#: " & T55 & ") ") & "(Ref: " & H55 & ") (" & IF(ISNUMBER(SEARCH("NEFT",G55)), "NEFT:", IF(ISNUMBER(SEARCH("RTGS",G55)), "RTGS:", IF(ISNUMBER(SEARCH("IMPS",G55)), "IMPS:", ""))) & " " & IF(ISNUMBER(SEARCH("SOHNA ROAD", G55)), "", IFERROR(MID(G55, FIND("-", G55, FIND("-", G55) + 1) + 1, LEN(G55)), SUBSTITUTE(SUBSTITUTE(SUBSTITUTE(G55, "IMPS/", ""), "NEFT/", ""), "RTGS/", ""))) & ") (Type: " & P55 & ") (BU: " & L55 & ")", IF(LEN(G55)-LEN(SUBSTITUTE(G55,"-",""))>=3, "Receipt: From x" & RIGHT(MID(G55, FIND("|", SUBSTITUTE(G55, "-", "|", 3)) + 1, LEN(G55)), 4) & " towards " & IF(ISBLANK(U55), L55, U55) & IF(OR(L55="Cancellation", L55="Collection"), " Apt No " & T55, "") & " (Ref: " & H55 & ") (Type: " & P55 & ") (BU: " & L55 & ") (Head: " & M55 & ")" & IF(ISBLANK(T55), "", " (Apt#: " & T55 & ")"), "Receipt: Against " & IF(ISBLANK(U55), L55, U55) & IF(OR(L55="Cancellation", L55="Collection"), " Apt No " & T55, "") & " (Ref: " & H55 & ") (Type: " & P55 & ") (BU: " & L55 & ") (Head: " & M55 & ")" & IF(ISBLANK(T55), "", " (Apt#: " & T55 & ")"))), IF(LEN(G55)-LEN(SUBSTITUTE(G55,"-",""))>=3, "Payment: To x" & RIGHT(MID(G55, FIND("|", SUBSTITUTE(G55, "-", "|", 3)) + 1, LEN(G55)), 4) & " for " & IF(ISBLANK(U55), L55, U55) & " (Ref: " & H55 & ") (Type: " & P55 & ") (BU: " & L55 & ") (Head: " & M55 & ")" & IF(ISBLANK(T55), "", " (Apt#: " & T55 & ")"), "Payment: Disbursement for " & IF(ISBLANK(U55), "", IF(ISBLANK(U55), "", U55) & " ") & "(Ref: " & H55 & ") (Type: " & P55 & ") (BU: " & L55 & ") (Head: " & M55 & ")" & IF(ISBLANK(T55), "", " (Apt#: " & T55 & ")"))))) -> Receipt: For (Apt#: P-064) (Ref: YBP6196616883455) (IMPS: SUNITA SUNITA/XXX8258/RRN:619612512425/STATE BANK OF INDIA) (Type: Customer Collection) (BU: Casa Romana)
A56: 181 | B56: =IF(D56="","?",_xludf.IFS( MONTH(D56)<=3,"Q4", MONTH(D56)<=6,"Q1", MONTH(D56)<=9,"Q2", TRUE,"Q3" )) -> #NAME? | C56: =MONTH(D56) -> 7 | D56: 46218 | E56: 46218 | G56: NEFT Cr-ICIC0SF0002-NEELKANT GUMMALLA-DWARKADHIS PROJECTS PRIVA-IN12619646598201 | H56: YES0N6196325504800 | J56: 148372 | K56: =K57+J56-I56 -> 177587.5 | L56: Casa Romana | M56: Collection | O56: Entry | P56: Customer Collection | Q56: Credit- no effect | T56: U-102 | V56: on account | W56: =TRIM(IF(M56="Internal", IF(ISBLANK(G56), IF(LEN(G56)-LEN(SUBSTITUTE(G56,"-",""))>=3, "Fund Transfer: From x" & RIGHT(MID(G56, FIND("|", SUBSTITUTE(G56, "-", "|", 3)) + 1, LEN(G56)), 4) & " to YES MASTER 0264 (Ref: " & H56 & ") (Type: " & P56 & ") (BU: " & L56 & ") (Head: " & M56 & ")", "Fund Transfer: To YES MASTER 0264 (Ref: " & H56 & ") (Type: " & P56 & ") (BU: " & L56 & ") (Head: " & M56 & ")"), IF(LEN(G56)-LEN(SUBSTITUTE(G56,"-",""))>=3, "Fund Transfer: From YES MASTER 0264 to x" & RIGHT(MID(G56, FIND("|", SUBSTITUTE(G56, "-", "|", 3)) + 1, LEN(G56)), 4) & " (Ref: " & H56 & ") (Type: " & P56 & ") (BU: " & L56 & ") (Head: " & M56 & ")", "Fund Transfer: From YES MASTER 0264 (Ref: " & H56 & ") (Type: " & P56 & ") (BU: " & L56 & ") (Head: " & M56 & ")")), IF(NOT(ISBLANK(J56)), IF(P56="Customer Collection", "Receipt: For " & IF(ISBLANK(T56), "", "(Apt#: " & T56 & ") ") & "(Ref: " & H56 & ") (" & IF(ISNUMBER(SEARCH("NEFT",G56)), "NEFT:", IF(ISNUMBER(SEARCH("RTGS",G56)), "RTGS:", IF(ISNUMBER(SEARCH("IMPS",G56)), "IMPS:", ""))) & " " & IF(ISNUMBER(SEARCH("SOHNA ROAD", G56)), "", IFERROR(MID(G56, FIND("-", G56, FIND("-", G56) + 1) + 1, LEN(G56)), SUBSTITUTE(SUBSTITUTE(SUBSTITUTE(G56, "IMPS/", ""), "NEFT/", ""), "RTGS/", ""))) & ") (Type: " & P56 & ") (BU: " & L56 & ")", IF(LEN(G56)-LEN(SUBSTITUTE(G56,"-",""))>=3, "Receipt: From x" & RIGHT(MID(G56, FIND("|", SUBSTITUTE(G56, "-", "|", 3)) + 1, LEN(G56)), 4) & " towards " & IF(ISBLANK(U56), L56, U56) & IF(OR(L56="Cancellation", L56="Collection"), " Apt No " & T56, "") & " (Ref: " & H56 & ") (Type: " & P56 & ") (BU: " & L56 & ") (Head: " & M56 & ")" & IF(ISBLANK(T56), "", " (Apt#: " & T56 & ")"), "Receipt: Against " & IF(ISBLANK(U56), L56, U56) & IF(OR(L56="Cancellation", L56="Collection"), " Apt No " & T56, "") & " (Ref: " & H56 & ") (Type: " & P56 & ") (BU: " & L56 & ") (Head: " & M56 & ")" & IF(ISBLANK(T56), "", " (Apt#: " & T56 & ")"))), IF(LEN(G56)-LEN(SUBSTITUTE(G56,"-",""))>=3, "Payment: To x" & RIGHT(MID(G56, FIND("|", SUBSTITUTE(G56, "-", "|", 3)) + 1, LEN(G56)), 4) & " for " & IF(ISBLANK(U56), L56, U56) & " (Ref: " & H56 & ") (Type: " & P56 & ") (BU: " & L56 & ") (Head: " & M56 & ")" & IF(ISBLANK(T56), "", " (Apt#: " & T56 & ")"), "Payment: Disbursement for " & IF(ISBLANK(U56), "", IF(ISBLANK(U56), "", U56) & " ") & "(Ref: " & H56 & ") (Type: " & P56 & ") (BU: " & L56 & ") (Head: " & M56 & ")" & IF(ISBLANK(T56), "", " (Apt#: " & T56 & ")"))))) -> Receipt: For (Apt#: U-102) (Ref: YES0N6196325504800) (NEFT: NEELKANT GUMMALLA-DWARKADHIS PROJECTS PRIVA-IN12619646598201) (Type: Customer Collection) (BU: Casa Romana) | X56: 0.05
A57: 180 | B57: =IF(D57="","?",_xludf.IFS( MONTH(D57)<=3,"Q4", MONTH(D57)<=6,"Q1", MONTH(D57)<=9,"Q2", TRUE,"Q3" )) -> #NAME? | C57: =MONTH(D57) -> 7 | D57: 46216 | E57: 46216 | G57: YIB-TPT-Dwarkadhis Projects Pvt Ltd-CRM To CRF-045563400002477 | H57: YESME6194005638000 | I57: 30000 | K57: =K58+J57-I57 -> 29215.5 | L57: Casa Romana | M57: Internal | O57: Entry | P57: Master to Free | Q57: Internal transfer | W57: =TRIM(IF(M57="Internal", IF(ISBLANK(G57), IF(LEN(G57)-LEN(SUBSTITUTE(G57,"-",""))>=3, "Fund Transfer: From x" & RIGHT(MID(G57, FIND("|", SUBSTITUTE(G57, "-", "|", 3)) + 1, LEN(G57)), 4) & " to YES MASTER 0264 (Ref: " & H57 & ") (Type: " & P57 & ") (BU: " & L57 & ") (Head: " & M57 & ")", "Fund Transfer: To YES MASTER 0264 (Ref: " & H57 & ") (Type: " & P57 & ") (BU: " & L57 & ") (Head: " & M57 & ")"), IF(LEN(G57)-LEN(SUBSTITUTE(G57,"-",""))>=3, "Fund Transfer: From YES MASTER 0264 to x" & RIGHT(MID(G57, FIND("|", SUBSTITUTE(G57, "-", "|", 3)) + 1, LEN(G57)), 4) & " (Ref: " & H57 & ") (Type: " & P57 & ") (BU: " & L57 & ") (Head: " & M57 & ")", "Fund Transfer: From YES MASTER 0264 (Ref: " & H57 & ") (Type: " & P57 & ") (BU: " & L57 & ") (Head: " & M57 & ")")), IF(NOT(ISBLANK(J57)), IF(P57="Customer Collection", "Receipt: For " & IF(ISBLANK(T57), "", "(Apt#: " & T57 & ") ") & "(Ref: " & H57 & ") (" & IF(ISNUMBER(SEARCH("NEFT",G57)), "NEFT:", IF(ISNUMBER(SEARCH("RTGS",G57)), "RTGS:", IF(ISNUMBER(SEARCH("IMPS",G57)), "IMPS:", ""))) & " " & IF(ISNUMBER(SEARCH("SOHNA ROAD", G57)), "", IFERROR(MID(G57, FIND("-", G57, FIND("-", G57) + 1) + 1, LEN(G57)), SUBSTITUTE(SUBSTITUTE(SUBSTITUTE(G57, "IMPS/", ""), "NEFT/", ""), "RTGS/", ""))) & ") (Type: " & P57 & ") (BU: " & L57 & ")", IF(LEN(G57)-LEN(SUBSTITUTE(G57,"-",""))>=3, "Receipt: From x" & RIGHT(MID(G57, FIND("|", SUBSTITUTE(G57, "-", "|", 3)) + 1, LEN(G57)), 4) & " towards " & IF(ISBLANK(U57), L57, U57) & IF(OR(L57="Cancellation", L57="Collection"), " Apt No " & T57, "") & " (Ref: " & H57 & ") (Type: " & P57 & ") (BU: " & L57 & ") (Head: " & M57 & ")" & IF(ISBLANK(T57), "", " (Apt#: " & T57 & ")"), "Receipt: Against " & IF(ISBLANK(U57), L57, U57) & IF(OR(L57="Cancellation", L57="Collection"), " Apt No " & T57, "") & " (Ref: " & H57 & ") (Type: " & P57 & ") (BU: " & L57 & ") (Head: " & M57 & ")" & IF(ISBLANK(T57), "", " (Apt#: " & T57 & ")"))), IF(LEN(G57)-LEN(SUBSTITUTE(G57,"-",""))>=3, "Payment: To x" & RIGHT(MID(G57, FIND("|", SUBSTITUTE(G57, "-", "|", 3)) + 1, LEN(G57)), 4) & " for " & IF(ISBLANK(U57), L57, U57) & " (Ref: " & H57 & ") (Type: " & P57 & ") (BU: " & L57 & ") (Head: " & M57 & ")" & IF(ISBLANK(T57), "", " (Apt#: " & T57 & ")"), "Payment: Disbursement for " & IF(ISBLANK(U57), "", IF(ISBLANK(U57), "", U57) & " ") & "(Ref: " & H57 & ") (Type: " & P57 & ") (BU: " & L57 & ") (Head: " & M57 & ")" & IF(ISBLANK(T57), "", " (Apt#: " & T57 & ")"))))) -> Fund Transfer: From YES MASTER 0264 to x2477 (Ref: YESME6194005638000) (Type: Master to Free) (BU: Casa Romana) (Head: Internal)
A58: 179 | B58: =IF(D58="","?",_xludf.IFS( MONTH(D58)<=3,"Q4", MONTH(D58)<=6,"Q1", MONTH(D58)<=9,"Q2", TRUE,"Q3" )) -> #NAME? | C58: =MONTH(D58) -> 7 | D58: 46216 | E58: 46216 | G58: YIB-TPT-DWARKADHIS PROJECTS PRIVATE LIMITED-CRM to CRR-045563200000377 | H58: YESME6194005637900 | I58: 70000 | K58: =K59+J58-I58 -> 59215.5 | L58: Casa Romana | M58: Internal | O58: Entry | P58: Master 2 RERA | Q58: Internal transfer | W58: =TRIM(IF(M58="Internal", IF(ISBLANK(G58), IF(LEN(G58)-LEN(SUBSTITUTE(G58,"-",""))>=3, "Fund Transfer: From x" & RIGHT(MID(G58, FIND("|", SUBSTITUTE(G58, "-", "|", 3)) + 1, LEN(G58)), 4) & " to YES MASTER 0264 (Ref: " & H58 & ") (Type: " & P58 & ") (BU: " & L58 & ") (Head: " & M58 & ")", "Fund Transfer: To YES MASTER 0264 (Ref: " & H58 & ") (Type: " & P58 & ") (BU: " & L58 & ") (Head: " & M58 & ")"), IF(LEN(G58)-LEN(SUBSTITUTE(G58,"-",""))>=3, "Fund Transfer: From YES MASTER 0264 to x" & RIGHT(MID(G58, FIND("|", SUBSTITUTE(G58, "-", "|", 3)) + 1, LEN(G58)), 4) & " (Ref: " & H58 & ") (Type: " & P58 & ") (BU: " & L58 & ") (Head: " & M58 & ")", "Fund Transfer: From YES MASTER 0264 (Ref: " & H58 & ") (Type: " & P58 & ") (BU: " & L58 & ") (Head: " & M58 & ")")), IF(NOT(ISBLANK(J58)), IF(P58="Customer Collection", "Receipt: For " & IF(ISBLANK(T58), "", "(Apt#: " & T58 & ") ") & "(Ref: " & H58 & ") (" & IF(ISNUMBER(SEARCH("NEFT",G58)), "NEFT:", IF(ISNUMBER(SEARCH("RTGS",G58)), "RTGS:", IF(ISNUMBER(SEARCH("IMPS",G58)), "IMPS:", ""))) & " " & IF(ISNUMBER(SEARCH("SOHNA ROAD", G58)), "", IFERROR(MID(G58, FIND("-", G58, FIND("-", G58) + 1) + 1, LEN(G58)), SUBSTITUTE(SUBSTITUTE(SUBSTITUTE(G58, "IMPS/", ""), "NEFT/", ""), "RTGS/", ""))) & ") (Type: " & P58 & ") (BU: " & L58 & ")", IF(LEN(G58)-LEN(SUBSTITUTE(G58,"-",""))>=3, "Receipt: From x" & RIGHT(MID(G58, FIND("|", SUBSTITUTE(G58, "-", "|", 3)) + 1, LEN(G58)), 4) & " towards " & IF(ISBLANK(U58), L58, U58) & IF(OR(L58="Cancellation", L58="Collection"), " Apt No " & T58, "") & " (Ref: " & H58 & ") (Type: " & P58 & ") (BU: " & L58 & ") (Head: " & M58 & ")" & IF(ISBLANK(T58), "", " (Apt#: " & T58 & ")"), "Receipt: Against " & IF(ISBLANK(U58), L58, U58) & IF(OR(L58="Cancellation", L58="Collection"), " Apt No " & T58, "") & " (Ref: " & H58 & ") (Type: " & P58 & ") (BU: " & L58 & ") (Head: " & M58 & ")" & IF(ISBLANK(T58), "", " (Apt#: " & T58 & ")"))), IF(LEN(G58)-LEN(SUBSTITUTE(G58,"-",""))>=3, "Payment: To x" & RIGHT(MID(G58, FIND("|", SUBSTITUTE(G58, "-", "|", 3)) + 1, LEN(G58)), 4) & " for " & IF(ISBLANK(U58), L58, U58) & " (Ref: " & H58 & ") (Type: " & P58 & ") (BU: " & L58 & ") (Head: " & M58 & ")" & IF(ISBLANK(T58), "", " (Apt#: " & T58 & ")"), "Payment: Disbursement for " & IF(ISBLANK(U58), "", IF(ISBLANK(U58), "", U58) & " ") & "(Ref: " & H58 & ") (Type: " & P58 & ") (BU: " & L58 & ") (Head: " & M58 & ")" & IF(ISBLANK(T58), "", " (Apt#: " & T58 & ")"))))) -> Fund Transfer: From YES MASTER 0264 to x0377 (Ref: YESME6194005637900) (Type: Master 2 RERA) (BU: Casa Romana) (Head: Internal)
A59: 178 | B59: =IF(D59="","?",_xludf.IFS( MONTH(D59)<=3,"Q4", MONTH(D59)<=6,"Q1", MONTH(D59)<=9,"Q2", TRUE,"Q3" )) -> #NAME? | C59: =MONTH(D59) -> 7 | D59: 46215 | E59: 46215 | G59: IMPS/MRIGANKACHAKRABORTY/XXX7113/RRN:619321078962/AXIS BANK | H59: YBP6193613167067 | J59: 100000 | K59: =K60+J59-I59 -> 129215.5 | L59: Casa Romana | M59: Collection | O59: Entry | P59: Customer Collection | Q59: Credit- no effect | T59: P-071 | V59: Adjust | W59: =TRIM(IF(M59="Internal", IF(ISBLANK(G59), IF(LEN(G59)-LEN(SUBSTITUTE(G59,"-",""))>=3, "Fund Transfer: From x" & RIGHT(MID(G59, FIND("|", SUBSTITUTE(G59, "-", "|", 3)) + 1, LEN(G59)), 4) & " to YES MASTER 0264 (Ref: " & H59 & ") (Type: " & P59 & ") (BU: " & L59 & ") (Head: " & M59 & ")", "Fund Transfer: To YES MASTER 0264 (Ref: " & H59 & ") (Type: " & P59 & ") (BU: " & L59 & ") (Head: " & M59 & ")"), IF(LEN(G59)-LEN(SUBSTITUTE(G59,"-",""))>=3, "Fund Transfer: From YES MASTER 0264 to x" & RIGHT(MID(G59, FIND("|", SUBSTITUTE(G59, "-", "|", 3)) + 1, LEN(G59)), 4) & " (Ref: " & H59 & ") (Type: " & P59 & ") (BU: " & L59 & ") (Head: " & M59 & ")", "Fund Transfer: From YES MASTER 0264 (Ref: " & H59 & ") (Type: " & P59 & ") (BU: " & L59 & ") (Head: " & M59 & ")")), IF(NOT(ISBLANK(J59)), IF(P59="Customer Collection", "Receipt: For " & IF(ISBLANK(T59), "", "(Apt#: " & T59 & ") ") & "(Ref: " & H59 & ") (" & IF(ISNUMBER(SEARCH("NEFT",G59)), "NEFT:", IF(ISNUMBER(SEARCH("RTGS",G59)), "RTGS:", IF(ISNUMBER(SEARCH("IMPS",G59)), "IMPS:", ""))) & " " & IF(ISNUMBER(SEARCH("SOHNA ROAD", G59)), "", IFERROR(MID(G59, FIND("-", G59, FIND("-", G59) + 1) + 1, LEN(G59)), SUBSTITUTE(SUBSTITUTE(SUBSTITUTE(G59, "IMPS/", ""), "NEFT/", ""), "RTGS/", ""))) & ") (Type: " & P59 & ") (BU: " & L59 & ")", IF(LEN(G59)-LEN(SUBSTITUTE(G59,"-",""))>=3, "Receipt: From x" & RIGHT(MID(G59, FIND("|", SUBSTITUTE(G59, "-", "|", 3)) + 1, LEN(G59)), 4) & " towards " & IF(ISBLANK(U59), L59, U59) & IF(OR(L59="Cancellation", L59="Collection"), " Apt No " & T59, "") & " (Ref: " & H59 & ") (Type: " & P59 & ") (BU: " & L59 & ") (Head: " & M59 & ")" & IF(ISBLANK(T59), "", " (Apt#: " & T59 & ")"), "Receipt: Against " & IF(ISBLANK(U59), L59, U59) & IF(OR(L59="Cancellation", L59="Collection"), " Apt No " & T59, "") & " (Ref: " & H59 & ") (Type: " & P59 & ") (BU: " & L59 & ") (Head: " & M59 & ")" & IF(ISBLANK(T59), "", " (Apt#: " & T59 & ")"))), IF(LEN(G59)-LEN(SUBSTITUTE(G59,"-",""))>=3, "Payment: To x" & RIGHT(MID(G59, FIND("|", SUBSTITUTE(G59, "-", "|", 3)) + 1, LEN(G59)), 4) & " for " & IF(ISBLANK(U59), L59, U59) & " (Ref: " & H59 & ") (Type: " & P59 & ") (BU: " & L59 & ") (Head: " & M59 & ")" & IF(ISBLANK(T59), "", " (Apt#: " & T59 & ")"), "Payment: Disbursement for " & IF(ISBLANK(U59), "", IF(ISBLANK(U59), "", U59) & " ") & "(Ref: " & H59 & ") (Type: " & P59 & ") (BU: " & L59 & ") (Head: " & M59 & ")" & IF(ISBLANK(T59), "", " (Apt#: " & T59 & ")"))))) -> Receipt: For (Apt#: P-071) (Ref: YBP6193613167067) (IMPS: MRIGANKACHAKRABORTY/XXX7113/RRN:619321078962/AXIS BANK) (Type: Customer Collection) (BU: Casa Romana)
A60: 177 | B60: =IF(D60="","?",_xludf.IFS( MONTH(D60)<=3,"Q4", MONTH(D60)<=6,"Q1", MONTH(D60)<=9,"Q2", TRUE,"Q3" )) -> #NAME? | C60: =MONTH(D60) -> 7 | D60: 46214 | E60: 46214 | G60: YIB-TPT-Dwarkadhis Projects Pvt Ltd-Internal-045563400002477 | H60: YESME6192004439900 | I60: 54510 | K60: =K61+J60-I60 -> 29215.5 | L60: Casa Romana | M60: Internal | O60: Entry | P60: Master to Free | Q60: Internal transfer | W60: =TRIM(IF(M60="Internal", IF(ISBLANK(G60), IF(LEN(G60)-LEN(SUBSTITUTE(G60,"-",""))>=3, "Fund Transfer: From x" & RIGHT(MID(G60, FIND("|", SUBSTITUTE(G60, "-", "|", 3)) + 1, LEN(G60)), 4) & " to YES MASTER 0264 (Ref: " & H60 & ") (Type: " & P60 & ") (BU: " & L60 & ") (Head: " & M60 & ")", "Fund Transfer: To YES MASTER 0264 (Ref: " & H60 & ") (Type: " & P60 & ") (BU: " & L60 & ") (Head: " & M60 & ")"), IF(LEN(G60)-LEN(SUBSTITUTE(G60,"-",""))>=3, "Fund Transfer: From YES MASTER 0264 to x" & RIGHT(MID(G60, FIND("|", SUBSTITUTE(G60, "-", "|", 3)) + 1, LEN(G60)), 4) & " (Ref: " & H60 & ") (Type: " & P60 & ") (BU: " & L60 & ") (Head: " & M60 & ")", "Fund Transfer: From YES MASTER 0264 (Ref: " & H60 & ") (Type: " & P60 & ") (BU: " & L60 & ") (Head: " & M60 & ")")), IF(NOT(ISBLANK(J60)), IF(P60="Customer Collection", "Receipt: For " & IF(ISBLANK(T60), "", "(Apt#: " & T60 & ") ") & "(Ref: " & H60 & ") (" & IF(ISNUMBER(SEARCH("NEFT",G60)), "NEFT:", IF(ISNUMBER(SEARCH("RTGS",G60)), "RTGS:", IF(ISNUMBER(SEARCH("IMPS",G60)), "IMPS:", ""))) & " " & IF(ISNUMBER(SEARCH("SOHNA ROAD", G60)), "", IFERROR(MID(G60, FIND("-", G60, FIND("-", G60) + 1) + 1, LEN(G60)), SUBSTITUTE(SUBSTITUTE(SUBSTITUTE(G60, "IMPS/", ""), "NEFT/", ""), "RTGS/", ""))) & ") (Type: " & P60 & ") (BU: " & L60 & ")", IF(LEN(G60)-LEN(SUBSTITUTE(G60,"-",""))>=3, "Receipt: From x" & RIGHT(MID(G60, FIND("|", SUBSTITUTE(G60, "-", "|", 3)) + 1, LEN(G60)), 4) & " towards " & IF(ISBLANK(U60), L60, U60) & IF(OR(L60="Cancellation", L60="Collection"), " Apt No " & T60, "") & " (Ref: " & H60 & ") (Type: " & P60 & ") (BU: " & L60 & ") (Head: " & M60 & ")" & IF(ISBLANK(T60), "", " (Apt#: " & T60 & ")"), "Receipt: Against " & IF(ISBLANK(U60), L60, U60) & IF(OR(L60="Cancellation", L60="Collection"), " Apt No " & T60, "") & " (Ref: " & H60 & ") (Type: " & P60 & ") (BU: " & L60 & ") (Head: " & M60 & ")" & IF(ISBLANK(T60), "", " (Apt#: " & T60 & ")"))), IF(LEN(G60)-LEN(SUBSTITUTE(G60,"-",""))>=3, "Payment: To x" & RIGHT(MID(G60, FIND("|", SUBSTITUTE(G60, "-", "|", 3)) + 1, LEN(G60)), 4) & " for " & IF(ISBLANK(U60), L60, U60) & " (Ref: " & H60 & ") (Type: " & P60 & ") (BU: " & L60 & ") (Head: " & M60 & ")" & IF(ISBLANK(T60), "", " (Apt#: " & T60 & ")"), "Payment: Disbursement for " & IF(ISBLANK(U60), "", IF(ISBLANK(U60), "", U60) & " ") & "(Ref: " & H60 & ") (Type: " & P60 & ") (BU: " & L60 & ") (Head: " & M60 & ")" & IF(ISBLANK(T60), "", " (Apt#: " & T60 & ")"))))) -> Fund Transfer: From YES MASTER 0264 to x2477 (Ref: YESME6192004439900) (Type: Master to Free) (BU: Casa Romana) (Head: Internal)
A61: 176 | B61: =IF(D61="","?",_xludf.IFS( MONTH(D61)<=3,"Q4", MONTH(D61)<=6,"Q1", MONTH(D61)<=9,"Q2", TRUE,"Q3" )) -> #NAME? | C61: =MONTH(D61) -> 7 | D61: 46214 | E61: 46214 | G61: YIB-TPT-DWARKADHIS PROJECTS PRIVATE LIMITED-Internal-045563200000377 | H61: YESME6192004439800 | I61: 127190 | K61: =K62+J61-I61 -> 83725.5 | L61: Casa Romana | M61: Internal | O61: Entry | P61: Master 2 RERA | Q61: Internal transfer | W61: =TRIM(IF(M61="Internal", IF(ISBLANK(G61), IF(LEN(G61)-LEN(SUBSTITUTE(G61,"-",""))>=3, "Fund Transfer: From x" & RIGHT(MID(G61, FIND("|", SUBSTITUTE(G61, "-", "|", 3)) + 1, LEN(G61)), 4) & " to YES MASTER 0264 (Ref: " & H61 & ") (Type: " & P61 & ") (BU: " & L61 & ") (Head: " & M61 & ")", "Fund Transfer: To YES MASTER 0264 (Ref: " & H61 & ") (Type: " & P61 & ") (BU: " & L61 & ") (Head: " & M61 & ")"), IF(LEN(G61)-LEN(SUBSTITUTE(G61,"-",""))>=3, "Fund Transfer: From YES MASTER 0264 to x" & RIGHT(MID(G61, FIND("|", SUBSTITUTE(G61, "-", "|", 3)) + 1, LEN(G61)), 4) & " (Ref: " & H61 & ") (Type: " & P61 & ") (BU: " & L61 & ") (Head: " & M61 & ")", "Fund Transfer: From YES MASTER 0264 (Ref: " & H61 & ") (Type: " & P61 & ") (BU: " & L61 & ") (Head: " & M61 & ")")), IF(NOT(ISBLANK(J61)), IF(P61="Customer Collection", "Receipt: For " & IF(ISBLANK(T61), "", "(Apt#: " & T61 & ") ") & "(Ref: " & H61 & ") (" & IF(ISNUMBER(SEARCH("NEFT",G61)), "NEFT:", IF(ISNUMBER(SEARCH("RTGS",G61)), "RTGS:", IF(ISNUMBER(SEARCH("IMPS",G61)), "IMPS:", ""))) & " " & IF(ISNUMBER(SEARCH("SOHNA ROAD", G61)), "", IFERROR(MID(G61, FIND("-", G61, FIND("-", G61) + 1) + 1, LEN(G61)), SUBSTITUTE(SUBSTITUTE(SUBSTITUTE(G61, "IMPS/", ""), "NEFT/", ""), "RTGS/", ""))) & ") (Type: " & P61 & ") (BU: " & L61 & ")", IF(LEN(G61)-LEN(SUBSTITUTE(G61,"-",""))>=3, "Receipt: From x" & RIGHT(MID(G61, FIND("|", SUBSTITUTE(G61, "-", "|", 3)) + 1, LEN(G61)), 4) & " towards " & IF(ISBLANK(U61), L61, U61) & IF(OR(L61="Cancellation", L61="Collection"), " Apt No " & T61, "") & " (Ref: " & H61 & ") (Type: " & P61 & ") (BU: " & L61 & ") (Head: " & M61 & ")" & IF(ISBLANK(T61), "", " (Apt#: " & T61 & ")"), "Receipt: Against " & IF(ISBLANK(U61), L61, U61) & IF(OR(L61="Cancellation", L61="Collection"), " Apt No " & T61, "") & " (Ref: " & H61 & ") (Type: " & P61 & ") (BU: " & L61 & ") (Head: " & M61 & ")" & IF(ISBLANK(T61), "", " (Apt#: " & T61 & ")"))), IF(LEN(G61)-LEN(SUBSTITUTE(G61,"-",""))>=3, "Payment: To x" & RIGHT(MID(G61, FIND("|", SUBSTITUTE(G61, "-", "|", 3)) + 1, LEN(G61)), 4) & " for " & IF(ISBLANK(U61), L61, U61) & " (Ref: " & H61 & ") (Type: " & P61 & ") (BU: " & L61 & ") (Head: " & M61 & ")" & IF(ISBLANK(T61), "", " (Apt#: " & T61 & ")"), "Payment: Disbursement for " & IF(ISBLANK(U61), "", IF(ISBLANK(U61), "", U61) & " ") & "(Ref: " & H61 & ") (Type: " & P61 & ") (BU: " & L61 & ") (Head: " & M61 & ")" & IF(ISBLANK(T61), "", " (Apt#: " & T61 & ")"))))) -> Fund Transfer: From YES MASTER 0264 to x0377 (Ref: YESME6192004439800) (Type: Master 2 RERA) (BU: Casa Romana) (Head: Internal)
A62: 175 | B62: =IF(D62="","?",_xludf.IFS( MONTH(D62)<=3,"Q4", MONTH(D62)<=6,"Q1", MONTH(D62)<=9,"Q2", TRUE,"Q3" )) -> #NAME? | C62: =MONTH(D62) -> 7 | D62: 46213 | E62: 46213 | G62: CHQ DEP CBI 10-JUL-26 SAKET | H62: 412307 | J62: 34039 | K62: =K63+J62-I62 -> 210915.5 | L62: Casa Romana | M62: Collection | O62: Entry | P62: Customer Collection | Q62: Credit- no effect | T62: M-072 | U62: JOGINDER PAUL SUD | V62: as on 21-July adjust | W62: =TRIM(IF(M62="Internal", IF(ISBLANK(G62), IF(LEN(G62)-LEN(SUBSTITUTE(G62,"-",""))>=3, "Fund Transfer: From x" & RIGHT(MID(G62, FIND("|", SUBSTITUTE(G62, "-", "|", 3)) + 1, LEN(G62)), 4) & " to YES MASTER 0264 (Ref: " & H62 & ") (Type: " & P62 & ") (BU: " & L62 & ") (Head: " & M62 & ")", "Fund Transfer: To YES MASTER 0264 (Ref: " & H62 & ") (Type: " & P62 & ") (BU: " & L62 & ") (Head: " & M62 & ")"), IF(LEN(G62)-LEN(SUBSTITUTE(G62,"-",""))>=3, "Fund Transfer: From YES MASTER 0264 to x" & RIGHT(MID(G62, FIND("|", SUBSTITUTE(G62, "-", "|", 3)) + 1, LEN(G62)), 4) & " (Ref: " & H62 & ") (Type: " & P62 & ") (BU: " & L62 & ") (Head: " & M62 & ")", "Fund Transfer: From YES MASTER 0264 (Ref: " & H62 & ") (Type: " & P62 & ") (BU: " & L62 & ") (Head: " & M62 & ")")), IF(NOT(ISBLANK(J62)), IF(P62="Customer Collection", "Receipt: For " & IF(ISBLANK(T62), "", "(Apt#: " & T62 & ") ") & "(Ref: " & H62 & ") (" & IF(ISNUMBER(SEARCH("NEFT",G62)), "NEFT:", IF(ISNUMBER(SEARCH("RTGS",G62)), "RTGS:", IF(ISNUMBER(SEARCH("IMPS",G62)), "IMPS:", ""))) & " " & IF(ISNUMBER(SEARCH("SOHNA ROAD", G62)), "", IFERROR(MID(G62, FIND("-", G62, FIND("-", G62) + 1) + 1, LEN(G62)), SUBSTITUTE(SUBSTITUTE(SUBSTITUTE(G62, "IMPS/", ""), "NEFT/", ""), "RTGS/", ""))) & ") (Type: " & P62 & ") (BU: " & L62 & ")", IF(LEN(G62)-LEN(SUBSTITUTE(G62,"-",""))>=3, "Receipt: From x" & RIGHT(MID(G62, FIND("|", SUBSTITUTE(G62, "-", "|", 3)) + 1, LEN(G62)), 4) & " towards " & IF(ISBLANK(U62), L62, U62) & IF(OR(L62="Cancellation", L62="Collection"), " Apt No " & T62, "") & " (Ref: " & H62 & ") (Type: " & P62 & ") (BU: " & L62 & ") (Head: " & M62 & ")" & IF(ISBLANK(T62), "", " (Apt#: " & T62 & ")"), "Receipt: Against " & IF(ISBLANK(U62), L62, U62) & IF(OR(L62="Cancellation", L62="Collection"), " Apt No " & T62, "") & " (Ref: " & H62 & ") (Type: " & P62 & ") (BU: " & L62 & ") (Head: " & M62 & ")" & IF(ISBLANK(T62), "", " (Apt#: " & T62 & ")"))), IF(LEN(G62)-LEN(SUBSTITUTE(G62,"-",""))>=3, "Payment: To x" & RIGHT(MID(G62, FIND("|", SUBSTITUTE(G62, "-", "|", 3)) + 1, LEN(G62)), 4) & " for " & IF(ISBLANK(U62), L62, U62) & " (Ref: " & H62 & ") (Type: " & P62 & ") (BU: " & L62 & ") (Head: " & M62 & ")" & IF(ISBLANK(T62), "", " (Apt#: " & T62 & ")"), "Payment: Disbursement for " & IF(ISBLANK(U62), "", IF(ISBLANK(U62), "", U62) & " ") & "(Ref: " & H62 & ") (Type: " & P62 & ") (BU: " & L62 & ") (Head: " & M62 & ")" & IF(ISBLANK(T62), "", " (Apt#: " & T62 & ")"))))) -> Receipt: For (Apt#: M-072) (Ref: 412307) ( 26 SAKET) (Type: Customer Collection) (BU: Casa Romana)
A63: 174 | B63: =IF(D63="","?",_xludf.IFS( MONTH(D63)<=3,"Q4", MONTH(D63)<=6,"Q1", MONTH(D63)<=9,"Q2", TRUE,"Q3" )) -> #NAME? | C63: =MONTH(D63) -> 7 | D63: 46213 | E63: 46213 | G63: IMPS/ABHIJEET ./XXX1052/RRN:619113959999/ | H63: YBP6191609955191 | J63: 147661 | K63: =K64+J63-I63 -> 176876.5 | L63: Casa Romana | M63: Collection | O63: Entry | P63: Customer Collection | Q63: Credit- no effect | T63: N-124 | V63: adjust | W63: =TRIM(IF(M63="Internal", IF(ISBLANK(G63), IF(LEN(G63)-LEN(SUBSTITUTE(G63,"-",""))>=3, "Fund Transfer: From x" & RIGHT(MID(G63, FIND("|", SUBSTITUTE(G63, "-", "|", 3)) + 1, LEN(G63)), 4) & " to YES MASTER 0264 (Ref: " & H63 & ") (Type: " & P63 & ") (BU: " & L63 & ") (Head: " & M63 & ")", "Fund Transfer: To YES MASTER 0264 (Ref: " & H63 & ") (Type: " & P63 & ") (BU: " & L63 & ") (Head: " & M63 & ")"), IF(LEN(G63)-LEN(SUBSTITUTE(G63,"-",""))>=3, "Fund Transfer: From YES MASTER 0264 to x" & RIGHT(MID(G63, FIND("|", SUBSTITUTE(G63, "-", "|", 3)) + 1, LEN(G63)), 4) & " (Ref: " & H63 & ") (Type: " & P63 & ") (BU: " & L63 & ") (Head: " & M63 & ")", "Fund Transfer: From YES MASTER 0264 (Ref: " & H63 & ") (Type: " & P63 & ") (BU: " & L63 & ") (Head: " & M63 & ")")), IF(NOT(ISBLANK(J63)), IF(P63="Customer Collection", "Receipt: For " & IF(ISBLANK(T63), "", "(Apt#: " & T63 & ") ") & "(Ref: " & H63 & ") (" & IF(ISNUMBER(SEARCH("NEFT",G63)), "NEFT:", IF(ISNUMBER(SEARCH("RTGS",G63)), "RTGS:", IF(ISNUMBER(SEARCH("IMPS",G63)), "IMPS:", ""))) & " " & IF(ISNUMBER(SEARCH("SOHNA ROAD", G63)), "", IFERROR(MID(G63, FIND("-", G63, FIND("-", G63) + 1) + 1, LEN(G63)), SUBSTITUTE(SUBSTITUTE(SUBSTITUTE(G63, "IMPS/", ""), "NEFT/", ""), "RTGS/", ""))) & ") (Type: " & P63 & ") (BU: " & L63 & ")", IF(LEN(G63)-LEN(SUBSTITUTE(G63,"-",""))>=3, "Receipt: From x" & RIGHT(MID(G63, FIND("|", SUBSTITUTE(G63, "-", "|", 3)) + 1, LEN(G63)), 4) & " towards " & IF(ISBLANK(U63), L63, U63) & IF(OR(L63="Cancellation", L63="Collection"), " Apt No " & T63, "") & " (Ref: " & H63 & ") (Type: " & P63 & ") (BU: " & L63 & ") (Head: " & M63 & ")" & IF(ISBLANK(T63), "", " (Apt#: " & T63 & ")"), "Receipt: Against " & IF(ISBLANK(U63), L63, U63) & IF(OR(L63="Cancellation", L63="Collection"), " Apt No " & T63, "") & " (Ref: " & H63 & ") (Type: " & P63 & ") (BU: " & L63 & ") (Head: " & M63 & ")" & IF(ISBLANK(T63), "", " (Apt#: " & T63 & ")"))), IF(LEN(G63)-LEN(SUBSTITUTE(G63,"-",""))>=3, "Payment: To x" & RIGHT(MID(G63, FIND("|", SUBSTITUTE(G63, "-", "|", 3)) + 1, LEN(G63)), 4) & " for " & IF(ISBLANK(U63), L63, U63) & " (Ref: " & H63 & ") (Type: " & P63 & ") (BU: " & L63 & ") (Head: " & M63 & ")" & IF(ISBLANK(T63), "", " (Apt#: " & T63 & ")"), "Payment: Disbursement for " & IF(ISBLANK(U63), "", IF(ISBLANK(U63), "", U63) & " ") & "(Ref: " & H63 & ") (Type: " & P63 & ") (BU: " & L63 & ") (Head: " & M63 & ")" & IF(ISBLANK(T63), "", " (Apt#: " & T63 & ")"))))) -> Receipt: For (Apt#: N-124) (Ref: YBP6191609955191) (IMPS: ABHIJEET ./XXX1052/RRN:619113959999/) (Type: Customer Collection) (BU: Casa Romana)
A64: 173 | B64: =IF(D64="","?",_xludf.IFS( MONTH(D64)<=3,"Q4", MONTH(D64)<=6,"Q1", MONTH(D64)<=9,"Q2", TRUE,"Q3" )) -> #NAME? | C64: =MONTH(D64) -> 7 | D64: 46211 | E64: 46211 | G64: YIB-TPT-Dwarkadhis Projects Pvt Ltd-tfr F-045563400002477 | H64: YESME6189005399100 | I64: 82500 | K64: =K65+J64-I64 -> 29215.5 | L64: Casa Romana | M64: Internal | O64: Entry | P64: Master to Free | Q64: Internal transfer | W64: =TRIM(IF(M64="Internal", IF(ISBLANK(G64), IF(LEN(G64)-LEN(SUBSTITUTE(G64,"-",""))>=3, "Fund Transfer: From x" & RIGHT(MID(G64, FIND("|", SUBSTITUTE(G64, "-", "|", 3)) + 1, LEN(G64)), 4) & " to YES MASTER 0264 (Ref: " & H64 & ") (Type: " & P64 & ") (BU: " & L64 & ") (Head: " & M64 & ")", "Fund Transfer: To YES MASTER 0264 (Ref: " & H64 & ") (Type: " & P64 & ") (BU: " & L64 & ") (Head: " & M64 & ")"), IF(LEN(G64)-LEN(SUBSTITUTE(G64,"-",""))>=3, "Fund Transfer: From YES MASTER 0264 to x" & RIGHT(MID(G64, FIND("|", SUBSTITUTE(G64, "-", "|", 3)) + 1, LEN(G64)), 4) & " (Ref: " & H64 & ") (Type: " & P64 & ") (BU: " & L64 & ") (Head: " & M64 & ")", "Fund Transfer: From YES MASTER 0264 (Ref: " & H64 & ") (Type: " & P64 & ") (BU: " & L64 & ") (Head: " & M64 & ")")), IF(NOT(ISBLANK(J64)), IF(P64="Customer Collection", "Receipt: For " & IF(ISBLANK(T64), "", "(Apt#: " & T64 & ") ") & "(Ref: " & H64 & ") (" & IF(ISNUMBER(SEARCH("NEFT",G64)), "NEFT:", IF(ISNUMBER(SEARCH("RTGS",G64)), "RTGS:", IF(ISNUMBER(SEARCH("IMPS",G64)), "IMPS:", ""))) & " " & IF(ISNUMBER(SEARCH("SOHNA ROAD", G64)), "", IFERROR(MID(G64, FIND("-", G64, FIND("-", G64) + 1) + 1, LEN(G64)), SUBSTITUTE(SUBSTITUTE(SUBSTITUTE(G64, "IMPS/", ""), "NEFT/", ""), "RTGS/", ""))) & ") (Type: " & P64 & ") (BU: " & L64 & ")", IF(LEN(G64)-LEN(SUBSTITUTE(G64,"-",""))>=3, "Receipt: From x" & RIGHT(MID(G64, FIND("|", SUBSTITUTE(G64, "-", "|", 3)) + 1, LEN(G64)), 4) & " towards " & IF(ISBLANK(U64), L64, U64) & IF(OR(L64="Cancellation", L64="Collection"), " Apt No " & T64, "") & " (Ref: " & H64 & ") (Type: " & P64 & ") (BU: " & L64 & ") (Head: " & M64 & ")" & IF(ISBLANK(T64), "", " (Apt#: " & T64 & ")"), "Receipt: Against " & IF(ISBLANK(U64), L64, U64) & IF(OR(L64="Cancellation", L64="Collection"), " Apt No " & T64, "") & " (Ref: " & H64 & ") (Type: " & P64 & ") (BU: " & L64 & ") (Head: " & M64 & ")" & IF(ISBLANK(T64), "", " (Apt#: " & T64 & ")"))), IF(LEN(G64)-LEN(SUBSTITUTE(G64,"-",""))>=3, "Payment: To x" & RIGHT(MID(G64, FIND("|", SUBSTITUTE(G64, "-", "|", 3)) + 1, LEN(G64)), 4) & " for " & IF(ISBLANK(U64), L64, U64) & " (Ref: " & H64 & ") (Type: " & P64 & ") (BU: " & L64 & ") (Head: " & M64 & ")" & IF(ISBLANK(T64), "", " (Apt#: " & T64 & ")"), "Payment: Disbursement for " & IF(ISBLANK(U64), "", IF(ISBLANK(U64), "", U64) & " ") & "(Ref: " & H64 & ") (Type: " & P64 & ") (BU: " & L64 & ") (Head: " & M64 & ")" & IF(ISBLANK(T64), "", " (Apt#: " & T64 & ")"))))) -> Fund Transfer: From YES MASTER 0264 to x2477 (Ref: YESME6189005399100) (Type: Master to Free) (BU: Casa Romana) (Head: Internal) | Y64: =K64 -> 29215.5 | Z64: =Y64=K64 -> TRUE
A65: 172 | B65: =IF(D65="","?",_xludf.IFS( MONTH(D65)<=3,"Q4", MONTH(D65)<=6,"Q1", MONTH(D65)<=9,"Q2", TRUE,"Q3" )) -> #NAME? | C65: =MONTH(D65) -> 7 | D65: 46211 | E65: 46211 | G65: YIB-TPT-DWARKADHIS PROJECTS PRIVATE LIMITED-tfr r-045563200000377 | H65: YESME6189005399200 | I65: 192500 | K65: =K66+J65-I65 -> 111715.5 | L65: Casa Romana | M65: Internal | O65: Entry | P65: Master 2 RERA | Q65: Internal transfer | W65: =TRIM(IF(M65="Internal", IF(ISBLANK(G65), IF(LEN(G65)-LEN(SUBSTITUTE(G65,"-",""))>=3, "Fund Transfer: From x" & RIGHT(MID(G65, FIND("|", SUBSTITUTE(G65, "-", "|", 3)) + 1, LEN(G65)), 4) & " to YES MASTER 0264 (Ref: " & H65 & ") (Type: " & P65 & ") (BU: " & L65 & ") (Head: " & M65 & ")", "Fund Transfer: To YES MASTER 0264 (Ref: " & H65 & ") (Type: " & P65 & ") (BU: " & L65 & ") (Head: " & M65 & ")"), IF(LEN(G65)-LEN(SUBSTITUTE(G65,"-",""))>=3, "Fund Transfer: From YES MASTER 0264 to x" & RIGHT(MID(G65, FIND("|", SUBSTITUTE(G65, "-", "|", 3)) + 1, LEN(G65)), 4) & " (Ref: " & H65 & ") (Type: " & P65 & ") (BU: " & L65 & ") (Head: " & M65 & ")", "Fund Transfer: From YES MASTER 0264 (Ref: " & H65 & ") (Type: " & P65 & ") (BU: " & L65 & ") (Head: " & M65 & ")")), IF(NOT(ISBLANK(J65)), IF(P65="Customer Collection", "Receipt: For " & IF(ISBLANK(T65), "", "(Apt#: " & T65 & ") ") & "(Ref: " & H65 & ") (" & IF(ISNUMBER(SEARCH("NEFT",G65)), "NEFT:", IF(ISNUMBER(SEARCH("RTGS",G65)), "RTGS:", IF(ISNUMBER(SEARCH("IMPS",G65)), "IMPS:", ""))) & " " & IF(ISNUMBER(SEARCH("SOHNA ROAD", G65)), "", IFERROR(MID(G65, FIND("-", G65, FIND("-", G65) + 1) + 1, LEN(G65)), SUBSTITUTE(SUBSTITUTE(SUBSTITUTE(G65, "IMPS/", ""), "NEFT/", ""), "RTGS/", ""))) & ") (Type: " & P65 & ") (BU: " & L65 & ")", IF(LEN(G65)-LEN(SUBSTITUTE(G65,"-",""))>=3, "Receipt: From x" & RIGHT(MID(G65, FIND("|", SUBSTITUTE(G65, "-", "|", 3)) + 1, LEN(G65)), 4) & " towards " & IF(ISBLANK(U65), L65, U65) & IF(OR(L65="Cancellation", L65="Collection"), " Apt No " & T65, "") & " (Ref: " & H65 & ") (Type: " & P65 & ") (BU: " & L65 & ") (Head: " & M65 & ")" & IF(ISBLANK(T65), "", " (Apt#: " & T65 & ")"), "Receipt: Against " & IF(ISBLANK(U65), L65, U65) & IF(OR(L65="Cancellation", L65="Collection"), " Apt No " & T65, "") & " (Ref: " & H65 & ") (Type: " & P65 & ") (BU: " & L65 & ") (Head: " & M65 & ")" & IF(ISBLANK(T65), "", " (Apt#: " & T65 & ")"))), IF(LEN(G65)-LEN(SUBSTITUTE(G65,"-",""))>=3, "Payment: To x" & RIGHT(MID(G65, FIND("|", SUBSTITUTE(G65, "-", "|", 3)) + 1, LEN(G65)), 4) & " for " & IF(ISBLANK(U65), L65, U65) & " (Ref: " & H65 & ") (Type: " & P65 & ") (BU: " & L65 & ") (Head: " & M65 & ")" & IF(ISBLANK(T65), "", " (Apt#: " & T65 & ")"), "Payment: Disbursement for " & IF(ISBLANK(U65), "", IF(ISBLANK(U65), "", U65) & " ") & "(Ref: " & H65 & ") (Type: " & P65 & ") (BU: " & L65 & ") (Head: " & M65 & ")" & IF(ISBLANK(T65), "", " (Apt#: " & T65 & ")"))))) -> Fund Transfer: From YES MASTER 0264 to x0377 (Ref: YESME6189005399200) (Type: Master 2 RERA) (BU: Casa Romana) (Head: Internal)
A66: 171 | B66: =IF(D66="","?",_xludf.IFS( MONTH(D66)<=3,"Q4", MONTH(D66)<=6,"Q1", MONTH(D66)<=9,"Q2", TRUE,"Q3" )) -> #NAME? | C66: =MONTH(D66) -> 7 | D66: 46210 | E66: 46210 | G66: UPI/169410392263/From:9811295007@ybl/To:045563200000264@YESB0000455.ifsc.npci/Payment from PhonePe | H66: YBS6188921330701 | J66: 55000 | K66: =K67+J66-I66 -> 304215.5 | L66: Casa Romana | M66: Collection | O66: Entry | P66: Customer Collection | Q66: Credit- no effect | T66: U-072 | U66: Mr. VIJAY SHARMA | V66: adjust | W66: =TRIM(IF(M66="Internal", IF(ISBLANK(G66), IF(LEN(G66)-LEN(SUBSTITUTE(G66,"-",""))>=3, "Fund Transfer: From x" & RIGHT(MID(G66, FIND("|", SUBSTITUTE(G66, "-", "|", 3)) + 1, LEN(G66)), 4) & " to YES MASTER 0264 (Ref: " & H66 & ") (Type: " & P66 & ") (BU: " & L66 & ") (Head: " & M66 & ")", "Fund Transfer: To YES MASTER 0264 (Ref: " & H66 & ") (Type: " & P66 & ") (BU: " & L66 & ") (Head: " & M66 & ")"), IF(LEN(G66)-LEN(SUBSTITUTE(G66,"-",""))>=3, "Fund Transfer: From YES MASTER 0264 to x" & RIGHT(MID(G66, FIND("|", SUBSTITUTE(G66, "-", "|", 3)) + 1, LEN(G66)), 4) & " (Ref: " & H66 & ") (Type: " & P66 & ") (BU: " & L66 & ") (Head: " & M66 & ")", "Fund Transfer: From YES MASTER 0264 (Ref: " & H66 & ") (Type: " & P66 & ") (BU: " & L66 & ") (Head: " & M66 & ")")), IF(NOT(ISBLANK(J66)), IF(P66="Customer Collection", "Receipt: For " & IF(ISBLANK(T66), "", "(Apt#: " & T66 & ") ") & "(Ref: " & H66 & ") (" & IF(ISNUMBER(SEARCH("NEFT",G66)), "NEFT:", IF(ISNUMBER(SEARCH("RTGS",G66)), "RTGS:", IF(ISNUMBER(SEARCH("IMPS",G66)), "IMPS:", ""))) & " " & IF(ISNUMBER(SEARCH("SOHNA ROAD", G66)), "", IFERROR(MID(G66, FIND("-", G66, FIND("-", G66) + 1) + 1, LEN(G66)), SUBSTITUTE(SUBSTITUTE(SUBSTITUTE(G66, "IMPS/", ""), "NEFT/", ""), "RTGS/", ""))) & ") (Type: " & P66 & ") (BU: " & L66 & ")", IF(LEN(G66)-LEN(SUBSTITUTE(G66,"-",""))>=3, "Receipt: From x" & RIGHT(MID(G66, FIND("|", SUBSTITUTE(G66, "-", "|", 3)) + 1, LEN(G66)), 4) & " towards " & IF(ISBLANK(U66), L66, U66) & IF(OR(L66="Cancellation", L66="Collection"), " Apt No " & T66, "") & " (Ref: " & H66 & ") (Type: " & P66 & ") (BU: " & L66 & ") (Head: " & M66 & ")" & IF(ISBLANK(T66), "", " (Apt#: " & T66 & ")"), "Receipt: Against " & IF(ISBLANK(U66), L66, U66) & IF(OR(L66="Cancellation", L66="Collection"), " Apt No " & T66, "") & " (Ref: " & H66 & ") (Type: " & P66 & ") (BU: " & L66 & ") (Head: " & M66 & ")" & IF(ISBLANK(T66), "", " (Apt#: " & T66 & ")"))), IF(LEN(G66)-LEN(SUBSTITUTE(G66,"-",""))>=3, "Payment: To x" & RIGHT(MID(G66, FIND("|", SUBSTITUTE(G66, "-", "|", 3)) + 1, LEN(G66)), 4) & " for " & IF(ISBLANK(U66), L66, U66) & " (Ref: " & H66 & ") (Type: " & P66 & ") (BU: " & L66 & ") (Head: " & M66 & ")" & IF(ISBLANK(T66), "", " (Apt#: " & T66 & ")"), "Payment: Disbursement for " & IF(ISBLANK(U66), "", IF(ISBLANK(U66), "", U66) & " ") & "(Ref: " & H66 & ") (Type: " & P66 & ") (BU: " & L66 & ") (Head: " & M66 & ")" & IF(ISBLANK(T66), "", " (Apt#: " & T66 & ")"))))) -> Receipt: For (Apt#: U-072) (Ref: YBS6188921330701) ( UPI/169410392263/From:9811295007@ybl/To:045563200000264@YESB0000455.ifsc.npci/Payment from PhonePe) (Type: Customer Collection) (BU: Casa Romana)
A67: 170 | B67: =IF(D67="","?",_xludf.IFS( MONTH(D67)<=3,"Q4", MONTH(D67)<=6,"Q1", MONTH(D67)<=9,"Q2", TRUE,"Q3" )) -> #NAME? | C67: =MONTH(D67) -> 7 | D67: 46210 | E67: 46210 | G67: UPI/310650751520/From:9799400249-2@axl/To:045563200000264@YESB0000455.ifsc.npci/Payment from PhonePe | H67: YBS6188920633298 | J67: 10000 | K67: =K68+J67-I67 -> 249215.5 | L67: Casa Romana | M67: Collection | O67: Entry | P67: Customer Collection | Q67: Credit- no effect | T67: N-041 | U67: Ms. SUMAN | V67: adjust | W67: =TRIM(IF(M67="Internal", IF(ISBLANK(G67), IF(LEN(G67)-LEN(SUBSTITUTE(G67,"-",""))>=3, "Fund Transfer: From x" & RIGHT(MID(G67, FIND("|", SUBSTITUTE(G67, "-", "|", 3)) + 1, LEN(G67)), 4) & " to YES MASTER 0264 (Ref: " & H67 & ") (Type: " & P67 & ") (BU: " & L67 & ") (Head: " & M67 & ")", "Fund Transfer: To YES MASTER 0264 (Ref: " & H67 & ") (Type: " & P67 & ") (BU: " & L67 & ") (Head: " & M67 & ")"), IF(LEN(G67)-LEN(SUBSTITUTE(G67,"-",""))>=3, "Fund Transfer: From YES MASTER 0264 to x" & RIGHT(MID(G67, FIND("|", SUBSTITUTE(G67, "-", "|", 3)) + 1, LEN(G67)), 4) & " (Ref: " & H67 & ") (Type: " & P67 & ") (BU: " & L67 & ") (Head: " & M67 & ")", "Fund Transfer: From YES MASTER 0264 (Ref: " & H67 & ") (Type: " & P67 & ") (BU: " & L67 & ") (Head: " & M67 & ")")), IF(NOT(ISBLANK(J67)), IF(P67="Customer Collection", "Receipt: For " & IF(ISBLANK(T67), "", "(Apt#: " & T67 & ") ") & "(Ref: " & H67 & ") (" & IF(ISNUMBER(SEARCH("NEFT",G67)), "NEFT:", IF(ISNUMBER(SEARCH("RTGS",G67)), "RTGS:", IF(ISNUMBER(SEARCH("IMPS",G67)), "IMPS:", ""))) & " " & IF(ISNUMBER(SEARCH("SOHNA ROAD", G67)), "", IFERROR(MID(G67, FIND("-", G67, FIND("-", G67) + 1) + 1, LEN(G67)), SUBSTITUTE(SUBSTITUTE(SUBSTITUTE(G67, "IMPS/", ""), "NEFT/", ""), "RTGS/", ""))) & ") (Type: " & P67 & ") (BU: " & L67 & ")", IF(LEN(G67)-LEN(SUBSTITUTE(G67,"-",""))>=3, "Receipt: From x" & RIGHT(MID(G67, FIND("|", SUBSTITUTE(G67, "-", "|", 3)) + 1, LEN(G67)), 4) & " towards " & IF(ISBLANK(U67), L67, U67) & IF(OR(L67="Cancellation", L67="Collection"), " Apt No " & T67, "") & " (Ref: " & H67 & ") (Type: " & P67 & ") (BU: " & L67 & ") (Head: " & M67 & ")" & IF(ISBLANK(T67), "", " (Apt#: " & T67 & ")"), "Receipt: Against " & IF(ISBLANK(U67), L67, U67) & IF(OR(L67="Cancellation", L67="Collection"), " Apt No " & T67, "") & " (Ref: " & H67 & ") (Type: " & P67 & ") (BU: " & L67 & ") (Head: " & M67 & ")" & IF(ISBLANK(T67), "", " (Apt#: " & T67 & ")"))), IF(LEN(G67)-LEN(SUBSTITUTE(G67,"-",""))>=3, "Payment: To x" & RIGHT(MID(G67, FIND("|", SUBSTITUTE(G67, "-", "|", 3)) + 1, LEN(G67)), 4) & " for " & IF(ISBLANK(U67), L67, U67) & " (Ref: " & H67 & ") (Type: " & P67 & ") (BU: " & L67 & ") (Head: " & M67 & ")" & IF(ISBLANK(T67), "", " (Apt#: " & T67 & ")"), "Payment: Disbursement for " & IF(ISBLANK(U67), "", IF(ISBLANK(U67), "", U67) & " ") & "(Ref: " & H67 & ") (Type: " & P67 & ") (BU: " & L67 & ") (Head: " & M67 & ")" & IF(ISBLANK(T67), "", " (Apt#: " & T67 & ")"))))) -> Receipt: For (Apt#: N-041) (Ref: YBS6188920633298) ( UPI/310650751520/From:9799400249-2@axl/To:045563200000264@YESB0000455.ifsc.npci/Payment from PhonePe) (Type: Customer Collection) (BU: Casa Romana)
A68: 169 | B68: =IF(D68="","?",_xludf.IFS( MONTH(D68)<=3,"Q4", MONTH(D68)<=6,"Q1", MONTH(D68)<=9,"Q2", TRUE,"Q3" )) -> #NAME? | C68: =MONTH(D68) -> 7 | D68: 46209 | E68: 46209 | G68: NEFT Cr-IDFB0021001-Mrs. ANSHU SHARMA-DWARKADHIS PROJECTS PRIVA-IDFB6187M8433490 | H68: YES0N6187270443400 | J68: 150000 | K68: =K69+J68-I68 -> 239215.5 | L68: Casa Romana | M68: Collection | O68: Entry | P68: Customer Collection | Q68: Credit- no effect | T68: S-064 | V68: adjust | W68: =TRIM(IF(M68="Internal", IF(ISBLANK(G68), IF(LEN(G68)-LEN(SUBSTITUTE(G68,"-",""))>=3, "Fund Transfer: From x" & RIGHT(MID(G68, FIND("|", SUBSTITUTE(G68, "-", "|", 3)) + 1, LEN(G68)), 4) & " to YES MASTER 0264 (Ref: " & H68 & ") (Type: " & P68 & ") (BU: " & L68 & ") (Head: " & M68 & ")", "Fund Transfer: To YES MASTER 0264 (Ref: " & H68 & ") (Type: " & P68 & ") (BU: " & L68 & ") (Head: " & M68 & ")"), IF(LEN(G68)-LEN(SUBSTITUTE(G68,"-",""))>=3, "Fund Transfer: From YES MASTER 0264 to x" & RIGHT(MID(G68, FIND("|", SUBSTITUTE(G68, "-", "|", 3)) + 1, LEN(G68)), 4) & " (Ref: " & H68 & ") (Type: " & P68 & ") (BU: " & L68 & ") (Head: " & M68 & ")", "Fund Transfer: From YES MASTER 0264 (Ref: " & H68 & ") (Type: " & P68 & ") (BU: " & L68 & ") (Head: " & M68 & ")")), IF(NOT(ISBLANK(J68)), IF(P68="Customer Collection", "Receipt: For " & IF(ISBLANK(T68), "", "(Apt#: " & T68 & ") ") & "(Ref: " & H68 & ") (" & IF(ISNUMBER(SEARCH("NEFT",G68)), "NEFT:", IF(ISNUMBER(SEARCH("RTGS",G68)), "RTGS:", IF(ISNUMBER(SEARCH("IMPS",G68)), "IMPS:", ""))) & " " & IF(ISNUMBER(SEARCH("SOHNA ROAD", G68)), "", IFERROR(MID(G68, FIND("-", G68, FIND("-", G68) + 1) + 1, LEN(G68)), SUBSTITUTE(SUBSTITUTE(SUBSTITUTE(G68, "IMPS/", ""), "NEFT/", ""), "RTGS/", ""))) & ") (Type: " & P68 & ") (BU: " & L68 & ")", IF(LEN(G68)-LEN(SUBSTITUTE(G68,"-",""))>=3, "Receipt: From x" & RIGHT(MID(G68, FIND("|", SUBSTITUTE(G68, "-", "|", 3)) + 1, LEN(G68)), 4) & " towards " & IF(ISBLANK(U68), L68, U68) & IF(OR(L68="Cancellation", L68="Collection"), " Apt No " & T68, "") & " (Ref: " & H68 & ") (Type: " & P68 & ") (BU: " & L68 & ") (Head: " & M68 & ")" & IF(ISBLANK(T68), "", " (Apt#: " & T68 & ")"), "Receipt: Against " & IF(ISBLANK(U68), L68, U68) & IF(OR(L68="Cancellation", L68="Collection"), " Apt No " & T68, "") & " (Ref: " & H68 & ") (Type: " & P68 & ") (BU: " & L68 & ") (Head: " & M68 & ")" & IF(ISBLANK(T68), "", " (Apt#: " & T68 & ")"))), IF(LEN(G68)-LEN(SUBSTITUTE(G68,"-",""))>=3, "Payment: To x" & RIGHT(MID(G68, FIND("|", SUBSTITUTE(G68, "-", "|", 3)) + 1, LEN(G68)), 4) & " for " & IF(ISBLANK(U68), L68, U68) & " (Ref: " & H68 & ") (Type: " & P68 & ") (BU: " & L68 & ") (Head: " & M68 & ")" & IF(ISBLANK(T68), "", " (Apt#: " & T68 & ")"), "Payment: Disbursement for " & IF(ISBLANK(U68), "", IF(ISBLANK(U68), "", U68) & " ") & "(Ref: " & H68 & ") (Type: " & P68 & ") (BU: " & L68 & ") (Head: " & M68 & ")" & IF(ISBLANK(T68), "", " (Apt#: " & T68 & ")"))))) -> Receipt: For (Apt#: S-064) (Ref: YES0N6187270443400) (NEFT: Mrs. ANSHU SHARMA-DWARKADHIS PROJECTS PRIVA-IDFB6187M8433490) (Type: Customer Collection) (BU: Casa Romana)
A69: 168 | B69: =IF(D69="","?",_xludf.IFS( MONTH(D69)<=3,"Q4", MONTH(D69)<=6,"Q1", MONTH(D69)<=9,"Q2", TRUE,"Q3" )) -> #NAME? | C69: =MONTH(D69) -> 7 | D69: 46209 | E69: 46209 | G69: NEFT Cr-ICIC0SF0002-ROHITAS KUMAR-DWARKADHIS PROJECTS PRIVA-IN12618745392512 | H69: YES0N6187256961500 | J69: 60000 | K69: =K70+J69-I69 -> 89215.5 | L69: Casa Romana | M69: Collection | O69: Entry | P69: Customer Collection | Q69: Credit- no effect | T69: L-113 | V69: on Account | W69: =TRIM(IF(M69="Internal", IF(ISBLANK(G69), IF(LEN(G69)-LEN(SUBSTITUTE(G69,"-",""))>=3, "Fund Transfer: From x" & RIGHT(MID(G69, FIND("|", SUBSTITUTE(G69, "-", "|", 3)) + 1, LEN(G69)), 4) & " to YES MASTER 0264 (Ref: " & H69 & ") (Type: " & P69 & ") (BU: " & L69 & ") (Head: " & M69 & ")", "Fund Transfer: To YES MASTER 0264 (Ref: " & H69 & ") (Type: " & P69 & ") (BU: " & L69 & ") (Head: " & M69 & ")"), IF(LEN(G69)-LEN(SUBSTITUTE(G69,"-",""))>=3, "Fund Transfer: From YES MASTER 0264 to x" & RIGHT(MID(G69, FIND("|", SUBSTITUTE(G69, "-", "|", 3)) + 1, LEN(G69)), 4) & " (Ref: " & H69 & ") (Type: " & P69 & ") (BU: " & L69 & ") (Head: " & M69 & ")", "Fund Transfer: From YES MASTER 0264 (Ref: " & H69 & ") (Type: " & P69 & ") (BU: " & L69 & ") (Head: " & M69 & ")")), IF(NOT(ISBLANK(J69)), IF(P69="Customer Collection", "Receipt: For " & IF(ISBLANK(T69), "", "(Apt#: " & T69 & ") ") & "(Ref: " & H69 & ") (" & IF(ISNUMBER(SEARCH("NEFT",G69)), "NEFT:", IF(ISNUMBER(SEARCH("RTGS",G69)), "RTGS:", IF(ISNUMBER(SEARCH("IMPS",G69)), "IMPS:", ""))) & " " & IF(ISNUMBER(SEARCH("SOHNA ROAD", G69)), "", IFERROR(MID(G69, FIND("-", G69, FIND("-", G69) + 1) + 1, LEN(G69)), SUBSTITUTE(SUBSTITUTE(SUBSTITUTE(G69, "IMPS/", ""), "NEFT/", ""), "RTGS/", ""))) & ") (Type: " & P69 & ") (BU: " & L69 & ")", IF(LEN(G69)-LEN(SUBSTITUTE(G69,"-",""))>=3, "Receipt: From x" & RIGHT(MID(G69, FIND("|", SUBSTITUTE(G69, "-", "|", 3)) + 1, LEN(G69)), 4) & " towards " & IF(ISBLANK(U69), L69, U69) & IF(OR(L69="Cancellation", L69="Collection"), " Apt No " & T69, "") & " (Ref: " & H69 & ") (Type: " & P69 & ") (BU: " & L69 & ") (Head: " & M69 & ")" & IF(ISBLANK(T69), "", " (Apt#: " & T69 & ")"), "Receipt: Against " & IF(ISBLANK(U69), L69, U69) & IF(OR(L69="Cancellation", L69="Collection"), " Apt No " & T69, "") & " (Ref: " & H69 & ") (Type: " & P69 & ") (BU: " & L69 & ") (Head: " & M69 & ")" & IF(ISBLANK(T69), "", " (Apt#: " & T69 & ")"))), IF(LEN(G69)-LEN(SUBSTITUTE(G69,"-",""))>=3, "Payment: To x" & RIGHT(MID(G69, FIND("|", SUBSTITUTE(G69, "-", "|", 3)) + 1, LEN(G69)), 4) & " for " & IF(ISBLANK(U69), L69, U69) & " (Ref: " & H69 & ") (Type: " & P69 & ") (BU: " & L69 & ") (Head: " & M69 & ")" & IF(ISBLANK(T69), "", " (Apt#: " & T69 & ")"), "Payment: Disbursement for " & IF(ISBLANK(U69), "", IF(ISBLANK(U69), "", U69) & " ") & "(Ref: " & H69 & ") (Type: " & P69 & ") (BU: " & L69 & ") (Head: " & M69 & ")" & IF(ISBLANK(T69), "", " (Apt#: " & T69 & ")"))))) -> Receipt: For (Apt#: L-113) (Ref: YES0N6187256961500) (NEFT: ROHITAS KUMAR-DWARKADHIS PROJECTS PRIVA-IN12618745392512) (Type: Customer Collection) (BU: Casa Romana) | X69: 0.05
